Workbook
Name __xlfn_IFERROR: #N/A
Name AnchorCell: #REF!
Name ProductID: #REF!

Sheet Home Ext
C5: Halooo… Sahabat Referral | E5: Karyawan Internal | I5: Dana Tunai | O5: Pembiayaan Mobil Bekas | U5: Kelengkapan Dokumen & Tracking Aplikasi | AC5: Pembiayaan Emas / Logam Mulia | AI5: Pembiayaan Mobil Baru
E7: Karyawan Authorized Dealer | I7: Type Debitur | O7: Type Debitur | AC7: Type Debitur | AI7: Type Debitur
E9: Karyawan Perbankan | I9: Perorangan (Wiraswasta) | O9: Perorangan (Wiraswasta) | U9: Kode Referral | AC9: Perorangan | AI9: Perorangan
E11: Karyawan Asuransi Rekanan | I11: Jika Debitur Perorangan, usia saat ini | O11: Jika Debitur Perorangan, usia saat ini | U11: 9anxfq | AC11: Jika Debitur Perorangan, usia saat ini | AI11: Jika Debitur Perorangan, usia saat ini
E13: Agent Retail | I13: 36-45 tahun | O13: 36-45 tahun | U13: Nama Debitur | AC13: 36-45 tahun | AI13: 36-45 tahun
E15: Showroom Mobil Bekas | I15: =IF($C$95="Pembiayaan Emas / Logam Mulia","","Type Kendaraan") -> Type Kendaraan | O15: =IF($C$95="Pembiayaan Emas / Logam Mulia","","Type Kendaraan") -> Type Kendaraan | U15: =VLOOKUP($U$11,'Data in out'!$B$24:$AL$323,2,0) -> AAAAAA | AC15: =IF($C$95="Pembiayaan Emas / Logam Mulia","","Type Kendaraan") -> Type Kendaraan | AI15: =IF($C$95="Pembiayaan Emas / Logam Mulia","","Type Kendaraan") -> Type Kendaraan
I17: Passenger | O17: Commercial | U17: Nama AO | AC17: Passenger | AI17: Passenger
I19: =IF(C95="Pembiayaan Emas / Logam Mulia","","Merk Kendaraan") -> Merk Kendaraan | O19: =IF(I95="Pembiayaan Emas / Logam Mulia","","Merk Kendaraan") -> Merk Kendaraan | U19: =VLOOKUP($U$11,'Data in out'!$B$24:$AL$323,3,0) -> Ade | AC19: =IF(W75="Pembiayaan Emas / Logam Mulia","","Merk Kendaraan") -> Merk Kendaraan | AI19: =IF(AC75="Pembiayaan Emas / Logam Mulia","","Merk Kendaraan") -> Merk Kendaraan
C21: Butuh Dana Tunai untuk? dan Kebutuhan? | E21: Pendidikan | I21: HONDA | O21: HONDA | U21: Type Debitur | AC21: HONDA | AI21: HONDA
E23: Modal Usaha | I23: Type Kendaraan | O23: Type Kendaraan | U23: =VLOOKUP($U$11,'Data in out'!$B$24:$AL$323,6,0) -> Perorangan (Non Wiraswasta) | AC23: Type Kendaraan | AI23: Type Kendaraan
E25: Renovasi Rumah | I25: BRIO | O25: BRIO | U25: =IF($U$23="Badan Hukum Usaha"," ","Konfirmasi Sumber Penghasilan lainnya") -> Konfirmasi Sumber Penghasilan lainnya | AC25: BRIO | AI25: BRIO
C27: Debitur/ Nasabah, dengan jaminan BPKB Mobil | E27: Liburan / Wisata Religi | I27: Model Kendaraan | O27: Model Kendaraan | U27: =VLOOKUP($U$11,'Data in out'!$B$24:$AL$323,7,0) -> Pasangan Bekerja dan memiliki penghasilan | AC27: Model Kendaraan | AI27: Model Kendaraan
E29: Pernikahan / Persalinan | I29: ALL NEW BRIO RS CVT | O29: ALL NEW BRIO RS CVT | AC29: ALL NEW BRIO RS CVT | AI29: ALL NEW BRIO RS CVT
I31: Tahun Kendaraan | K31: Type Angsuran | O31: Tahun Kendaraan | Q31: Type Angsuran | AC31: Tahun Kendaraan | AI31: Tahun Kendaraan
C33: Cara Mudah Mendapatkan Simulasi Pembiayaan & | D33: Cara Mudah Mengajukan Pinjaman | E33: Cara Mudah Mengajukan Pinjaman | I33: 2020 | K33: ADDB | O33: 2015 | Q33: ADDB | AC33: 2017 | AI33: 2017
C35: Tracking Proses Permohonan Pembiayaan Realtime | I35: Asuransi | O35: Asuransi | U35: Kelengkapan Dokumen Permohonan Pembiayaan
I37: Comprehensive 1 tahun | O37: TLO All Tenor | U37: 1 | W37: =IF($U$23="Badan Hukum Usaha","KTP Komisaris","KTP Pemohon") -> KTP Pemohon | Y37: =Z37 -> 2 | Z37: =VLOOKUP($U$15,'Data in out'!$C$24:$BQ$323,7,0) -> 2
D39: 1 | E39: Registrasi | U39: 2 | W39: =IF($U$23="Badan Hukum Usaha","KTP Direksi","KTP Pasangan") -> KTP Pasangan | Y39: =Z39 -> 2 | Z39: =VLOOKUP($U$15,'Data in out'!$C$24:$BQ$323,8,0) -> 2
I41: Simulasi Dana Tunai | O41: Simulasi Pembiayaan Mobil Bekas | U41: 3 | W41: =IF($U$23="Badan Hukum Usaha","NPWP Direksi","NPWP Pemohon") -> NPWP Pemohon | Y41: =Z41 -> 2 | Z41: =VLOOKUP($U$15,'Data in out'!$C$24:$BQ$323,9,0) -> 2
I43: STNK atas nama | U43: 4 | W43: =IF($U$23="Badan Hukum Usaha","NPWP Usaha","Kartu Keluarga") -> Kartu Keluarga | Y43: =Z43 -> 2 | Z43: =VLOOKUP($U$15,'Data in out'!$C$24:$BQ$323,10,0) -> 2 | AC43: STNK atas nama | AI43: STNK atas nama
I45: Pribadi (milik sendiri) | U45: 5 | W45: =IF($U$23="Badan Hukum Usaha","Akte Pendirian","Bukti Kepemilikan Rumah (SPPT PBB/AJB/SHM") -> Bukti Kepemilikan Rumah (SPPT PBB/AJB/SHM | Y45: =Z45 -> 2 | Z45: =VLOOKUP($U$15,'Data in out'!$C$24:$BQ$323,11,0) -> 2 | AC45: Pribadi (milik sendiri) | AI45: Pribadi (milik sendiri)
D47: 2 | E47: Isi Form Online | I47: Harga Taksasi | O47: Harga Pasar | U47: 6 | W47: =IF($U$23="Badan Hukum Usaha","Akte Perubahan","Rek Koran 3 bulan terakhir") -> Rek Koran 3 bulan terakhir | Y47: 1 | Z47: =VLOOKUP($U$15,'Data in out'!$C$24:$BQ$323,12,0) -> 2 | AC47: Harga OTR | AI47: Harga OTR
I49: =ROUNDDOWN(VLOOKUP('DT Ext'!$B$10,'PHPM 1 DT Ext'!$K$5:$L$841,2,0),-2) -> 140000000 | O49: 110000000 | U49: 7 | W49: =IF($U$23="Perorangan (Wiraswasta)","Legalitas Usaha (NIB/SKDU)",IF($U$23="Perorangan (Non Wiraswasta)","Slip Gaji Carbonized","SK Kemenkumham")) -> Slip Gaji Carbonized | Y49: 1 | Z49: =VLOOKUP($U$15,'Data in out'!$C$24:$BQ$323,13,0) -> 2 | AC49: ='DT Ext'!$F$13 -> 140000000 | AI49: ='DT Ext'!$F$13 -> 140000000
I51: Pencairan Maksimal | K51: Angsuran perbulan | O51: Pencairan All In | Q51: Angsuran perbulan | U51: =IF(W51=" "," ",8) | W51: =IF($U$23="Perorangan (Wiraswasta)","Bon / Faktur Penjualan",IF($U$23="Perorangan (Non Wiraswasta)"," ","Legalitas Usaha (NIB & Ijin Usaha khusus)")) | Y51: =Z51 -> 0 | Z51: =IF(W51=" ",0,VLOOKUP($U$15,'Data in out'!$C$24:$BQ$323,14,0)) -> 0 | AC51: Pencairan Maksimal | AE51: Angsuran perbulan | AI51: Pencairan Maksimal | AK51: Angsuran perbulan
I53: ='DT Ext'!$E$73 -> 122059100 | J53: =_xlfn.UNICHAR(9312) -> ① | K53: ='DT Ext'!$G$73 -> 11926000 | O53: ='UC Ext'!$E$78 -> 0 | P53: =_xlfn.UNICHAR(9312) -> ① | Q53: ='UC Ext'!$G$78 -> 0 | U53: =IF(W53=" "," ",9) | W53: =IF($U$23="Perorangan (Wiraswasta)","Surat Ijin Profesi (khusus untuk tenaga profesional)",IF($U$23="Perorangan (Non Wiraswasta)"," ","Laporan Keuangan")) | Y53: =Z53 -> 0 | Z53: =IF(W53=" ",0,VLOOKUP($U$15,'Data in out'!$C$24:$BQ$323,15,0)) -> 0 | AC53: ='DT Ext'!$E$73 -> 122059100 | AD53: =_xlfn.UNICHAR(9312) -> ① | AE53: ='DT Ext'!$G$73 -> 11926000 | AI53: ='DT Ext'!$E$73 -> 122059100 | AJ53: =_xlfn.UNICHAR(9312) -> ① | AK53: ='DT Ext'!$G$73 -> 11926000
D55: 3 | E55: Ajukan sesuai kebutuhan Debitur anda | I55: ='DT Ext'!$E$74 -> 120594700 | J55: =_xlfn.UNICHAR(9313) -> ② | K55: ='DT Ext'!$G$74 -> 6352000 | O55: ='UC Ext'!$E$79 -> 0 | P55: =_xlfn.UNICHAR(9313) -> ② | Q55: ='UC Ext'!$G$79 -> 0 | U55: =IF(W55=" "," ",10) | W55: =IF($U$23="Perorangan (Wiraswasta)"," ",IF($U$23="Perorangan (Non Wiraswasta)"," ","Rek Koran 3 Bulan terakhir")) | Y55: =Z55 -> 0 | Z55: =IF(W55=" ",0,VLOOKUP($U$15,'Data in out'!$C$24:$BQ$323,16,0)) -> 0 | AC55: ='DT Ext'!$E$74 -> 120594700 | AD55: =_xlfn.UNICHAR(9313) -> ② | AE55: ='DT Ext'!$G$74 -> 6352000 | AI55: ='DT Ext'!$E$74 -> 120594700 | AJ55: =_xlfn.UNICHAR(9313) -> ② | AK55: ='DT Ext'!$G$74 -> 6352000
I57: ='DT Ext'!$E$75 -> 118902100 | J57: =_xlfn.UNICHAR(9314) -> ③ | K57: ='DT Ext'!$G$75 -> 4514000 | O57: ='UC Ext'!$E$80 -> 0 | P57: =_xlfn.UNICHAR(9314) -> ③ | Q57: ='UC Ext'!$G$80 -> 0 | U57: =IF(W57=" "," ",11) | W57: =IF($U$23="Perorangan (Wiraswasta)"," ",IF($U$23="Perorangan (Non Wiraswasta)"," ","SPK /MOU")) | Y57: =Z57 -> 0 | Z57: =IF(W57=" ",0,VLOOKUP($U$15,'Data in out'!$C$24:$BQ$323,17,0)) -> 0 | AC57: ='DT Ext'!$E$75 -> 118902100 | AD57: =_xlfn.UNICHAR(9314) -> ③ | AE57: ='DT Ext'!$G$75 -> 4514000 | AI57: ='DT Ext'!$E$75 -> 118902100 | AJ57: =_xlfn.UNICHAR(9314) -> ③ | AK57: ='DT Ext'!$G$75 -> 4514000
I59: ='DT Ext'!$E$76 -> 116972900 | J59: =_xlfn.UNICHAR(9315) -> ④ | K59: ='DT Ext'!$G$76 -> 3700000 | O59: ='UC Ext'!$E$81 -> 0 | P59: =_xlfn.UNICHAR(9315) -> ④ | Q59: ='UC Ext'!$G$81 -> 0 | AC59: ='DT Ext'!$E$76 -> 116972900 | AD59: =_xlfn.UNICHAR(9315) -> ④ | AE59: ='DT Ext'!$G$76 -> 3700000 | AI59: ='DT Ext'!$E$76 -> 116972900 | AJ59: =_xlfn.UNICHAR(9315) -> ④ | AK59: ='DT Ext'!$G$76 -> 3700000
C61: Bosan dengan mobil anda, atau mau ganti yang lebih muda? | I61: ='DT Ext'!$E$77 -> 115171100 | J61: =_xlfn.UNICHAR(9316) -> ⑤ | K61: ='DT Ext'!$G$77 -> 3227000 | O61: ='UC Ext'!$E$82 -> 0 | P61: =_xlfn.UNICHAR(9316) -> ⑤ | Q61: ='UC Ext'!$G$82 -> 0 | AC61: ='DT Ext'!$E$77 -> 115171100 | AD61: =_xlfn.UNICHAR(9316) -> ⑤ | AE61: ='DT Ext'!$G$77 -> 3227000 | AI61: ='DT Ext'!$E$77 -> 115171100 | AJ61: =_xlfn.UNICHAR(9316) -> ⑤ | AK61: ='DT Ext'!$G$77 -> 3227000
C63: Atau ganti dengan Mobil Baru? | I63: Nominal pembiayaan bersifat Estimasi | O63: Nominal pembiayaan bersifat Estimasi | U63: =IF($U$23="Badan Hukum Usaha"," ",IF($U$27="Tidak Ada"," ",$U$27)) -> Pasangan Bekerja dan memiliki penghasilan | AC63: Nominal pembiayaan bersifat Estimasi | AI63: Nominal pembiayaan bersifat Estimasi
C65: Atau mau lengkapi koleksi Logam Mulia anda, dengan cara mudah | I65: Besarnya pembiayaan berdasarkan hasil | O65: Besarnya pembiayaan berdasarkan hasil | U65: =IF($U$23="Badan Hukum Usaha"," ",IF($U$27="Tidak Ada"," ",1)) -> 1 | W65: =IF($U$23="Badan Hukum Usaha"," ",IF($U$27="Tidak Ada"," ","Rek Koran 3 bulan terakhir")) -> Rek Koran 3 bulan terakhir | Y65: =Z65 -> 2 | Z65: =IF(W65=" ",0,VLOOKUP($U$15,'Data in out'!$C$24:$BQ$323,18,0)) -> 2 | AC65: Besarnya pembiayaan berdasarkan hasil | AI65: Besarnya pembiayaan berdasarkan hasil
C67: Kami hadir Mewujudkan mimpi anda, sekarang | I67: Verifikasi Profil Debitur dan kondisi Kendaraan | O67: Verifikasi Profil Debitur dan kondisi Kendaraan | U67: =IF($U$23="Badan Hukum Usaha"," ",IF($U$27="Tidak Ada"," ",2)) -> 2 | W67: =IF($U$23="Badan Hukum Usaha"," ",IF($U$27="Pasangan Bekerja dan memiliki penghasilan","Slip Gaji Carbonized",IF($U$27="Pasangan memiliki usaha lainnya dan memiliki penghasilan","Legalitas Usaha (NIB/SKDU)",IF($U$27="Pasangan adalah profesional dan memiliki penghasilan","Surat Ijin Profesi"," ")))) -> Slip Gaji Carbonized | Y67: =Z67 -> 2 | Z67: =IF(W67=" ",0,VLOOKUP($U$15,'Data in out'!$C$24:$BQ$323,19,0)) -> 2 | AC67: Verifikasi Profil Debitur dan kondisi Kendaraan | AI67: Verifikasi Profil Debitur dan kondisi Kendaraan
C69: menawarkan Solusi Cepat dan Mudah | I69: AJUKAN | O69: AJUKAN | U69: =IF(OR($U$23="Perorangan (Wiraswasta)",$W$69="Bon / Faktur Penjualan"),3," ") | W69: =IF($U$23="Badan Hukum Usaha"," ",IF($U$27="Pasangan Bekerja dan memiliki penghasilan"," ",IF($U$27="Pasangan memiliki usaha lainnya dan memiliki penghasilan","Bon / Faktur Penjualan",IF($U$27="Pasangan adalah profesional dan memiliki penghasilan"," "," ")))) | Y69: =Z69 -> 0 | Z69: =IF(W69=" ",0,VLOOKUP($U$15,'Data in out'!$C$24:$BQ$323,20,0)) -> 0 | AC69: AJUKAN | AI69: AJUKAN
C73: NAMA LENGKAP | I73: Dana yang dibutuhkan | O73: Total DP Dikehendaki | AC73: Dana yang dibutuhkan | AI73: Dana yang dibutuhkan
I75: 60000000 | O75: 60000000 | U75: Tracking Aplikasi | AC75: 60000000 | AI75: 60000000
C77: TGL LAHIR | I77: Hitung | O77: Hitung | U77: 1 | W77: Verifikasi, Validasi dan kelengkapan data permohonan | Y77: =Z77 -> 2 | Z77: =IF(W77=" ",0,VLOOKUP($U$15,'Data in out'!$C$24:$BQ$323,21+U77,0)) -> 2 | AC77: Hitung | AI77: Hitung
C79: DD/MM/YYYY | J79: =_xlfn.UNICHAR(9312) -> ① | K79: ='DT Ext'!$G$69 -> 6361000 | P79: =_xlfn.UNICHAR(9312) -> ① | Q79: ='UC Ext'!$O$78 -> 0 | U79: 2 | W79: Survey Domisili & Tempat usaha/Kantor | Y79: =Z79 -> 2 | Z79: =IF(W79=" ",0,VLOOKUP($U$15,'Data in out'!$C$24:$BQ$323,21+U79,0)) -> 2 | AD79: =_xlfn.UNICHAR(9312) -> ① | AE79: ='DT Ext'!$G$69 -> 6361000 | AJ79: =_xlfn.UNICHAR(9312) -> ① | AK79: ='DT Ext'!$G$69 -> 6361000
C81: ALAMAT EMAIL | J81: =_xlfn.UNICHAR(9313) -> ② | K81: ='DT Ext'!$O$74 -> 3458000 | P81: =_xlfn.UNICHAR(9313) -> ② | Q81: ='UC Ext'!$O$79 -> 0 | U81: 3 | W81: Cek fisik Kendaraan | Y81: =Z81 -> 2 | Z81: =IF(W81=" ",0,VLOOKUP($U$15,'Data in out'!$C$24:$BQ$323,21+U81,0)) -> 2 | AD81: =_xlfn.UNICHAR(9313) -> ② | AE81: ='DT Ext'!$O$74 -> 3458000 | AJ81: =_xlfn.UNICHAR(9313) -> ② | AK81: ='DT Ext'!$O$74 -> 3458000
J83: =_xlfn.UNICHAR(9314) -> ③ | K83: ='DT Ext'!$O$75 -> 2515000 | P83: =_xlfn.UNICHAR(9314) -> ③ | Q83: ='UC Ext'!$O$80 -> 0 | U83: 4 | W83: Laporan Hasil Survey. | Y83: =Z83 -> 2 | Z83: =IF(W83=" ",0,VLOOKUP($U$15,'Data in out'!$C$24:$BQ$323,21+U83,0)) -> 2 | AD83: =_xlfn.UNICHAR(9314) -> ③ | AE83: ='DT Ext'!$O$75 -> 2515000 | AJ83: =_xlfn.UNICHAR(9314) -> ③ | AK83: ='DT Ext'!$O$75 -> 2515000
C85: No. HAND PHONE | J85: =_xlfn.UNICHAR(9315) -> ④ | K85: ='DT Ext'!$O$76 -> 2115000 | P85: =_xlfn.UNICHAR(9315) -> ④ | Q85: ='UC Ext'!$O$81 -> 0 | U85: 5 | W85: Proses Aplikasi | Y85: =Z85 -> 2 | Z85: =IF(W85=" ",0,VLOOKUP($U$15,'Data in out'!$C$24:$BQ$323,21+U85,0)) -> 2 | AD85: =_xlfn.UNICHAR(9315) -> ④ | AE85: ='DT Ext'!$O$76 -> 2115000 | AJ85: =_xlfn.UNICHAR(9315) -> ④ | AK85: ='DT Ext'!$O$76 -> 2115000
J87: =_xlfn.UNICHAR(9316) -> ⑤ | K87: ='DT Ext'!$O$77 -> 1889000 | P87: =_xlfn.UNICHAR(9316) -> ⑤ | Q87: ='UC Ext'!$O$82 -> 0 | U87: 6 | W87: Konfirmasi Debitur by phone & Scoring Credit | Y87: =Z87 -> 2 | Z87: =IF(W87=" ",0,VLOOKUP($U$15,'Data in out'!$C$24:$BQ$323,21+U87,0)) -> 2 | AD87: =_xlfn.UNICHAR(9316) -> ⑤ | AE87: ='DT Ext'!$O$77 -> 1889000 | AJ87: =_xlfn.UNICHAR(9316) -> ⑤ | AK87: ='DT Ext'!$O$77 -> 1889000
C89: REFERRAL | I89: Nominal pembiayaan bersifat Estimasi | O89: Nominal pembiayaan bersifat Estimasi | U89: 7 | W89: Permohonan Persetujuan Pembiayaan | Y89: =Z89 -> 2 | Z89: =IF(W89=" ",0,VLOOKUP($U$15,'Data in out'!$C$24:$BQ$323,21+U89,0)) -> 2 | AC89: Nominal pembiayaan bersifat Estimasi | AI89: Nominal pembiayaan bersifat Estimasi
C91: Captive External | I91: Besarnya pembiayaan berdasarkan hasil | O91: Besarnya pembiayaan berdasarkan hasil | U91: 8 | W91: Persetujuan Pembiayaan (PO) | Y91: 2 | Z91: =IF(W91=" ",0,VLOOKUP($U$15,'Data in out'!$C$24:$BQ$323,21+U91,0)) -> 1 | AC91: Besarnya pembiayaan berdasarkan hasil | AI91: Besarnya pembiayaan berdasarkan hasil
C93: SME & Private/Prioritas | I93: Verifikasi Profil Debitur dan kondisi Kendaraan | O93: Verifikasi Profil Debitur dan kondisi Kendaraan | U93: 9 | W93: Verifikasi, Validasi dan kelengkapan Jaminan (BPKB) | Y93: 2 | Z93: =IF(W93=" ",0,VLOOKUP($U$15,'Data in out'!$C$24:$BQ$323,21+U93,0)) -> 1 | AC93: Verifikasi Profil Debitur dan kondisi Kendaraan | AI93: Verifikasi Profil Debitur dan kondisi Kendaraan
I95: AJUKAN | O95: AJUKAN | U95: 10 | W95: Kofirmasi Debitur by phone | Y95: 2 | Z95: =IF(W95=" ",0,VLOOKUP($U$15,'Data in out'!$C$24:$BQ$323,21+U95,0)) -> 1 | AC95: AJUKAN | AI95: AJUKAN
C97: Nama Cabang ; Contoh Tunas Toyota Pecenongan | U97: 11 | W97: Golive & Payment | Y97: 2 | Z97: =IF(W97=" ",0,VLOOKUP($U$15,'Data in out'!$C$24:$BQ$323,21+U97,0)) -> 1
C101: NAMA USER
C105: KATA SANDI
C109: KONFIRMASI KATA SANDI
C115: Daftar | E115: Batal
C131: NAMA USER
C135: KATA SANDI
C141: Masuk | E141: Batal
C143: Simulasi / Tracking
C145: Simulasi Kredit
C147: Jenis Pembiayaan
C149: Dana Tunai
C151: Domisili Debitur
C153: Jakarta Barat

Sheet DT Ext
B4: Merk | D4: ='Home Ext'!$I$21 -> HONDA | G4: Type Kendaraan | I4: ='Home Ext'!$I$25 -> BRIO | N4: Deposit Angsuran | P4: 0 | Q4: Up ACP | S4: 0.3
B5: Type Debitur | D5: ='Home Ext'!$I$9 -> Perorangan (Wiraswasta) | G5: Model Kendaraan | I5: ='Home Ext'!$I$29 -> ALL NEW BRIO RS CVT | N5: BBNKB | O5: 0 | Q5: Up Rate | S5: 0
B6: Type Angsuran | D6: ADDB | G6: Penggunaan Unit | I6: ='Home Ext'!$I$17 -> Passenger | N6: PKB | O6: 0 | Q6: Up Adm | S6: 0
B7: Type Unit | D7: =VLOOKUP('Home Ext'!$I$21,'PHPM 2 DT Ext'!$D$4:$E$55,2,0) -> Japan | G7: Product | I7: =CONCATENATE(VLOOKUP('Home Ext'!$C$91,'Data Ext'!$C$5:$F$11,2,0)," ",'Home Ext'!$I$17," ",VLOOKUP('Home Ext'!$C$91,'Data Ext'!$C$5:$F$11,4,0)) -> Captive Passenger Khusus SME & Private/Prioritas | N7: FAKTUR | O7: 0 | Q7: Up Provisi | S7: 0
B8: Thn (NIK) | D8: ='Home Ext'!$I$33 -> 2020 | F8: =15-(2026-D8) -> 9 | G8: Asuransi | I8: Comprehensive 1 tahun, sisanya TLO | N8: Asuransi | O8: BATAS BAWAH | Q8: Usia Debitur | S8: ='Home Ext'!$I$13 -> 36-45 tahun
B9: TENOR | F9: 1 | G9: =F9*12 -> 12 | I9: 2 | J9: =I9*12 -> 24 | L9: 3 | M9: =L9*12 -> 36 | O9: 4 | P9: =O9*12 -> 48 | R9: 5 | S9: =R9*12 -> 60
B10: =CONCATENATE('Home Ext'!$I$21,"-",'Home Ext'!$I$25,"-",'Home Ext'!$I$29) -> HONDA-BRIO-ALL NEW BRIO RS CVT | F10: =(16-F9)-(2026-$D$8) -> 9 | I10: =(16-I9)-(2026-$D$8) -> 8 | L10: =(16-L9)-(2026-$D$8) -> 7 | O10: =(16-O9)-(2026-$D$8) -> 6 | R10: =(16-R9)-(2026-$D$8) -> 5
B11: Harga OTR | D11: PASAR | F11: =F13 -> 140000000 | I11: =I13 -> 140000000 | L11: =L13 -> 140000000 | O11: =O13 -> 140000000 | R11: =R13 -> 140000000
D12: PHPM | F12: =IF(F10>=1,VLOOKUP($B$10,'PHPM 1 DT Ext'!$K$5:$L$841,2,0),0) -> 140000016 | I12: =IF(I10>=1,VLOOKUP($B$10,'PHPM 1 DT Ext'!$K$5:$L$841,2,0),0) -> 140000016 | L12: =IF(L10>=1,VLOOKUP($B$10,'PHPM 1 DT Ext'!$K$5:$L$841,2,0),0) -> 140000016 | O12: =IF(O10>=1,VLOOKUP($B$10,'PHPM 1 DT Ext'!$K$5:$L$841,2,0),0) -> 140000016 | R12: =IF(R10>=1,VLOOKUP($B$10,'PHPM 1 DT Ext'!$K$5:$L$841,2,0),0) -> 140000016
D13: ROUNDDOWN PHPM | F13: =ROUNDDOWN(F12,-2) -> 140000000 | I13: =ROUNDDOWN(I12,-2) -> 140000000 | L13: =ROUNDDOWN(L12,-2) -> 140000000 | O13: =ROUNDDOWN(O12,-2) -> 140000000 | R13: =ROUNDDOWN(R12,-2) -> 140000000
B14: Deviasi (%) | D14: (Rp.) | F14: =IFERROR(G14/F11,0) -> 0 | G14: =IF(F11<=F12,0,F11-F12) -> 0 | I14: =IFERROR(J14/I11,0) -> 0 | J14: =IF(I11<=I12,0,I11-I12) -> 0 | L14: =IFERROR(M14/L11,0) -> 0 | M14: =IF(L11<=L12,0,L11-L12) -> 0 | O14: =IFERROR(P14/O11,0) -> 0 | P14: =IF(O11<=O12,0,O11-O12) -> 0 | R14: =IFERROR(S14/R11,0) -> 0 | S14: =IF(R11<=R12,0,R11-R12) -> 0
B15: Sum Insured | D15: % | E15: Rp. | F15: 1 | G15: =F11*F15 -> 140000000 | I15: 0.9 | J15: =I11*I15 -> 126000000 | L15: 0.8 | M15: =L11*L15 -> 112000000 | O15: 0.7 | P15: =O11*O15 -> 98000000 | R15: 0.7 | S15: =R11*R15 -> 98000000
B16: Net DP | D16: % | E16: Rp. | F16: =IF('Home Ext'!$I$45="Orang lain",15%,IF(OR($I$6="Commercial",$D$7="Non Japan"),15%,5%)) -> 0.05 | G16: =F11*F16 -> 7000000 | I16: =IF('Home Ext'!$I$45="Orang lain",15%,IF(OR($I$6="Commercial",$D$7="Non Japan"),15%,5%)) -> 0.05 | J16: =I11*I16 -> 7000000 | L16: =IF('Home Ext'!$I$45="Orang lain",15%,IF(OR($I$6="Commercial",$D$7="Non Japan"),15%,5%)) -> 0.05 | M16: =L11*L16 -> 7000000 | O16: =IF('Home Ext'!$I$45="Orang lain",15%,IF(OR($I$6="Commercial",$D$7="Non Japan"),15%,5%)) -> 0.05 | P16: =O11*O16 -> 7000000 | R16: =IF('Home Ext'!$I$45="Orang lain",15%,IF(OR($I$6="Commercial",$D$7="Non Japan"),15%,5%)) -> 0.05 | S16: =R11*R16 -> 7000000
B17: LTV | D17: % | E17: Rp. | F17: =100%-F16 -> 0.95 | G17: =F11-G16 -> 133000000 | I17: =100%-I16 -> 0.95 | J17: =I11-J16 -> 133000000 | L17: =100%-L16 -> 0.95 | M17: =L11-M16 -> 133000000 | O17: =100%-O16 -> 0.95 | P17: =O11-P16 -> 133000000 | R17: =100%-R16 -> 0.95 | S17: =R11-S16 -> 133000000
B18: RATE p.a (%) | D18: Eff R | E18: Flat Rate | F18: =VLOOKUP($I$7,Product!$B$6:$K$25,1+F9,0) -> 0.1374 | G18: =IF($D$6="ADDM",(((PMT(F18/12,G9,1,0,1)*(-1))*G9)-1)*12/G9,IF($D$6="ADDB",(((PMT(F18/12,G9,1,0,0)*(-1))*G9)-1)*12/G9," ")) -> 0.075977942 | H18: =G18+$S$5 -> 0.075977942 | I18: =VLOOKUP($I$7,Product!$B$6:$K$25,1+I9,0) -> 0.1345 | J18: =IF($D$6="ADDM",(((PMT(I18/12,J9,1,0,1)*(-1))*J9)-1)*12/J9,IF($D$6="ADDB",(((PMT(I18/12,J9,1,0,0)*(-1))*J9)-1)*12/J9," ")) -> 0.073041578 | K18: =J18+$S$5 -> 0.073041578 | L18: =VLOOKUP($I$7,Product!$B$6:$K$25,1+L9,0) -> 0.135 | M18: =IF($D$6="ADDM",(((PMT(L18/12,M9,1,0,1)*(-1))*M9)-1)*12/M9,IF($D$6="ADDB",(((PMT(L18/12,M9,1,0,0)*(-1))*M9)-1)*12/M9," ")) -> 0.073890115 | N18: =M18+$S$5 -> 0.073890115 | O18: =VLOOKUP($I$7,Product!$B$6:$K$25,1+O9,0) -> 0.1497 | P18: =IF($D$6="ADDM",(((PMT(O18/12,P9,1,0,1)*(-1))*P9)-1)*12/P9,IF($D$6="ADDB",(((PMT(O18/12,P9,1,0,0)*(-1))*P9)-1)*12/P9," ")) -> 0.083786521 | Q18: =P18+$S$5 -> 0.083786521 | R18: =VLOOKUP($I$7,Product!$B$6:$K$25,1+R9,0) -> 0.1589 | S18: =IF($D$6="ADDM",(((PMT(R18/12,S9,1,0,1)*(-1))*S9)-1)*12/S9,IF($D$6="ADDB",(((PMT(R18/12,S9,1,0,0)*(-1))*S9)-1)*12/S9," ")) -> 0.091115791 | T18: =S18+$S$5 -> 0.091115791
B19: Bunga Jual | D19: % | E19: Rp. | F19: =(H18*F9) -> 0.075977942 | G19: =G17*F19 -> 10105066 | I19: =(K18*I9) -> 0.14608316 | J19: =J17*I19 -> 19429060 | L19: =(N18*L9) -> 0.22167034 | M19: =M17*L19 -> 29482156 | O19: =(Q18*O9) -> 0.33514608 | P19: =P17*O19 -> 44574429 | R19: =(T18*R9) -> 0.45557895 | S19: =S17*R19 -> 60592001
B20: TOTAL A/R | G20: =G17+G19 -> 1.4310507e+08 | J20: =J17+J19 -> 1.5242906e+08 | M20: =M17+M19 -> 1.6248216e+08 | P20: =P17+P19 -> 1.7757443e+08 | S20: =S17+S19 -> 1.93592e+08
B21: ANGSURAN | F21: =ROUNDUP(G20/G9,-3) -> 11926000 | I21: =ROUNDUP(J20/J9,-3) -> 6352000 | L21: =ROUNDUP(M20/M9,-3) -> 4514000 | O21: =ROUNDUP(P20/P9,-3) -> 3700000 | R21: =ROUNDUP(S20/S9,-3) -> 3227000
B22: TOTAL BAYAR PERTAMA
B23: ASURANSI | F23: =IF(OR($I$8="Comprehensive 1 tahun, sisanya TLO",I8="Comprehensive All Tenor"),"Comprehensive","TLO") -> Comprehensive | I23: =IF($I$8="Comprehensive All Tenor","Comprehensive","TLO") -> TLO | L23: =IF($I$8="Comprehensive All Tenor","Comprehensive","TLO") -> TLO | O23: =IF($I$8="Comprehensive All Tenor","Comprehensive","TLO") -> TLO | R23: =IF($I$8="Comprehensive All Tenor","Comprehensive","TLO") -> TLO
C24: Casco | F24: =IF(F23="Comprehensive",IF(AND(G15>=1,G15<=125000000),'Asr Ext'!$C$22,IF(AND(G15>125000000,G15<=200000000),'Asr Ext'!$C$23,IF(AND(G15>200000000,G15<=400000000),'Asr Ext'!$C$24,IF(AND(G15>400000000,G15<=800000000),'Asr Ext'!$C$25,'Asr Ext'!$C$26)))),IF(AND(G15>=1,G15<=125000000),'Asr Ext'!$D$22,IF(AND(G15>125000000,G15<=200000000),'Asr Ext'!$D$23,IF(AND(G15>200000000,G15<=400000000),'Asr Ext'!$D$24,IF(AND(G15>400000000,G15<=800000000),'Asr Ext'!$D$25,'Asr Ext'!$D$26))))) -> 0.0247 | G24: =F24*G15 -> 3458000 | I24: =IF(I23="Comprehensive",IF(AND(J15>=1,J15<=125000000),'Asr Ext'!$C$22,IF(AND(J15>125000000,J15<=200000000),'Asr Ext'!$C$23,IF(AND(J15>200000000,J15<=400000000),'Asr Ext'!$C$24,IF(AND(J15>400000000,J15<=800000000),'Asr Ext'!$C$25,'Asr Ext'!$C$26)))),IF(AND(J15>=1,J15<=125000000),'Asr Ext'!$D$22,IF(AND(J15>125000000,J15<=200000000),'Asr Ext'!$D$23,IF(AND(J15>200000000,J15<=400000000),'Asr Ext'!$D$24,IF(AND(J15>400000000,J15<=800000000),'Asr Ext'!$D$25,'Asr Ext'!$D$26))))) -> 0.0044 | J24: =(I24*J15)+G24 -> 4012400 | L24: =IF(L23="Comprehensive",IF(AND(M15>=1,M15<=125000000),'Asr Ext'!$C$22,IF(AND(M15>125000000,M15<=200000000),'Asr Ext'!$C$23,IF(AND(M15>200000000,M15<=400000000),'Asr Ext'!$C$24,IF(AND(M15>400000000,M15<=800000000),'Asr Ext'!$C$25,'Asr Ext'!$C$26)))),IF(AND(M15>=1,M15<=125000000),'Asr Ext'!$D$22,IF(AND(M15>125000000,M15<=200000000),'Asr Ext'!$D$23,IF(AND(M15>200000000,M15<=400000000),'Asr Ext'!$D$24,IF(AND(M15>400000000,M15<=800000000),'Asr Ext'!$D$25,'Asr Ext'!$D$26))))) -> 0.0065 | M24: =(L24*M15)+J24 -> 4740400 | O24: =IF(O23="Comprehensive",IF(AND(P15>=1,P15<=125000000),'Asr Ext'!$C$22,IF(AND(P15>125000000,P15<=200000000),'Asr Ext'!$C$23,IF(AND(P15>200000000,P15<=400000000),'Asr Ext'!$C$24,IF(AND(P15>400000000,P15<=800000000),'Asr Ext'!$C$25,'Asr Ext'!$C$26)))),IF(AND(P15>=1,P15<=125000000),'Asr Ext'!$D$22,IF(AND(P15>125000000,P15<=200000000),'Asr Ext'!$D$23,IF(AND(P15>200000000,P15<=400000000),'Asr Ext'!$D$24,IF(AND(P15>400000000,P15<=800000000),'Asr Ext'!$D$25,'Asr Ext'!$D$26))))) -> 0.0065 | P24: =(O24*P15)+M24 -> 5377400 | R24: =IF(R23="Comprehensive",IF(AND(S15>=1,S15<=125000000),'Asr Ext'!$C$22,IF(AND(S15>125000000,S15<=200000000),'Asr Ext'!$C$23,IF(AND(S15>200000000,S15<=400000000),'Asr Ext'!$C$24,IF(AND(S15>400000000,S15<=800000000),'Asr Ext'!$C$25,'Asr Ext'!$C$26)))),IF(AND(S15>=1,S15<=125000000),'Asr Ext'!$D$22,IF(AND(S15>125000000,S15<=200000000),'Asr Ext'!$D$23,IF(AND(S15>200000000,S15<=400000000),'Asr Ext'!$D$24,IF(AND(S15>400000000,S15<=800000000),'Asr Ext'!$D$25,'Asr Ext'!$D$26))))) -> 0.0065 | S24: =(R24*S15)+P24 -> 6014400
C25: Loading | F25: =IFERROR(IF(F23="Comprehensive",VLOOKUP($D$8,'Asr Ext'!$L$6:$N$20,3,0),0),0) -> 0.05 | G25: =G24*F25 -> 172900 | I25: =IFERROR(IF(I23="Comprehensive",VLOOKUP($D$8,'Asr Ext'!$L$6:$N$20,3,0),0),0) -> 0 | J25: =(J24*I25)+G25 -> 172900 | L25: =IFERROR(IF(L23="Comprehensive",VLOOKUP($D$8,'Asr Ext'!$L$6:$N$20,3,0),0),0) -> 0 | M25: =(M24*L25)+J25 -> 172900 | O25: =IFERROR(IF(O23="Comprehensive",VLOOKUP($D$8,'Asr Ext'!$L$6:$N$20,3,0),0),0) -> 0 | P25: =(P24*O25)+M25 -> 172900 | R25: =IFERROR(IF(R23="Comprehensive",VLOOKUP($D$8,'Asr Ext'!$L$6:$N$20,3,0),0),0) -> 0 | S25: =(S24*R25)+P25 -> 172900
C26: Banjir | E26: Tidak | F26: =IF($E$26="YA",IF(F23="Comprehensive",0.1%,0%),0) -> 0 | G26: =F26*G15 -> 0 | I26: =IF($E$26="YA",IF(I23="Comprehensive",0.1%,0%),0) -> 0 | J26: =(I26*J15)+G26 -> 0 | L26: =IF($E$26="YA",IF(L23="Comprehensive",0.1%,0%),0) -> 0 | M26: =(L26*M15)+J26 -> 0 | O26: =IF($E$26="YA",IF(O23="Comprehensive",0.1%,0%),0) -> 0 | P26: =(O26*P15)+M26 -> 0 | R26: =IF($E$26="YA",IF(R23="Comprehensive",0.1%,0%),0) -> 0 | S26: =(R26*S15)+P26 -> 0
C27: Gempa | E27: Tidak | F27: =IF($E$27="YA",IF(F23="Comprehensive",0.1%,0%),0) -> 0 | G27: =F27*G15 -> 0 | I27: =IF($E$27="YA",IF(I23="Comprehensive",0.1%,0%),0) -> 0 | J27: =(I27*J15)+G27 -> 0 | L27: =IF($E$27="YA",IF(L23="Comprehensive",0.1%,0%),0) -> 0 | M27: =(L27*M15)+J27 -> 0 | O27: =IF($E$27="YA",IF(O23="Comprehensive",0.1%,0%),0) -> 0 | P27: =(O27*P15)+M27 -> 0 | R27: =IF($E$27="YA",IF(R23="Comprehensive",0.1%,0%),0) -> 0 | S27: =(R27*S15)+P27 -> 0
C28: Huru-hara | E28: Tidak | F28: =IF($E$28="YA",IF(F23="Comprehensive",0.05%,0%),0) -> 0 | G28: =F28*G15 -> 0 | I28: =IF($E$28="YA",IF(I23="Comprehensive",0.05%,0%),0) -> 0 | J28: =(I28*J15)+G28 -> 0 | L28: =IF($E$28="YA",IF(L23="Comprehensive",0.05%,0%),0) -> 0 | M28: =(L28*M15)+J28 -> 0 | O28: =IF($E$28="YA",IF(O23="Comprehensive",0.05%,0%),0) -> 0 | P28: =(O28*P15)+M28 -> 0 | R28: =IF($E$28="YA",IF(R23="Comprehensive",0.05%,0%),0) -> 0 | S28: =(R28*S15)+P28 -> 0
C29: Teroris | E29: Tidak | F29: =IF($E$29="YA",IF(F23="Comprehensive",0.05%,0%),0) -> 0 | G29: =F29*G15 -> 0 | I29: =IF($E$29="YA",IF(I23="Comprehensive",0.05%,0%),0) -> 0 | J29: =(I29*J15)+G29 -> 0 | L29: =IF($E$29="YA",IF(L23="Comprehensive",0.05%,0%),0) -> 0 | M29: =(L29*M15)+J29 -> 0 | O29: =IF($E$29="YA",IF(O23="Comprehensive",0.05%,0%),0) -> 0 | P29: =(O29*P15)+M29 -> 0 | R29: =IF($E$29="YA",IF(R23="Comprehensive",0.05%,0%),0) -> 0 | S29: =(R29*S15)+P29 -> 0
C30: ASURANSI CASCO + PERLUASAN | G30: =SUM(G24:H29) -> 3630900 | J30: =SUM(J24:K29) -> 4185300 | M30: =SUM(M24:N29) -> 4913300 | P30: =SUM(P24:Q29) -> 5550300 | S30: =SUM(S24:T29) -> 6187300
C31: GAP | E31: Tidak
C32: HIC | E32: Tidak
C33: TJH | D33: 0 | E33: Tidak | G33: =IF(F23="Comprehensive",VLOOKUP(F9,'Asr Ext'!$G$40:$M$44,7,0),0) -> 0 | J33: =IF(I23="Comprehensive",VLOOKUP(I9,'Asr Ext'!$G$40:$M$44,7,0),0)+G33 -> 0 | M33: =IF(L23="Comprehensive",VLOOKUP(L9,'Asr Ext'!$G$40:$M$44,7,0),0)+J33 -> 0 | P33: =IF(O23="Comprehensive",VLOOKUP(O9,'Asr Ext'!$G$40:$M$44,7,0),0)+M33 -> 0 | S33: =IF(R23="Comprehensive",VLOOKUP(R9,'Asr Ext'!$G$40:$M$44,7,0),0)+P33 -> 0
C34: Pengemudi | D34: 0 | E34: Tidak | F34: =IF($E$34="YA",IF(F23="Comprehensive",0.5%,0%),0) -> 0 | G34: =$D$34*F34 -> 0 | I34: =IF($E$34="YA",IF(I23="Comprehensive",0.5%,0%),0) -> 0 | J34: =(I34*$D$34)+G34 -> 0 | L34: =IF($E$34="YA",IF(L23="Comprehensive",0.5%,0%),0) -> 0 | M34: =(L34*$D$34)+J34 -> 0 | O34: =IF($E$34="YA",IF(O23="Comprehensive",0.5%,0%),0) -> 0 | P34: =(O34*$D$34)+M34 -> 0 | R34: =IF($E$34="YA",IF(R23="Comprehensive",0.5%,0%),0) -> 0 | S34: =(R34*$D$34)+P34 -> 0
C35: Penumpang | D35: 0 | E35: 0 | F35: =IF(AND(F23="Comprehensive",$E$35>0),0.1%,0%)*E35 -> 0 | G35: =F35*$D$35 -> 0 | I35: =IF(AND(I23="Comprehensive",$E$35>0),0.1%,0%)*H35 -> 0 | J35: =(I35*$D$35)+G35 -> 0 | L35: =IF(AND(L23="Comprehensive",$E$35>0),0.1%,0%)*K35 -> 0 | M35: =(L35*$D$35)+J35 -> 0 | O35: =IF(AND(O23="Comprehensive",$E$35>0),0.1%,0%)*N35 -> 0 | P35: =(O35*$D$35)+M35 -> 0 | R35: =IF(AND(R23="Comprehensive",$E$35>0),0.1%,0%)*Q35 -> 0 | S35: =(R35*$D$35)+P35 -> 0
C36: ACP | E36: =IF('Home Ext'!$I$9="Badan Hukum Usaha","Tidak","Ya") -> Ya | F36: =IF($E$36="Ya",IF(OR($I$6="Passenger",G17<1000000000),VLOOKUP($S$8,'Asr Ext'!$C$70:$H$73,F9+1,0),0),0) -> 0.0065 | G36: =F12*F36 -> 910000.1 | I36: =IF($E$36="Ya",IF(OR($I$6="Passenger",J17<1000000000),VLOOKUP($S$8,'Asr Ext'!$C$70:$H$73,I9+1,0),0),0) -> 0.013 | J36: =I12*I36 -> 1820000.2 | L36: =IF($E$36="Ya",IF(OR($I$6="Passenger",M17<1000000000),VLOOKUP($S$8,'Asr Ext'!$C$70:$H$73,L9+1,0),0),0) -> 0.01989 | M36: =L12*L36 -> 2784600.3 | O36: =IF($E$36="Ya",IF(OR($I$6="Passenger",P17<1000000000),VLOOKUP($S$8,'Asr Ext'!$C$70:$H$73,O9+1,0),0),0) -> 0.02912 | P36: =O12*O36 -> 4076800.5 | R36: =IF($E$36="Ya",IF(OR($I$6="Passenger",S17<1000000000),VLOOKUP($S$8,'Asr Ext'!$C$70:$H$73,R9+1,0),0),0) -> 0.03744 | S36: =R12*R36 -> 5241600.6
C37: GARANSI MESIN | E37: Ya | G37: =IF($E$37="ya",1500000,0) -> 1500000 | J37: =IF($E$37="ya",1500000,0) -> 1500000 | M37: =IF($E$37="ya",1500000,0) -> 1500000 | P37: =IF($E$37="ya",1500000,0) -> 1500000 | S37: =IF($E$37="ya",1500000,0) -> 1500000
B38: TOTAL ASURANSI | G38: =ROUNDDOWN(SUM(G31:H37)+G30,-2) -> 6040900 | J38: =ROUNDDOWN(SUM(J31:K37)+J30,-2) -> 7505300 | M38: =ROUNDDOWN(SUM(M31:N37)+M30,-2) -> 9197900 | P38: =ROUNDDOWN(SUM(P31:Q37)+P30,-2) -> 11127100 | S38: =ROUNDDOWN(SUM(S31:T37)+S30,-2) -> 12928900
B39: PROVISI | E39: =S7 -> 0 | F39: =VLOOKUP($I$7,Product!$B$6:$K$25,10,0)+$E$39 -> 0 | G39: =F39*G17 -> 0 | I39: =VLOOKUP($I$7,Product!$B$6:$K$25,10,0)+$E$39 -> 0 | J39: =I39*J17 -> 0 | L39: =VLOOKUP($I$7,Product!$B$6:$K$25,10,0)+$E$39 -> 0 | M39: =L39*M17 -> 0 | O39: =VLOOKUP($I$7,Product!$B$6:$K$25,10,0)+$E$39 -> 0 | P39: =O39*P17 -> 0 | R39: =VLOOKUP($I$7,Product!$B$6:$K$25,10,0)+$E$39 -> 0 | S39: =R39*S17 -> 0
B40: ADMINISTRASI | F40: =VLOOKUP($I$7,Product!$B$6:$K$25,9,0) -> 4400000 | I40: =VLOOKUP($I$7,Product!$B$6:$K$25,9,0) -> 4400000 | L40: =VLOOKUP($I$7,Product!$B$6:$K$25,9,0) -> 4400000 | O40: =VLOOKUP($I$7,Product!$B$6:$K$25,9,0) -> 4400000 | R40: =VLOOKUP($I$7,Product!$B$6:$K$25,9,0) -> 4400000
B41: FIDUCIA | F41: =IF(AND(F11>0,F11<=25000000),350000,IF(AND(F11>25000000,F11<=50000000),375000,IF(AND(F11>50000000,F11<=100000000),400000,IF(AND(F11>100000000,F11<=250000000),500000,IF(AND(F11>250000000,F11<=500000000),750000,IF(AND(F11>500000000,F11<=1000000000),1150000,2250000)))))) -> 500000 | I41: =IF(AND(I11>0,I11<=25000000),350000,IF(AND(I11>25000000,I11<=50000000),375000,IF(AND(I11>50000000,I11<=100000000),400000,IF(AND(I11>100000000,I11<=250000000),500000,IF(AND(I11>250000000,I11<=500000000),750000,IF(AND(I11>500000000,I11<=1000000000),1150000,2250000)))))) -> 500000 | L41: =IF(AND(L11>0,L11<=25000000),350000,IF(AND(L11>25000000,L11<=50000000),375000,IF(AND(L11>50000000,L11<=100000000),400000,IF(AND(L11>100000000,L11<=250000000),500000,IF(AND(L11>250000000,L11<=500000000),750000,IF(AND(L11>500000000,L11<=1000000000),1150000,2250000)))))) -> 500000 | O41: =IF(AND(O11>0,O11<=25000000),350000,IF(AND(O11>25000000,O11<=50000000),375000,IF(AND(O11>50000000,O11<=100000000),400000,IF(AND(O11>100000000,O11<=250000000),500000,IF(AND(O11>250000000,O11<=500000000),750000,IF(AND(O11>500000000,O11<=1000000000),1150000,2250000)))))) -> 500000 | R41: =IF(AND(R11>0,R11<=25000000),350000,IF(AND(R11>25000000,R11<=50000000),375000,IF(AND(R11>50000000,R11<=100000000),400000,IF(AND(R11>100000000,R11<=250000000),500000,IF(AND(R11>250000000,R11<=500000000),750000,IF(AND(R11>500000000,R11<=1000000000),1150000,2250000)))))) -> 500000
B42: ANGSURAN | F42: =IF($D$6="ADDM",11,12) -> 12 | G42: =ROUNDUP(IF($D$6="ADDM",G20/G9,0),-3) -> 0 | I42: =IF($D$6="ADDM",23,24) -> 24 | J42: =ROUNDUP(IF($D$6="ADDM",J20/J9,0),-3) -> 0 | L42: =IF($D$6="ADDM",35,36) -> 36 | M42: =ROUNDUP(IF($D$6="ADDM",M20/M9,0),-3) -> 0 | O42: =IF($D$6="ADDM",47,48) -> 48 | P42: =ROUNDUP(IF($D$6="ADDM",P20/P9,0),-3) -> 0 | R42: =IF($D$6="ADDM",59,60) -> 60 | S42: =ROUNDUP(IF($D$6="ADDM",S20/S9,0),-3) -> 0
B43: TOTAL BAYAR PERTAMA | F43: =G16+G38+G39+F40+F41 -> 17940900 | I43: =J16+J38+J39+I40+I41 -> 19405300 | L43: =M16+M38+M39+L40+L41 -> 21097900 | O43: =P16+P38+P39+O40+O41 -> 23027100 | R43: =S16+S38+S39+R40+R41 -> 24828900
B44: PENCAIRAN GROSS | F44: =F11-F43 -> 122059100 | I44: =I11-I43 -> 120594700 | L44: =L11-L43 -> 118902100 | O44: =O11-O43 -> 116972900 | R44: =R11-R43 -> 115171100
B45: BBNKB | G45: =$O$5 -> 0 | J45: =$O$5 -> 0 | M45: =$O$5 -> 0 | P45: =$O$5 -> 0 | S45: =$O$5 -> 0
B46: PKB | G46: =$O$6 -> 0 | J46: =$O$6 -> 0 | M46: =$O$6 -> 0 | P46: =$O$6 -> 0 | S46: =$O$6 -> 0
B47: FAKTUR | G47: =$O$7 -> 0 | J47: =$O$7 -> 0 | M47: =$O$7 -> 0 | P47: =$O$7 -> 0 | S47: =$O$7 -> 0
B48: NILAI TITIPAN ANGSURAN | F48: =$P$4 -> 0 | G48: =G42*F48 -> 0 | I48: =$P$4 -> 0 | J48: =J42*I48 -> 0 | L48: =$P$4 -> 0 | M48: =M42*L48 -> 0 | O48: =$P$4 -> 0 | P48: =P42*O48 -> 0 | R48: =$P$4 -> 0 | S48: =S42*R48 -> 0
B49: PECAIRAN NETO | F49: =IF(F12=0,0,F44-(G45+G46+G47+G48)) -> 122059100 | I49: =IF(I12=0,0,I44-(J45+J46+J47+J48)) -> 120594700 | L49: =IF(L12=0,0,L44-(M45+M46+M47+M48)) -> 118902100 | O49: =IF(O12=0,0,O44-(P45+P46+P47+P48)) -> 116972900 | R49: =IF(R12=0,0,R44-(S45+S46+S47+S48)) -> 115171100
B51: REFUND ASURANSI
B52: REFUND BUNGA
B53: REFUND PROVISI
B54: REFUND ADMIN
B55: TOTAL REFUND
B56: PENCAIRAN ALL IN
B60: TENOR | F60: 1 | G60: =F60*12 -> 12 | I60: 2 | J60: =I60*12 -> 24 | L60: 3 | M60: =L60*12 -> 36 | O60: 4 | P60: =O60*12 -> 48 | R60: 5 | S60: =R60*12 -> 60
B62: PHPM | F62: =IF(F10>=1,VLOOKUP($B$10,'PHPM 1 DT Ext'!$K$5:$L$841,2,0),0) -> 140000016 | I62: =IF(I10>=1,VLOOKUP($B$10,'PHPM 1 DT Ext'!$K$5:$L$841,2,0),0) -> 140000016 | L62: =IF(L10>=1,VLOOKUP($B$10,'PHPM 1 DT Ext'!$K$5:$L$841,2,0),0) -> 140000016 | O62: =IF(O10>=1,VLOOKUP($B$10,'PHPM 1 DT Ext'!$K$5:$L$841,2,0),0) -> 140000016 | R62: =IF(R10>=1,VLOOKUP($B$10,'PHPM 1 DT Ext'!$K$5:$L$841,2,0),0) -> 140000016
B63: PENCAIRAN | F63: ='Home Ext'!$I$75 -> 60000000 | I63: ='Home Ext'!$I$75 -> 60000000 | L63: ='Home Ext'!$I$75 -> 60000000 | O63: ='Home Ext'!$I$75 -> 60000000 | R63: ='Home Ext'!$I$75 -> 60000000
B64: TOTAL DP | F64: =$G$38+$G$39+$F$40+$F$41 -> 10940900 | I64: =$J$38+$J$39+$I$40+$I$41 -> 12405300 | L64: =$M$38+$M$39+$L$40+$L$41 -> 14097900 | O64: =$P$38+$P$39+$O$40+$O$41 -> 16027100 | R64: =$S$38+$S$39+$R$40+$R$41 -> 17828900
B65: DP NET | F65: =G65/F62 -> 0.49327934 | G65: =F62-(F63+F64) -> 69059116 | I65: =J65/I62 -> 0.48281934 | J65: =I62-(I63+I64) -> 67594716 | L65: =M65/L62 -> 0.47072935 | M65: =L62-(L63+L64) -> 65902116 | O65: =P65/O62 -> 0.45694935 | P65: =O62-(O63+O64) -> 63972916 | R65: =S65/R62 -> 0.44407935 | S65: =R62-(R63+R64) -> 62171116
B66: LTV | F66: =IF(F65>=F16,(100%-(G65/F62)),0%) -> 0.50672066 | G66: =F62*F66 -> 70940900 | I66: =IF(I65>=I16,(100%-(J65/I62)),0%) -> 0.51718066 | J66: =I62*I66 -> 72405300 | L66: =IF(L65>=L16,(100%-(M65/L62)),0%) -> 0.52927065 | M66: =L62*L66 -> 74097900 | O66: =IF(O65>=O16,(100%-(P65/O62)),0%) -> 0.54305065 | P66: =O62*O66 -> 76027100 | R66: =IF(R65>=R16,(100%-(S65/R62)),0%) -> 0.55592065 | S66: =R62*R66 -> 77828900
B67: BUNGA JUAL | F67: =$F$19 -> 0.075977942 | G67: =G66*F67 -> 5389943.6 | I67: =$I$19 -> 0.14608316 | J67: =J66*I67 -> 10577195 | L67: =$L$19 -> 0.22167034 | M67: =M66*L67 -> 16425307 | O67: =$O$19 -> 0.33514608 | P67: =P66*O67 -> 25480185 | R67: =$R$19 -> 0.45557895 | S67: =S66*R67 -> 35457209
B68: TOTAL AR | F68: =G66+G67 -> 76330844 | I68: =J66+J67 -> 82982495 | L68: =M66+M67 -> 90523207 | O68: =P66+P67 -> 1.0150728e+08 | R68: =S66+S67 -> 1.1328611e+08
B69: ANGSURAN | F69: =$G$9 -> 12 | G69: =IFERROR(ROUNDUP(F68/G9,-3),0) -> 6361000 | I69: =$J$9 -> 24 | J69: =IFERROR(ROUNDUP(I68/J9,-3),0) -> 3458000 | L69: =$M$9 -> 36 | M69: =IFERROR(ROUNDUP(L68/M9,-3),0) -> 2515000 | O69: =$P$9 -> 48 | P69: =IFERROR(ROUNDUP(O68/P9,-3),0) -> 2115000 | R69: =$S$9 -> 60 | S69: =IFERROR(ROUNDUP(R68/S9,-3),0) -> 1889000
B71: Pencairan | F71: Maksimal | J71: Pencairan | N71: ='Home Ext'!$I$75 -> 60000000
B72: Tenor | E72: Pencairan | G72: Angsuran | J72: Tenor | M72: Pencairan | O72: Angsuran
B73: =$F$42 -> 12 | C73: Bulan | D73: =CONCATENATE($B$73," ",$C$73) -> 12 Bulan | E73: =IFERROR($F$49,0) -> 122059100 | G73: =IFERROR($F$21,0) -> 11926000 | J73: =$F$42 -> 12 | K73: Bulan | L73: =CONCATENATE($B$73," ",$C$73) -> 12 Bulan | M73: =IFERROR('Home Ext'!$I$75,0) -> 60000000 | O73: =IFERROR($G$69,0) -> 6361000
B74: =$I$42 -> 24 | C74: Bulan | D74: =CONCATENATE($B$74," ",$C$74) -> 24 Bulan | E74: =IFERROR($I$49,0) -> 120594700 | G74: =IFERROR($I$21,0) -> 6352000 | J74: =$I$42 -> 24 | K74: Bulan | L74: =CONCATENATE($B$74," ",$C$74) -> 24 Bulan | M74: =IFERROR('Home Ext'!$I$75,0) -> 60000000 | O74: =IFERROR($J$69,0) -> 3458000
B75: =$L$42 -> 36 | C75: Bulan | D75: =CONCATENATE($B$75," ",$C$75) -> 36 Bulan | E75: =IFERROR($L$49,0) -> 118902100 | G75: =IFERROR($L$21,0) -> 4514000 | J75: =$L$42 -> 36 | K75: Bulan | L75: =CONCATENATE($B$75," ",$C$75) -> 36 Bulan | M75: =IFERROR('Home Ext'!$I$75,0) -> 60000000 | O75: =IFERROR($M$69,) -> 2515000
B76: =$O$42 -> 48 | C76: Bulan | D76: =CONCATENATE($B$76," ",$C$76) -> 48 Bulan | E76: =IFERROR($O$49,0) -> 116972900 | G76: =IFERROR($O$21,0) -> 3700000 | J76: =$O$42 -> 48 | K76: Bulan | L76: =CONCATENATE($B$76," ",$C$76) -> 48 Bulan | M76: =IFERROR('Home Ext'!$I$75,0) -> 60000000 | O76: =IFERROR($P$69,0) -> 2115000
B77: =$R$42 -> 60 | C77: Bulan | D77: =CONCATENATE($B$77," ",$C$77) -> 60 Bulan | E77: =IFERROR($R$49,0) -> 115171100 | G77: =IFERROR($R$21,0) -> 3227000 | J77: =$R$42 -> 60 | K77: Bulan | L77: =CONCATENATE($B$77," ",$C$77) -> 60 Bulan | M77: =IFERROR('Home Ext'!$I$75,0) -> 60000000 | O77: =IFERROR($S$69,0) -> 1889000

Sheet UC Ext
B4: Merk | D4: ='Home Ext'!$O$21 -> HONDA | G4: Type Kendaraan | I4: ='Home Ext'!$O$25 -> BRIO | N4: Deposit Angsuran | P4: 0 | Q4: Up ACP | S4: 0
B5: Type Debitur | D5: ='Home Ext'!$O$9 -> Perorangan (Wiraswasta) | G5: Model Kendaraan | I5: ='Home Ext'!$O$29 -> ALL NEW BRIO RS CVT | N5: BBNKB | O5: 0 | Q5: Up Rate | S5: 0.005
B6: Type Angsuran | D6: ='Home Ext'!$Q$33 -> ADDB | G6: Penggunaan Unit | I6: ='Home Ext'!$O$17 -> Commercial | N6: PKB | O6: 0 | Q6: Up Adm | S6: 0
B7: Type Unit | D7: =VLOOKUP('Home Ext'!$O$21,'PHPM 2 UC Ext'!$D$4:$E$53,2,0) -> Japan | G7: Product | I7: =CONCATENATE("Captive"," ",'Home Ext'!$O$17," ","Low Rate") -> Captive Commercial Low Rate | N7: FAKTUR | O7: 0 | Q7: Up Provisi | S7: 0
B8: Thn (NIK) | D8: ='Home Ext'!$O$33 -> 2015 | F8: =15-(2026-D8) -> 4 | G8: Asuransi | I8: ='Home Ext'!$O$37 -> TLO All Tenor | N8: Asuransi | O8: BATAS BAWAH | Q8: Usia Debitur | S8: ='Home Ext'!$I$13 -> 36-45 tahun
B9: TENOR | F9: 1 | G9: =F9*12 -> 12 | I9: 2 | J9: =I9*12 -> 24 | L9: 3 | M9: =L9*12 -> 36 | O9: 4 | P9: =O9*12 -> 48 | R9: 5 | S9: =R9*12 -> 60
B10: =CONCATENATE('Home Ext'!$O$21,"-",'Home Ext'!$O$25,"-",'Home Ext'!$O$29) -> HONDA-BRIO-ALL NEW BRIO RS CVT | F10: =(16-F9)-(2026-$D$8) -> 4 | I10: =(16-I9)-(2026-$D$8) -> 3 | L10: =(16-L9)-(2026-$D$8) -> 2 | O10: =(16-O9)-(2026-$D$8) -> 1 | R10: =(16-R9)-(2026-$D$8) -> 0
B11: Harga OTR | D11: Showroom | F11: ='Home Ext'!$O$49 -> 110000000 | I11: ='Home Ext'!$O$49 -> 110000000 | L11: ='Home Ext'!$O$49 -> 110000000 | O11: ='Home Ext'!$O$49 -> 110000000 | R11: ='Home Ext'!$O$49 -> 110000000
D12: PHPM | F12: =IF(F10>=1,VLOOKUP($B$10,'PHPM 1 UC Ext'!$K$5:$L$841,2,0),0) -> #N/A | I12: =IF(I10>=1,VLOOKUP($B$10,'PHPM 1 DT Ext'!$K$5:$L$841,2,0),0) -> 140000016 | L12: =IF(L10>=1,VLOOKUP($B$10,'PHPM 1 DT Ext'!$K$5:$L$841,2,0),0) -> 140000016 | O12: =IF(O10>=1,VLOOKUP($B$10,'PHPM 1 DT Ext'!$K$5:$L$841,2,0),0) -> 140000016 | R12: =IF(R10>=1,VLOOKUP($B$10,'PHPM 1 DT Ext'!$K$5:$L$841,2,0),0) -> 0
D13: ROUNDDOWN PHPM | F13: =ROUNDDOWN(F12,-2) -> #N/A | I13: =ROUNDDOWN(I12,-2) -> 140000000 | L13: =ROUNDDOWN(L12,-2) -> 140000000 | O13: =ROUNDDOWN(O12,-2) -> 140000000 | R13: =ROUNDDOWN(R12,-2) -> 0
B14: Deviasi (%) | D14: (Rp.) | F14: =IFERROR(G14/F11,0) -> 0 | G14: =IF(F11<=F12,0,F11-F12) -> #N/A | I14: =IFERROR(J14/I11,0) -> 0 | J14: =IF(I11<=I12,0,I11-I12) -> 0 | L14: =IFERROR(M14/L11,0) -> 0 | M14: =IF(L11<=L12,0,L11-L12) -> 0 | O14: =IFERROR(P14/O11,0) -> 0 | P14: =IF(O11<=O12,0,O11-O12) -> 0 | R14: =IFERROR(S14/R11,0) -> 1 | S14: =IF(R11<=R12,0,R11-R12) -> 110000000
B15: Sum Insured | D15: % | E15: Rp. | F15: 1 | G15: =F11*F15 -> 110000000 | I15: 0.9 | J15: =I11*I15 -> 99000000 | L15: 0.8 | M15: =L11*L15 -> 88000000 | O15: 0.7 | P15: =O11*O15 -> 77000000 | R15: 0.7 | S15: =R11*R15 -> 77000000
B16: Net DP | D16: % | E16: Rp. | F16: =IF('Home Ext'!$O$9="Perorangan (Wiraswasta)",30%+F14,10%+F14) -> 0.3 | G16: =F11*F16 -> 33000000 | I16: =IF('Home Ext'!$O$9="Perorangan (Wiraswasta)",30%+I14,10%+I14) -> 0.3 | J16: =I11*I16 -> 33000000 | L16: =IF('Home Ext'!$O$9="Perorangan (Wiraswasta)",30%+L14,10%+L14) -> 0.3 | M16: =L11*L16 -> 33000000 | O16: =IF('Home Ext'!$O$9="Perorangan (Wiraswasta)",30%+O14,10%+O14) -> 0.3 | P16: =O11*O16 -> 33000000 | R16: =IF('Home Ext'!$O$9="Perorangan (Wiraswasta)",30%+R14,10%+R14) -> 1.3 | S16: =R11*R16 -> 143000000
B17: LTV | D17: % | E17: Rp. | F17: =100%-F16 -> 0.7 | G17: =F11-G16 -> 77000000 | I17: =100%-I16 -> 0.7 | J17: =I11-J16 -> 77000000 | L17: =100%-L16 -> 0.7 | M17: =L11-M16 -> 77000000 | O17: =100%-O16 -> 0.7 | P17: =O11-P16 -> 77000000 | R17: =100%-R16 -> -0.3 | S17: =R11-S16 -> -33000000
B18: RATE p.a (%) | D18: Eff R | E18: Flat Rate | F18: =VLOOKUP($I$7,Product!$B$6:$K$25,1+F9,0) -> #N/A | G18: =IF($D$6="ADDM",(((PMT(F18/12,G9,1,0,1)*(-1))*G9)-1)*12/G9,IF($D$6="ADDB",(((PMT(F18/12,G9,1,0,0)*(-1))*G9)-1)*12/G9," ")) -> #N/A | H18: =G18+$S$5 -> #N/A | I18: =VLOOKUP($I$7,Product!$B$6:$K$25,1+I9,0) -> #N/A | J18: =IF($D$6="ADDM",(((PMT(I18/12,J9,1,0,1)*(-1))*J9)-1)*12/J9,IF($D$6="ADDB",(((PMT(I18/12,J9,1,0,0)*(-1))*J9)-1)*12/J9," ")) -> #N/A | K18: =J18+$S$5 -> #N/A | L18: =VLOOKUP($I$7,Product!$B$6:$K$25,1+L9,0) -> #N/A | M18: =IF($D$6="ADDM",(((PMT(L18/12,M9,1,0,1)*(-1))*M9)-1)*12/M9,IF($D$6="ADDB",(((PMT(L18/12,M9,1,0,0)*(-1))*M9)-1)*12/M9," ")) -> #N/A | N18: =M18+$S$5 -> #N/A | O18: =VLOOKUP($I$7,Product!$B$6:$K$25,1+O9,0) -> #N/A | P18: =IF($D$6="ADDM",(((PMT(O18/12,P9,1,0,1)*(-1))*P9)-1)*12/P9,IF($D$6="ADDB",(((PMT(O18/12,P9,1,0,0)*(-1))*P9)-1)*12/P9," ")) -> #N/A | Q18: =P18+$S$5 -> #N/A | R18: =VLOOKUP($I$7,Product!$B$6:$K$25,1+R9,0) -> #N/A | S18: =IF($D$6="ADDM",(((PMT(R18/12,S9,1,0,1)*(-1))*S9)-1)*12/S9,IF($D$6="ADDB",(((PMT(R18/12,S9,1,0,0)*(-1))*S9)-1)*12/S9," ")) -> #N/A | T18: =S18+$S$5 -> #N/A
B19: Bunga Jual | D19: % | E19: Rp. | F19: =(H18*F9) -> #N/A | G19: =G17*F19 -> #N/A | I19: =(K18*I9) -> #N/A | J19: =J17*I19 -> #N/A | L19: =(N18*L9) -> #N/A | M19: =M17*L19 -> #N/A | O19: =(Q18*O9) -> #N/A | P19: =P17*O19 -> #N/A | R19: =(T18*R9) -> #N/A | S19: =S17*R19 -> #N/A
B20: TOTAL A/R | G20: =G17+G19 -> #N/A | J20: =J17+J19 -> #N/A | M20: =M17+M19 -> #N/A | P20: =P17+P19 -> #N/A | S20: =S17+S19 -> #N/A
B21: ANGSURAN | F21: =IF(F12=0,0,ROUNDUP(G20/G9,-3)) -> #N/A | I21: =IF(I12=0,0,ROUNDUP(J20/J9,-3)) -> #N/A | L21: =IF(L12=0,0,ROUNDUP(M20/M9,-3)) -> #N/A | O21: =IF(O12=0,0,ROUNDUP(P20/P9,-3)) -> #N/A | R21: =IF(R12=0,0,ROUNDUP(S20/S9,-3)) -> 0
B22: TOTAL BAYAR PERTAMA
B23: ASURANSI | F23: =IF(OR($I$8="Comprehensive 1 tahun",$I$8="Comprehensive All Tenor"),"Comprehensive","TLO") -> TLO | I23: =IF($I$8="Comprehensive All Tenor","Comprehensive","TLO") -> TLO | L23: =IF($I$8="Comprehensive All Tenor","Comprehensive","TLO") -> TLO | O23: =IF($I$8="Comprehensive All Tenor","Comprehensive","TLO") -> TLO | R23: =IF($I$8="Comprehensive All Tenor","Comprehensive","TLO") -> TLO
C24: Casco | F24: =IF(F23="Comprehensive",IF(AND(G15>=1,G15<=125000000),'Asr Ext'!$C$22,IF(AND(G15>125000000,G15<=200000000),'Asr Ext'!$C$23,IF(AND(G15>200000000,G15<=400000000),'Asr Ext'!$C$24,IF(AND(G15>400000000,G15<=800000000),'Asr Ext'!$C$25,'Asr Ext'!$C$26)))),IF(AND(G15>=1,G15<=125000000),'Asr Ext'!$D$22,IF(AND(G15>125000000,G15<=200000000),'Asr Ext'!$D$23,IF(AND(G15>200000000,G15<=400000000),'Asr Ext'!$D$24,IF(AND(G15>400000000,G15<=800000000),'Asr Ext'!$D$25,'Asr Ext'!$D$26))))) -> 0.0065 | G24: =F24*G15 -> 715000 | I24: =IF(I23="Comprehensive",IF(AND(J15>=1,J15<=125000000),'Asr Ext'!$C$22,IF(AND(J15>125000000,J15<=200000000),'Asr Ext'!$C$23,IF(AND(J15>200000000,J15<=400000000),'Asr Ext'!$C$24,IF(AND(J15>400000000,J15<=800000000),'Asr Ext'!$C$25,'Asr Ext'!$C$26)))),IF(AND(J15>=1,J15<=125000000),'Asr Ext'!$D$22,IF(AND(J15>125000000,J15<=200000000),'Asr Ext'!$D$23,IF(AND(J15>200000000,J15<=400000000),'Asr Ext'!$D$24,IF(AND(J15>400000000,J15<=800000000),'Asr Ext'!$D$25,'Asr Ext'!$D$26))))) -> 0.0065 | J24: =(I24*J15)+G24 -> 1358500 | L24: =IF(L23="Comprehensive",IF(AND(M15>=1,M15<=125000000),'Asr Ext'!$C$22,IF(AND(M15>125000000,M15<=200000000),'Asr Ext'!$C$23,IF(AND(M15>200000000,M15<=400000000),'Asr Ext'!$C$24,IF(AND(M15>400000000,M15<=800000000),'Asr Ext'!$C$25,'Asr Ext'!$C$26)))),IF(AND(M15>=1,M15<=125000000),'Asr Ext'!$D$22,IF(AND(M15>125000000,M15<=200000000),'Asr Ext'!$D$23,IF(AND(M15>200000000,M15<=400000000),'Asr Ext'!$D$24,IF(AND(M15>400000000,M15<=800000000),'Asr Ext'!$D$25,'Asr Ext'!$D$26))))) -> 0.0065 | M24: =(L24*M15)+J24 -> 1930500 | O24: =IF(O23="Comprehensive",IF(AND(P15>=1,P15<=125000000),'Asr Ext'!$C$22,IF(AND(P15>125000000,P15<=200000000),'Asr Ext'!$C$23,IF(AND(P15>200000000,P15<=400000000),'Asr Ext'!$C$24,IF(AND(P15>400000000,P15<=800000000),'Asr Ext'!$C$25,'Asr Ext'!$C$26)))),IF(AND(P15>=1,P15<=125000000),'Asr Ext'!$D$22,IF(AND(P15>125000000,P15<=200000000),'Asr Ext'!$D$23,IF(AND(P15>200000000,P15<=400000000),'Asr Ext'!$D$24,IF(AND(P15>400000000,P15<=800000000),'Asr Ext'!$D$25,'Asr Ext'!$D$26))))) -> 0.0065 | P24: =(O24*P15)+M24 -> 2431000 | R24: =IF(R23="Comprehensive",IF(AND(S15>=1,S15<=125000000),'Asr Ext'!$C$22,IF(AND(S15>125000000,S15<=200000000),'Asr Ext'!$C$23,IF(AND(S15>200000000,S15<=400000000),'Asr Ext'!$C$24,IF(AND(S15>400000000,S15<=800000000),'Asr Ext'!$C$25,'Asr Ext'!$C$26)))),IF(AND(S15>=1,S15<=125000000),'Asr Ext'!$D$22,IF(AND(S15>125000000,S15<=200000000),'Asr Ext'!$D$23,IF(AND(S15>200000000,S15<=400000000),'Asr Ext'!$D$24,IF(AND(S15>400000000,S15<=800000000),'Asr Ext'!$D$25,'Asr Ext'!$D$26))))) -> 0.0065 | S24: =(R24*S15)+P24 -> 2931500
C25: Loading | F25: =IFERROR(IF(F23="Comprehensive",VLOOKUP($D$8,'Asr Ext'!$L$6:$N$20,3,0),0),0) -> 0 | G25: =G24*F25 -> 0 | I25: =IFERROR(IF(I23="Comprehensive",VLOOKUP($D$8,'Asr Ext'!$L$6:$N$20,3,0),0),0) -> 0 | J25: =(J24*I25)+G25 -> 0 | L25: =IFERROR(IF(L23="Comprehensive",VLOOKUP($D$8,'Asr Ext'!$L$6:$N$20,3,0),0),0) -> 0 | M25: =(M24*L25)+J25 -> 0 | O25: =IFERROR(IF(O23="Comprehensive",VLOOKUP($D$8,'Asr Ext'!$L$6:$N$20,3,0),0),0) -> 0 | P25: =(P24*O25)+M25 -> 0 | R25: =IFERROR(IF(R23="Comprehensive",VLOOKUP($D$8,'Asr Ext'!$L$6:$N$20,3,0),0),0) -> 0 | S25: =(S24*R25)+P25 -> 0
C26: Banjir | E26: Tidak | F26: =IF($E$26="YA",IF(F23="Comprehensive",0.1%,0%),0) -> 0 | G26: =F26*G15 -> 0 | I26: =IF($E$26="YA",IF(I23="Comprehensive",0.1%,0%),0) -> 0 | J26: =(I26*J15)+G26 -> 0 | L26: =IF($E$26="YA",IF(L23="Comprehensive",0.1%,0%),0) -> 0 | M26: =(L26*M15)+J26 -> 0 | O26: =IF($E$26="YA",IF(O23="Comprehensive",0.1%,0%),0) -> 0 | P26: =(O26*P15)+M26 -> 0 | R26: =IF($E$26="YA",IF(R23="Comprehensive",0.1%,0%),0) -> 0 | S26: =(R26*S15)+P26 -> 0
C27: Gempa | E27: Tidak | F27: =IF($E$27="YA",IF(F23="Comprehensive",0.1%,0%),0) -> 0 | G27: =F27*G15 -> 0 | I27: =IF($E$27="YA",IF(I23="Comprehensive",0.1%,0%),0) -> 0 | J27: =(I27*J15)+G27 -> 0 | L27: =IF($E$27="YA",IF(L23="Comprehensive",0.1%,0%),0) -> 0 | M27: =(L27*M15)+J27 -> 0 | O27: =IF($E$27="YA",IF(O23="Comprehensive",0.1%,0%),0) -> 0 | P27: =(O27*P15)+M27 -> 0 | R27: =IF($E$27="YA",IF(R23="Comprehensive",0.1%,0%),0) -> 0 | S27: =(R27*S15)+P27 -> 0
C28: Huru-hara | E28: Tidak | F28: =IF($E$28="YA",IF(F23="Comprehensive",0.05%,0%),0) -> 0 | G28: =F28*G15 -> 0 | I28: =IF($E$28="YA",IF(I23="Comprehensive",0.05%,0%),0) -> 0 | J28: =(I28*J15)+G28 -> 0 | L28: =IF($E$28="YA",IF(L23="Comprehensive",0.05%,0%),0) -> 0 | M28: =(L28*M15)+J28 -> 0 | O28: =IF($E$28="YA",IF(O23="Comprehensive",0.05%,0%),0) -> 0 | P28: =(O28*P15)+M28 -> 0 | R28: =IF($E$28="YA",IF(R23="Comprehensive",0.05%,0%),0) -> 0 | S28: =(R28*S15)+P28 -> 0
C29: Teroris | E29: Tidak | F29: =IF($E$29="YA",IF(F23="Comprehensive",0.05%,0%),0) -> 0 | G29: =F29*G15 -> 0 | I29: =IF($E$29="YA",IF(I23="Comprehensive",0.05%,0%),0) -> 0 | J29: =(I29*J15)+G29 -> 0 | L29: =IF($E$29="YA",IF(L23="Comprehensive",0.05%,0%),0) -> 0 | M29: =(L29*M15)+J29 -> 0 | O29: =IF($E$29="YA",IF(O23="Comprehensive",0.05%,0%),0) -> 0 | P29: =(O29*P15)+M29 -> 0 | R29: =IF($E$29="YA",IF(R23="Comprehensive",0.05%,0%),0) -> 0 | S29: =(R29*S15)+P29 -> 0
C30: ASURANSI CASCO + PERLUASAN | F30: =SUM(G24:H29) -> 715000 | I30: =SUM(J24:K29) -> 1358500 | L30: =SUM(M24:N29) -> 1930500 | O30: =SUM(P24:Q29) -> 2431000 | R30: =SUM(S24:T29) -> 2931500
C31: GAP | E31: Tidak
C32: HIC | E32: Tidak
C33: TJH | D33: 0 | E33: Tidak | G33: =IF(F23="Comprehensive",VLOOKUP(F9,'Asr Ext'!$G$40:$M$44,7,0),0) -> 0 | J33: =IF(I23="Comprehensive",VLOOKUP(I9,'Asr Ext'!$G$40:$M$44,7,0),0)+G33 -> 0 | M33: =IF(L23="Comprehensive",VLOOKUP(L9,'Asr Ext'!$G$40:$M$44,7,0),0)+J33 -> 0 | P33: =IF(O23="Comprehensive",VLOOKUP(O9,'Asr Ext'!$G$40:$M$44,7,0),0)+M33 -> 0 | S33: =IF(R23="Comprehensive",VLOOKUP(R9,'Asr Ext'!$G$40:$M$44,7,0),0)+P33 -> 0
C34: Pengemudi | D34: 0 | E34: Tidak | F34: =IF($E$34="YA",IF(F23="Comprehensive",0.5%,0%),0) -> 0 | G34: =$D$34*F34 -> 0 | I34: =IF($E$34="YA",IF(I23="Comprehensive",0.5%,0%),0) -> 0 | J34: =(I34*$D$34)+G34 -> 0 | L34: =IF($E$34="YA",IF(L23="Comprehensive",0.5%,0%),0) -> 0 | M34: =(L34*$D$34)+J34 -> 0 | O34: =IF($E$34="YA",IF(O23="Comprehensive",0.5%,0%),0) -> 0 | P34: =(O34*$D$34)+M34 -> 0 | R34: =IF($E$34="YA",IF(R23="Comprehensive",0.5%,0%),0) -> 0 | S34: =(R34*$D$34)+P34 -> 0
C35: Penumpang | D35: 0 | E35: 0 | F35: =IF(AND(F23="Comprehensive",$E$35>0),0.1%,0%)*E35 -> 0 | G35: =F35*$D$35 -> 0 | I35: =IF(AND(I23="Comprehensive",$E$35>0),0.1%,0%)*H35 -> 0 | J35: =(I35*$D$35)+G35 -> 0 | L35: =IF(AND(L23="Comprehensive",$E$35>0),0.1%,0%)*K35 -> 0 | M35: =(L35*$D$35)+J35 -> 0 | O35: =IF(AND(O23="Comprehensive",$E$35>0),0.1%,0%)*N35 -> 0 | P35: =(O35*$D$35)+M35 -> 0 | R35: =IF(AND(R23="Comprehensive",$E$35>0),0.1%,0%)*Q35 -> 0 | S35: =(R35*$D$35)+P35 -> 0
C36: ACP | E36: Tidak | F36: =IF($E$36="Ya",IF(OR($I$6="Passenger",G17<1000000000),VLOOKUP($S$8,'Asr Ext'!$K$70:$P$73,F9+1,0),0),0) -> 0 | G36: =F11*F36 -> 0 | I36: =IF($E$36="Ya",IF(OR($I$6="Passenger",J17<1000000000),VLOOKUP($S$8,'Asr Ext'!$K$70:$P$73,I9+1,0),0),0) -> 0 | J36: =I11*I36 -> 0 | L36: =IF($E$36="Ya",IF(OR($I$6="Passenger",M17<1000000000),VLOOKUP($S$8,'Asr Ext'!$K$70:$P$73,L9+1,0),0),0) -> 0 | M36: =L11*L36 -> 0 | O36: =IF($E$36="Ya",IF(OR($I$6="Passenger",P17<1000000000),VLOOKUP($S$8,'Asr Ext'!$K$70:$P$73,O9+1,0),0),0) -> 0 | P36: =O11*O36 -> 0 | R36: =IF($E$36="Ya",IF(OR($I$6="Passenger",S17<1000000000),VLOOKUP($S$8,'Asr Ext'!$K$70:$P$73,R9+1,0),0),0) -> 0 | S36: =R11*R36 -> 0
C37: GARANSI MESIN | E37: Ya | G37: =IF($E$37="ya",1500000,0) -> 1500000 | J37: =IF($E$37="ya",1500000,0) -> 1500000 | M37: =IF($E$37="ya",1500000,0) -> 1500000 | P37: =IF($E$37="ya",1500000,0) -> 1500000 | S37: =IF($E$37="ya",1500000,0) -> 1500000
B38: TOTAL ASURANSI | F38: =ROUNDUP(SUM(G31:H37)+F30,-2) -> 2215000 | I38: =ROUNDUP(SUM(J31:K37)+I30,-2) -> 2858500 | L38: =ROUNDUP(SUM(M31:N37)+L30,-2) -> 3430500 | O38: =ROUNDUP(SUM(P31:Q37)+O30,-2) -> 3931000 | R38: =ROUNDUP(SUM(S31:T37)+R30,-2) -> 4431500
B39: PROVISI | E39: =S7 -> 0 | F39: =VLOOKUP($I$7,Product!$B$6:$K$25,10,0)+$E$39 -> #N/A | G39: =ROUNDUP(F39*G17,-2) -> #N/A | I39: =VLOOKUP($I$7,Product!$B$6:$K$25,10,0)+$E$39 -> #N/A | J39: =I39*J17 -> #N/A | L39: =VLOOKUP($I$7,Product!$B$6:$K$25,10,0)+$E$39 -> #N/A | M39: =L39*M17 -> #N/A | O39: =VLOOKUP($I$7,Product!$B$6:$K$25,10,0)+$E$39 -> #N/A | P39: =O39*P17 -> #N/A | R39: =VLOOKUP($I$7,Product!$B$6:$K$25,10,0)+$E$39 -> #N/A | S39: =R39*S17 -> #N/A
B40: ADMINISTRASI | F40: =VLOOKUP($I$7,Product!$B$6:$K$25,9,0) -> #N/A | I40: =VLOOKUP($I$7,Product!$B$6:$K$25,9,0) -> #N/A | L40: =VLOOKUP($I$7,Product!$B$6:$K$25,9,0) -> #N/A | O40: =VLOOKUP($I$7,Product!$B$6:$K$25,9,0) -> #N/A | R40: =VLOOKUP($I$7,Product!$B$6:$K$25,9,0) -> #N/A
B41: FIDUCIA | F41: =IF(AND(F11>0,F11<=25000000),350000,IF(AND(F11>25000000,F11<=50000000),375000,IF(AND(F11>50000000,F11<=100000000),400000,IF(AND(F11>100000000,F11<=250000000),500000,IF(AND(F11>250000000,F11<=500000000),750000,IF(AND(F11>500000000,F11<=1000000000),1150000,2250000)))))) -> 500000 | I41: =IF(AND(I11>0,I11<=25000000),350000,IF(AND(I11>25000000,I11<=50000000),375000,IF(AND(I11>50000000,I11<=100000000),400000,IF(AND(I11>100000000,I11<=250000000),500000,IF(AND(I11>250000000,I11<=500000000),750000,IF(AND(I11>500000000,I11<=1000000000),1150000,2250000)))))) -> 500000 | L41: =IF(AND(L11>0,L11<=25000000),350000,IF(AND(L11>25000000,L11<=50000000),375000,IF(AND(L11>50000000,L11<=100000000),400000,IF(AND(L11>100000000,L11<=250000000),500000,IF(AND(L11>250000000,L11<=500000000),750000,IF(AND(L11>500000000,L11<=1000000000),1150000,2250000)))))) -> 500000 | O41: =IF(AND(O11>0,O11<=25000000),350000,IF(AND(O11>25000000,O11<=50000000),375000,IF(AND(O11>50000000,O11<=100000000),400000,IF(AND(O11>100000000,O11<=250000000),500000,IF(AND(O11>250000000,O11<=500000000),750000,IF(AND(O11>500000000,O11<=1000000000),1150000,2250000)))))) -> 500000 | R41: =IF(AND(R11>0,R11<=25000000),350000,IF(AND(R11>25000000,R11<=50000000),375000,IF(AND(R11>50000000,R11<=100000000),400000,IF(AND(R11>100000000,R11<=250000000),500000,IF(AND(R11>250000000,R11<=500000000),750000,IF(AND(R11>500000000,R11<=1000000000),1150000,2250000)))))) -> 500000
B42: ANGSURAN PERTAMA | F42: =IF($D$6="ADDM",11,12) -> 12 | G42: =IF($D$6="ADDM",ROUNDUP(G20/G9,-3),0) -> 0 | I42: =IF($D$6="ADDM",23,24) -> 24 | J42: =IF($D$6="ADDM",ROUNDUP(J20/J9,-3),0) -> 0 | L42: =IF($D$6="ADDM",35,36) -> 36 | M42: =IF($D$6="ADDM",ROUNDUP(M20/M9,-3),0) -> 0 | O42: =IF($D$6="ADDM",47,48) -> 48 | P42: =IF($D$6="ADDM",ROUNDUP(P20/P9,-3),0) -> 0 | R42: =IF($D$6="ADDM",59,60) -> 60 | S42: =IF($D$6="ADDM",ROUNDUP(S20/S9,-3),0) -> 0
B43: TOTAL BAYAR PERTAMA | F43: =(G16+F38+G39+F40+F41+G42) -> #N/A | I43: =(J16+I38+J39+I40+I41+J42) -> #N/A | L43: =(M16+L38+M39+L40+L41+M42) -> #N/A | O43: =(P16+O38+P39+O40+O41+P42) -> #N/A | R43: =(S16+R38+S39+R40+R41+S42) -> #N/A
B44: PENCAIRAN GROSS | F44: =F11-F43 -> #N/A | I44: =I11-I43 -> #N/A | L44: =L11-L43 -> #N/A | O44: =O11-O43 -> #N/A | R44: =R11-R43 -> #N/A
B45: BBNKB | G45: =$O$5 -> 0 | J45: =$O$5 -> 0 | M45: =$O$5 -> 0 | P45: =$O$5 -> 0 | S45: =$O$5 -> 0
B46: PKB | G46: =$O$6 -> 0 | J46: =$O$6 -> 0 | M46: =$O$6 -> 0 | P46: =$O$6 -> 0 | S46: =$O$6 -> 0
B47: FAKTUR | G47: =$O$7 -> 0 | J47: =$O$7 -> 0 | M47: =$O$7 -> 0 | P47: =$O$7 -> 0 | S47: =$O$7 -> 0
B48: DEPOSIT ANGSURAN | E48: =P4 -> 0 | F48: =F21*$E$48 -> #N/A | I48: =I21*$E$48 -> #N/A | L48: =L21*$E$48 -> #N/A | O48: =O21*$E$48 -> #N/A | R48: =R21*$E$48 -> 0
B49: PECAIRAN NETO | F49: =IF(F12=0,0,(F44-(G45+G46+G47+F48))) -> #N/A | I49: =IF(I12=0,0,(I44-(J45+J46+J47+I48))) -> #N/A | L49: =IF(L12=0,0,(L44-(M45+M46+M47+L48))) -> #N/A | O49: =IF(O12=0,0,(O44-(P45+P46+P47+O48))) -> #N/A | R49: =IF(R12=0,0,(R44-(S45+S46+S47+R48))) -> 0
B51: REFUND ASURANSI | D51: 0.1 | E51: 1 | F51: =(F30*$D$51)*$E$51 -> 71500 | I51: =(I30*$D$51)*$E$51 -> 135850 | L51: =(L30*$D$51)*$E$51 -> 193050 | O51: =(O30*$D$51)*$E$51 -> 243100 | R51: =(R30*$D$51)*$E$51 -> 293150
B52: REFUND BUNGA | D52: =$S$5 -> 0.005 | E52: 0.8 | F52: =((G17*($D$52*F9))/((1+F19))*$E$52) -> #N/A | I52: =((J17*($D$52*I9))/((1+I19))*$E$52) -> #N/A | L52: =((M17*($D$52*L9))/((1+L19))*$E$52) -> #N/A | O52: =((P17*($D$52*O9))/((1+O19))*$E$52) -> #N/A | R52: =((S17*($D$52*R9))/((1+R19))*$E$52) -> #N/A
B53: REFUND PROVISI | D53: =$S$7 -> 0 | E53: 0.8 | F53: =G39*$E$53 -> #N/A | I53: =J39*$E$53 -> #N/A | L53: =M39*$E$53 -> #N/A | O53: =P39*$E$53 -> #N/A | R53: =S39*$E$53 -> #N/A
B54: REFUND ADMIN | D54: =$S$6 -> 0 | E54: 0.8 | F54: =$D$54*$E$54 -> 0 | I54: =$D$54*$E$54 -> 0 | L54: =$D$54*$E$54 -> 0 | O54: =$D$54*$E$54 -> 0 | R54: =$D$54*$E$54 -> 0
B55: TOTAL REFUND | F55: =ROUNDDOWN(SUM(F51:H54),-3) -> #N/A | I55: =ROUNDDOWN(SUM(I51:K54),-3) -> #N/A | L55: =ROUNDDOWN(SUM(L51:N54),-3) -> #N/A | O55: =ROUNDDOWN(SUM(O51:Q54),-3) -> #N/A | R55: =ROUNDDOWN(SUM(R51:T54),-3) -> #N/A
B56: PENCAIRAN ALL IN | F56: =$F$49+$F$55 -> #N/A | I56: =$I$49+$I$55 -> #N/A | L56: =$L$49+$L$55 -> #N/A | O56: =$O$49+$O$55 -> #N/A | R56: =$R$49+$R$55 -> #N/A
F58: =5913200-F38 -> 3698200
B60: TENOR | F60: 1 | G60: =F60*12 -> 12 | I60: 2 | J60: =I60*12 -> 24 | L60: 3 | M60: =L60*12 -> 36 | O60: 4 | P60: =O60*12 -> 48 | R60: 5 | S60: =R60*12 -> 60
B61: Harga Pasar | F61: =F11 -> 110000000 | I61: =I11 -> 110000000 | L61: =L11 -> 110000000 | O61: =O11 -> 110000000 | R61: =R11 -> 110000000
B62: PHPM | F62: =ROUNDDOWN(IF(F10>=1,VLOOKUP($B$10,'PHPM 1 DT Ext'!$K$5:$L$841,2,0),0),-2) -> 140000000 | I62: =ROUNDDOWN(IF(I10>=1,VLOOKUP($B$10,'PHPM 1 DT Ext'!$K$5:$L$841,2,0),0),-2) -> 140000000 | L62: =ROUNDDOWN(IF(L10>=1,VLOOKUP($B$10,'PHPM 1 DT Ext'!$K$5:$L$841,2,0),0),-2) -> 140000000 | O62: =ROUNDDOWN(IF(O10>=1,VLOOKUP($B$10,'PHPM 1 DT Ext'!$K$5:$L$841,2,0),0),-2) -> 140000000 | R62: =ROUNDDOWN(IF(R10>=1,VLOOKUP($B$10,'PHPM 1 DT Ext'!$K$5:$L$841,2,0),0),-2) -> 0
B63: Total DP | F63: ='Home Ext'!$O$75 -> 60000000 | I63: ='Home Ext'!$O$75 -> 60000000 | L63: ='Home Ext'!$O$75 -> 60000000 | O63: ='Home Ext'!$O$75 -> 60000000 | R63: ='Home Ext'!$O$75 -> 60000000
B64: TOTAL BAYAR PERTAMA | F64: =F65+F66+F67+F68 -> #N/A | I64: =I65+I66+I67+I68 -> #N/A | L64: =L65+L66+L67+L68 -> #N/A | O64: =O65+O66+O67+O68 -> #N/A | R64: =R65+R66+R67+R68 -> #N/A
C65: ASURANSI | F65: =F38 -> 2215000 | I65: =I38 -> 2858500 | L65: =L38 -> 3430500 | O65: =O38 -> 3931000 | R65: =R38 -> 4431500
C66: PROVISI | F66: =G39 -> #N/A | I66: =J39 -> #N/A | L66: =M39 -> #N/A | O66: =P39 -> #N/A | R66: =S39 -> #N/A
C67: ADMINISTRASI | F67: =F40 -> #N/A | I67: =I40 -> #N/A | L67: =L40 -> #N/A | O67: =O40 -> #N/A | R67: =R40 -> #N/A
C68: FIDUCIA | F68: =F41 -> 500000 | I68: =I41 -> 500000 | L68: =L41 -> 500000 | O68: =O41 -> 500000 | R68: =R41 -> 500000
C69: ANGSURAN PERBULAN | F69: =ROUNDUP(IF('Home Ext'!$K$33="ADDM",((F61-(F63-F64))*(1+F19))/(G9-(1+F19)),((F61-(F63-F64))*(1+F19))/G9),-3) -> #N/A | I69: =ROUNDUP(IF('Home Ext'!$K$33="ADDM",((I61-(I63-I64))*(1+I19))/(J9-(1+I19)),((I61-(I63-I64))*(1+I19))/J9),-3) -> #N/A | L69: =ROUNDUP(IF('Home Ext'!$K$33="ADDM",((L61-(L63-L64))*(1+L19))/(M9-(1+L19)),((L61-(L63-L64))*(1+L19))/M9),-3) -> #N/A | O69: =ROUNDUP(IF('Home Ext'!$K$33="ADDM",((O61-(O63-O64))*(1+O19))/(P9-(1+O19)),((O61-(O63-O64))*(1+O19))/P9),-3) -> #N/A | R69: =ROUNDUP(IF('Home Ext'!$K$33="ADDM",((R61-(R63-R64))*(1+R19))/(S9-(1+R19)),((R61-(R63-R64))*(1+R19))/S9),-3) -> #N/A
B70: DP NET | F70: =G70/F61 -> #N/A | G70: =IF('Home Ext'!$K$33="ADDM",F63-(F64+F69),F63-F64) -> #N/A | I70: =J70/I61 -> #N/A | J70: =IF('Home Ext'!$K$33="ADDM",I63-(I64+I69),I63-I64) -> #N/A | L70: =M70/L61 -> #N/A | M70: =IF('Home Ext'!$K$33="ADDM",L63-(L64+L69),L63-L64) -> #N/A | O70: =P70/O61 -> #N/A | P70: =IF('Home Ext'!$K$33="ADDM",O63-(O64+O69),O63-O64) -> #N/A | R70: =S70/R61 -> #N/A | S70: =IF('Home Ext'!$K$33="ADDM",R63-(R64+R69),R63-R64) -> #N/A
B71: LTV | F71: =IF(F70>=F16,(100%-(G70/F61)),0%) -> #N/A | G71: =F61-G70 -> #N/A | I71: =IF(I70>=I16,(100%-(J70/I61)),0%) -> #N/A | J71: =I61-J70 -> #N/A | L71: =IF(L70>=L16,(100%-(M70/L61)),0%) -> #N/A | M71: =L61-M70 -> #N/A | O71: =IF(O70>=O16,(100%-(P70/O61)),0%) -> #N/A | P71: =O61-P70 -> #N/A | R71: =IF(R70>=R16,(100%-(S70/R61)),0%) -> #N/A | S71: =R61-S70 -> #N/A
B72: BUNGA JUAL | F72: =$F$19 -> #N/A | G72: =G71*F72 -> #N/A | I72: =$I$19 -> #N/A | J72: =J71*I72 -> #N/A | L72: =$L$19 -> #N/A | M72: =M71*L72 -> #N/A | O72: =$O$19 -> #N/A | P72: =P71*O72 -> #N/A | R72: =$R$19 -> #N/A | S72: =S71*R72 -> #N/A
B73: TOTAL AR | F73: =G71+G72 -> #N/A | I73: =J71+J72 -> #N/A | L73: =M71+M72 -> #N/A | O73: =P71+P72 -> #N/A | R73: =S71+S72 -> #N/A
B74: ANGSURAN | F74: =$G$9 -> 12 | G74: =IF(F71=0%,0,ROUNDUP((G71*(1+F19))/G9,-3)) -> #N/A | I74: =$J$9 -> 24 | J74: =IF(I71=0%,0,ROUNDUP((J71*(1+I19))/J9,-3)) -> #N/A | L74: =$M$9 -> 36 | M74: =IF(L71=0%,0,ROUNDUP((M71*(1+L19))/M9,-3)) -> #N/A | O74: =$P$9 -> 48 | P74: =IF(O71=0%,0,ROUNDUP((P71*(1+O19))/P9,-3)) -> #N/A | R74: =$S$9 -> 60 | S74: =IF(R71=0%,0,ROUNDUP((S71*(1+R19))/S9,-3)) -> #N/A
B76: Pencairan All In | F76: Maksimal | J76: Total DP | N76: ='Home Ext'!$O$75 -> 60000000
B77: Tenor | E77: Pencairan | G77: Angsuran | J77: Tenor | M77: Pencairan | O77: Angsuran
B78: =$F$42 -> 12 | C78: Bulan | D78: =CONCATENATE($B$78," ",$C$78) -> 12 Bulan | E78: =IFERROR(F56,0) -> 0 | G78: =IFERROR($F$21,0) -> 0 | J78: =$F$42 -> 12 | K78: Bulan | L78: =CONCATENATE($B$78," ",$C$78) -> 12 Bulan | M78: =IFERROR('Home Ext'!$I$75,0) -> 60000000 | O78: =IFERROR($G$74,0) -> 0
B79: =$I$42 -> 24 | C79: Bulan | D79: =CONCATENATE($B$79," ",$C$79) -> 24 Bulan | E79: =IFERROR($I$56,0) -> 0 | G79: =IFERROR($I$21,0) -> 0 | J79: =$I$42 -> 24 | K79: Bulan | L79: =CONCATENATE($B$79," ",$C$79) -> 24 Bulan | M79: =IFERROR('Home Ext'!$I$75,0) -> 60000000 | O79: =IFERROR($J$74,0) -> 0
B80: =$L$42 -> 36 | C80: Bulan | D80: =CONCATENATE($B$80," ",$C$80) -> 36 Bulan | E80: =IFERROR($L$56,0) -> 0 | G80: =IFERROR($L$21,0) -> 0 | J80: =$L$42 -> 36 | K80: Bulan | L80: =CONCATENATE($B$80," ",$C$80) -> 36 Bulan | M80: =IFERROR('Home Ext'!$I$75,0) -> 60000000 | O80: =IFERROR($M$74,) -> 0
B81: =$O$42 -> 48 | C81: Bulan | D81: =CONCATENATE($B$81," ",$C$81) -> 48 Bulan | E81: =IFERROR($O$56,0) -> 0 | G81: =IFERROR($O$21,0) -> 0 | J81: =$O$42 -> 48 | K81: Bulan | L81: =CONCATENATE($B$81," ",$C$81) -> 48 Bulan | M81: =IFERROR('Home Ext'!$I$75,0) -> 60000000 | O81: =IFERROR($P$74,0) -> 0
B82: =$R$42 -> 60 | C82: Bulan | D82: =CONCATENATE($B$82," ",$C$82) -> 60 Bulan | E82: =IFERROR($R$56,0) -> 0 | G82: =IFERROR($R$21,0) -> 0 | J82: =$R$42 -> 60 | K82: Bulan | L82: =CONCATENATE($B$82," ",$C$82) -> 60 Bulan | M82: =IFERROR('Home Ext'!$I$75,0) -> 60000000 | O82: =IFERROR($S$74,0) -> 0
F85: =F49 -> #N/A
F86: =I49 -> #N/A
F87: =L49 -> #N/A
F88: =O49 -> #N/A
F89: =R49 -> 0

Sheet Asr Ext
C2: Wilayah 2
B3: OTR | C3: BATAS ATAS | G3: BATAS BAWAH | L3: LOADING ASURANSI
C4: Passenger | E4: Commercial | G4: Passenger | I4: Commercial
C5: Comprehensive | D5: TLO | E5: Comprehensive | F5: TLO | G5: Comprehensive | H5: TLO | I5: Comprehensive | J5: TLO
B6: 0-125 | C6: 0.0359 | D6: 0.0078 | E6: 0.0369 | F6: 0.0085 | G6: 0.0326 | H6: 0.0065 | I6: 0.0336 | J6: 0.0072 | L6: 2026 | M6: 0 | N6: 0 | O6: Comprehensive
B7: >125-200 | C7: 0.0272 | D7: 0.0053 | E7: 0.0282 | F7: 0.0057 | G7: 0.0247 | H7: 0.0044 | I7: 0.0257 | J7: 0.0048 | L7: =L6-1 -> 2025 | M7: 1 | N7: 0 | O7: Comprehensive
B8: >200-400 | C8: 0.0229 | D8: 0.0042 | E8: 0.0239 | F8: 0.0045 | G8: 0.0208 | H8: 0.0038 | I8: 0.0218 | J8: 0.0041 | L8: =L7-1 -> 2024 | M8: 2 | N8: 0 | O8: Comprehensive
B9: >400-800 | C9: 0.0132 | D9: 0.003 | E9: 0.0142 | F9: 0.0033 | G9: 0.012 | H9: 0.0025 | I9: 0.013 | J9: 0.0028 | L9: =L8-1 -> 2023 | M9: 3 | N9: 0 | O9: Comprehensive
B10: >800 | C10: 0.0116 | D10: 0.0024 | E10: 0.0126 | F10: 0.0026 | G10: 0.0105 | H10: 0.002 | I10: 0.0115 | J10: 0.0022 | L10: =L9-1 -> 2022 | M10: 4 | N10: 0 | O10: Comprehensive
L11: =L10-1 -> 2021 | M11: 5 | N11: 0 | O11: Comprehensive
B12: ='Home Ext'!$I$17 -> Passenger | C12: BATAS ATAS | E12: BATAS BAWAH | L12: =L11-1 -> 2020 | M12: 6 | N12: 0.05 | O12: Comprehensive Loading
C13: Comprehensive | D13: TLO | E13: Comprehensive | F13: TLO | L13: =L12-1 -> 2019 | M13: 7 | N13: 0.1 | O13: Comprehensive Loading
B14: 0-125 | C14: =IF($B$12="Passenger",C6,E6) -> 0.0359 | D14: =IF($B$12="Passenger",D6,F6) -> 0.0078 | E14: =IF($B$12="Passenger",G6,I6) -> 0.0326 | F14: =IF($B$12="Passenger",H6,J6) -> 0.0065 | L14: =L13-1 -> 2018 | M14: 8 | N14: 0.15 | O14: Comprehensive Loading
B15: >125-200 | C15: =IF($B$12="Passenger",C7,E7) -> 0.0272 | D15: =IF($B$12="Passenger",D7,F7) -> 0.0053 | E15: =IF($B$12="Passenger",G7,I7) -> 0.0247 | F15: =IF($B$12="Passenger",H7,J7) -> 0.0044 | L15: =L14-1 -> 2017 | M15: 9 | N15: 0.2 | O15: Comprehensive Loading
B16: >200-400 | C16: =IF($B$12="Passenger",C8,E8) -> 0.0229 | D16: =IF($B$12="Passenger",D8,F8) -> 0.0042 | E16: =IF($B$12="Passenger",G8,I8) -> 0.0208 | F16: =IF($B$12="Passenger",H8,J8) -> 0.0038 | L16: =L15-1 -> 2016 | M16: 10 | N16: 0.25 | O16: Comprehensive Loading
B17: >400-800 | C17: =IF($B$12="Passenger",C9,E9) -> 0.0132 | D17: =IF($B$12="Passenger",D9,F9) -> 0.003 | E17: =IF($B$12="Passenger",G9,I9) -> 0.012 | F17: =IF($B$12="Passenger",H9,J9) -> 0.0025 | L17: =L16-1 -> 2015 | M17: 11 | N17: 0
B18: >800 | C18: =IF($B$12="Passenger",C10,E10) -> 0.0116 | D18: =IF($B$12="Passenger",D10,F10) -> 0.0024 | E18: =IF($B$12="Passenger",G10,I10) -> 0.0105 | F18: =IF($B$12="Passenger",H10,J10) -> 0.002 | L18: =L17-1 -> 2014 | M18: 12 | N18: 0
L19: =L18-1 -> 2013 | M19: 13 | N19: 0
B20: =B12 -> Passenger | C20: ='DT Ext'!O8 -> BATAS BAWAH | L20: =L19-1 -> 2012 | M20: 14 | N20: 0
C21: Compre | D21: TLO
B22: 0-125 | C22: =IF($C$20="BATAS BAWAH",E14,C14) -> 0.0326 | D22: =IF($C$20="BATAS BAWAH",F14,D14) -> 0.0065
B23: >125-200 | C23: =IF($C$20="BATAS BAWAH",E15,C15) -> 0.0247 | D23: =IF($C$20="BATAS BAWAH",F15,D15) -> 0.0044
B24: >200-400 | C24: =IF($C$20="BATAS BAWAH",E16,C16) -> 0.0208 | D24: =IF($C$20="BATAS BAWAH",F16,D16) -> 0.0038
B25: >400-800 | C25: =IF($C$20="BATAS BAWAH",E17,C17) -> 0.012 | D25: =IF($C$20="BATAS BAWAH",F17,D17) -> 0.0025
B26: >800 | C26: =IF($C$20="BATAS BAWAH",E18,C18) -> 0.0105 | D26: =IF($C$20="BATAS BAWAH",F18,D18) -> 0.002
H28: TJH PEMBIAYAAN MOBIL BEKAS
B29: TENOR | C29: ACP BOTTOM | D29: UPPING | E29: ACP JUAL | H29: TJH NON KOMERSIAL | M29: TJH RUPIAH
B31: 12 | C31: =$D$70 -> 0.0065 | D31: =#REF! -> #REF! | E31: =C31+(C31*D31) -> #REF! | G31: 1 | H31: =IF('UC Ext'!$D$33>25000000,25000000,'UC Ext'!$D$33) -> 0 | I31: =IF('UC Ext'!$D$33>50000000,25000000,'UC Ext'!$D$33-H31) -> 0 | J31: =IF('UC Ext'!$D$33>50000000,25000000,'UC Ext'!$D$33-H31-I31) -> 0 | K31: ='UC Ext'!$D$33-H31-I31-J31 -> 0 | M31: =(H31*0.01)+(I31*0.005)+(J31*0.0025)+(K31*0.0015) -> 0
B32: 24 | C32: =$E$70 -> 0.013 | D32: =#REF! -> #REF! | E32: =C32+(C32*D32) -> #REF! | G32: 2 | H32: =IF('UC Ext'!$D$33>25000000,25000000,'UC Ext'!$D$33) -> 0 | I32: =IF('UC Ext'!$D$33>50000000,25000000,'UC Ext'!$D$33-H32) -> 0 | J32: =IF('UC Ext'!$D$33>50000000,25000000,'UC Ext'!$D$33-H32-I32) -> 0 | K32: ='UC Ext'!$D$33-H32-I32-J32 -> 0 | M32: =(H32*0.01)+(I32*0.005)+(J32*0.0025)+(K32*0.0015) -> 0
B33: 36 | C33: =$F$70 -> 0.01989 | D33: =#REF! -> #REF! | E33: =C33+(C33*D33) -> #REF! | G33: 3 | H33: =IF('UC Ext'!$D$33>25000000,25000000,'UC Ext'!$D$33) -> 0 | I33: =IF('UC Ext'!$D$33>50000000,25000000,'UC Ext'!$D$33-H33) -> 0 | J33: =IF('UC Ext'!$D$33>50000000,25000000,'UC Ext'!$D$33-H33-I33) -> 0 | K33: ='UC Ext'!$D$33-H33-I33-J33 -> 0 | M33: =(H33*0.01)+(I33*0.005)+(J33*0.0025)+(K33*0.0015) -> 0
B34: 48 | C34: =$G$70 -> 0.02912 | D34: =#REF! -> #REF! | E34: =C34+(C34*D34) -> #REF! | G34: 4 | H34: =IF('UC Ext'!$D$33>25000000,25000000,'UC Ext'!$D$33) -> 0 | I34: =IF('UC Ext'!$D$33>50000000,25000000,'UC Ext'!$D$33-H34) -> 0 | J34: =IF('UC Ext'!$D$33>50000000,25000000,'UC Ext'!$D$33-H34-I34) -> 0 | K34: ='UC Ext'!$D$33-H34-I34-J34 -> 0 | M34: =(H34*0.01)+(I34*0.005)+(J34*0.0025)+(K34*0.0015) -> 0
G35: 5 | H35: =IF('UC Ext'!$D$33>25000000,25000000,'UC Ext'!$D$33) -> 0 | I35: =IF('UC Ext'!$D$33>50000000,25000000,'UC Ext'!$D$33-H35) -> 0 | J35: =IF('UC Ext'!$D$33>50000000,25000000,'UC Ext'!$D$33-H35-I35) -> 0 | K35: ='UC Ext'!$D$33-H35-I35-J35 -> 0 | M35: =(H35*0.01)+(I35*0.005)+(J35*0.0025)+(K35*0.0015) -> 0 | X35: =IF(#REF!="COMPRE",1,0)+#REF! -> #REF! | Y35: =IF(#REF!="TLO",1,0)+#REF! -> #REF!
C37: RATE ACP BARU 2025 | H37: TJH DANA TUNAI
C38: 1 | D38: 2 | E38: 3 | F38: 4 | H38: TJH NON KOMERSIAL | M38: TJH RUPIAH
C39: 18-35th | D39: 36-45th | E39: 46-50th | F39: 51-60th
B40: 1 | C40: 0.005 | D40: 0.005 | E40: 0.005 | F40: 0.005 | G40: 1 | H40: =IF('DT Ext'!$D$33>25000000,25000000,'DT Ext'!$D$33) -> 0 | I40: =IF('DT Ext'!$D$33>50000000,25000000,'DT Ext'!$D$33-H40) -> 0 | J40: =IF('DT Ext'!$D$33>50000000,25000000,'DT Ext'!$D$33-H40-I40) -> 0 | K40: ='DT Ext'!$D$33-H40-I40-J40 -> 0 | M40: =(H40*0.01)+(I40*0.005)+(J40*0.0025)+(K40*0.0015) -> 0
B41: =B40+1 -> 2 | C41: 0.005 | D41: 0.005 | E41: 0.005 | F41: 0.005 | G41: 2 | H41: =IF('DT Ext'!D33>25000000,25000000,'DT Ext'!D33) -> 0 | I41: =IF('DT Ext'!$D$33>50000000,25000000,'DT Ext'!$D$33-H41) -> 0 | J41: =IF('DT Ext'!$D$33>50000000,25000000,'DT Ext'!$D$33-H41-I41) -> 0 | K41: ='DT Ext'!$D$33-H41-I41-J41 -> 0 | M41: =(H41*0.01)+(I41*0.005)+(J41*0.0025)+(K41*0.0015) -> 0
B42: =B41+1 -> 3 | C42: 0.0053 | D42: 0.0053 | E42: 0.0053 | F42: 0.0053 | G42: 3 | H42: =IF('DT Ext'!$D$33>25000000,25000000,'DT Ext'!$D$33) -> 0 | I42: =IF('DT Ext'!$D$33>50000000,25000000,'DT Ext'!$D$33-H42) -> 0 | J42: =IF('DT Ext'!$D$33>50000000,25000000,'DT Ext'!$D$33-H42-I42) -> 0 | K42: ='DT Ext'!$D$33-H42-I42-J42 -> 0 | M42: =(H42*0.01)+(I42*0.005)+(J42*0.0025)+(K42*0.0015) -> 0
B43: =B42+1 -> 4 | C43: 0.0071 | D43: 0.0071 | E43: 0.0071 | F43: 0.0071 | G43: 4 | H43: =IF('DT Ext'!$D$33>25000000,25000000,'DT Ext'!$D$33) -> 0 | I43: =IF('DT Ext'!$D$33>50000000,25000000,'DT Ext'!$D$33-H43) -> 0 | J43: =IF('DT Ext'!$D$33>50000000,25000000,'DT Ext'!$D$33-H43-I43) -> 0 | K43: ='DT Ext'!$D$33-H43-I43-J43 -> 0 | M43: =(H43*0.01)+(I43*0.005)+(J43*0.0025)+(K43*0.0015) -> 0
B44: =B43+1 -> 5 | C44: 0.0064 | D44: 0.0064 | E44: 0.0064 | F44: 0.0064 | G44: 5 | H44: =IF('DT Ext'!$D$33>25000000,25000000,'DT Ext'!$D$33) -> 0 | I44: =IF('DT Ext'!$D$33>50000000,25000000,'DT Ext'!$D$33-H44) -> 0 | J44: =IF('DT Ext'!$D$33>50000000,25000000,'DT Ext'!$D$33-H44-I44) -> 0 | K44: ='DT Ext'!$D$33-H44-I44-J44 -> 0 | M44: =(H44*0.01)+(I44*0.005)+(J44*0.0025)+(K44*0.0015) -> 0
B45: =B44+1 -> 6 | C45: 0.0053 | D45: 0.0053 | E45: 0.0053 | F45: 0.0053
H46: TJH | I46: Pengemudi | J46: Penumpang | K46: Jml Penumpang
H47: 0 | I47: 0 | J47: 0 | K47: 0
H48: 5000000 | I48: 10000000 | J48: 10000000 | K48: 4
H49: 10000000
H50: 15000000
H51: 20000000
H52: 25000000
H53: 30000000
H54: 35000000
H55: 40000000
H56: 45000000
H57: 50000000
C60: 18-35 tahun | D60: 36-45 tahun | E60: 46-50 tahun | F60: 51-60 tahun
B61: 1 | C61: 0.0044 | D61: 0.005 | E61: 0.0062 | F61: 0.007
B62: 2 | C62: 0.0086 | D62: 0.01 | E62: 0.0124 | F62: 0.015
B63: 3 | C63: 0.0131 | D63: 0.0153 | E63: 0.0189 | F63: 0.023
B64: 4 | C64: 0.0194 | D64: 0.0224 | E64: 0.0255 | F64: 0.031
B65: 5 | C65: 0.0249 | D65: 0.0288 | E65: 0.0322 | F65: 0.04
B66: 6 | C66: 0.0307 | D66: 0.0341 | E66: 0.0392 | F66: 0.05
C67: 0.0055
B68: Dana Tunai | J68: Used Car
B69: RATE ACP | D69: 1 | E69: 2 | F69: 3 | G69: 4 | H69: 5 | J69: RATE ACP | L69: 1 | M69: 2 | N69: 3 | O69: 4 | P69: 5
B70: ='DT Ext'!$S$4 -> 0.3 | C70: 18-35 tahun | D70: =$D$61+($D$61*B70) -> 0.0065 | E70: =$D$62+($D$62*B70) -> 0.013 | F70: =$D$63+($D$63*B70) -> 0.01989 | G70: =$D$64+($D$64*B70) -> 0.02912 | H70: =$D$65+($D$65*B70) -> 0.03744 | J70: ='UC Ext'!$S$4 -> 0 | K70: 18-35 tahun | L70: =$D$61+($D$61*J70) -> 0.005 | M70: =$D$62+($D$62*J70) -> 0.01 | N70: =$D$63+($D$63*J70) -> 0.0153 | O70: =$D$64+($D$64*J70) -> 0.0224 | P70: =$D$65+($D$65*J70) -> 0.0288
B71: ='DT Ext'!$S$4 -> 0.3 | C71: 36-45 tahun | D71: =$D$61+($D$61*B71) -> 0.0065 | E71: =$D$62+($D$62*B71) -> 0.013 | F71: =$D$63+($D$63*B71) -> 0.01989 | G71: =$D$64+($D$64*B71) -> 0.02912 | H71: =$D$65+($D$65*B71) -> 0.03744 | J71: ='UC Ext'!$S$4 -> 0 | K71: 36-45 tahun | L71: =$D$61+($D$61*J71) -> 0.005 | M71: =$D$62+($D$62*J71) -> 0.01 | N71: =$D$63+($D$63*J71) -> 0.0153 | O71: =$D$64+($D$64*J71) -> 0.0224 | P71: =$D$65+($D$65*J71) -> 0.0288
B72: ='DT Ext'!$S$4 -> 0.3 | C72: 46-50 tahun | D72: =$D$61+($D$61*B72) -> 0.0065 | E72: =$D$62+($D$62*B72) -> 0.013 | F72: =$D$63+($D$63*B72) -> 0.01989 | G72: =$D$64+($D$64*B72) -> 0.02912 | H72: =$D$65+($D$65*B72) -> 0.03744 | J72: ='UC Ext'!$S$4 -> 0 | K72: 46-50 tahun | L72: =$D$61+($D$61*J72) -> 0.005 | M72: =$D$62+($D$62*J72) -> 0.01 | N72: =$D$63+($D$63*J72) -> 0.0153 | O72: =$D$64+($D$64*J72) -> 0.0224 | P72: =$D$65+($D$65*J72) -> 0.0288
B73: 0.8 | C73: 51-60 tahun | D73: =$D$61+($D$61*B73) -> 0.009 | E73: =$D$62+($D$62*B73) -> 0.018 | F73: =$D$63+($D$63*B73) -> 0.02754 | G73: =$D$64+($D$64*B73) -> 0.04032 | H73: =$D$65+($D$65*B73) -> 0.05184 | J73: 0.8 | K73: 51-60 tahun | L73: =$D$61+($D$61*J73) -> 0.009 | M73: =$D$62+($D$62*J73) -> 0.018 | N73: =$D$63+($D$63*J73) -> 0.02754 | O73: =$D$64+($D$64*J73) -> 0.04032 | P73: =$D$65+($D$65*J73) -> 0.05184

Sheet Product
B3: 1 | C3: =B3+1 -> 2 | D3: =C3+1 -> 3 | E3: =D3+1 -> 4 | F3: =E3+1 -> 5 | G3: =F3+1 -> 6 | H3: =G3+1 -> 7 | I3: =H3+1 -> 8 | J3: =I3+1 -> 9 | K3: =J3+1 -> 10
A5: No | C5: 12 | D5: =C5+12 -> 24 | E5: =D5+12 -> 36 | F5: =E5+12 -> 48 | G5: =F5+12 -> 60 | H5: DP | I5: Admin Minimal | J5: Admin Maksimal | K5: Provisi
A6: 1 | B6: Captive Passenger Khusus Karyawan Bank Mandiri | C6: 0.1026 | D6: 0.0966 | E6: 0.0939 | F6: 0.0966 | G6: 0.1037 | H6: 0.05 | I6: 3500000 | J6: 4400000 | K6: 0
A7: 2 | B7: Captive Passenger Khusus SME & Private/Prioritas | C7: 0.1374 | D7: 0.1345 | E7: 0.135 | F7: 0.1497 | G7: 0.1589 | H7: 0.05 | I7: 3500000 | J7: 4400000 | K7: 0
A8: 3 | B8: Captive Passenger Semangat | C8: 0.1688 | D8: 0.1636 | E8: 0.1629 | F8: 0.1762 | G8: 0.1804 | H8: 0.05 | I8: 3500000 | J8: 4400000 | K8: 0
A9: 4 | B9: Captive Passenger Tengah | C9: 0.1769 | D9: 0.1685 | E9: 0.1697 | F9: 0.1784 | G9: 0.1865 | H9: 0.05 | I9: 3500000 | J9: 4400000 | K9: 0
A10: 5 | B10: Captive Passenger Cuan | C10: 0.1847 | D10: 0.1733 | E10: 0.1766 | F10: 0.1805 | G10: 0.1926 | H10: 0.05 | I10: 3500000 | J10: 4400000 | K10: 0
A11: 6 | B11: Captive Commercial Semangat | C11: 0.1983 | D11: 0.1907 | E11: 0.1931 | F11: 0.1921 | H11: 0.15 | I11: 3500000 | J11: 4400000 | K11: 0
A12: 7 | B12: Captive Commercial Tengah | C12: 0.2035 | D12: 0.1979 | E12: 0.1999 | F12: 0.1981 | H12: 0.15 | I12: 3500000 | J12: 4400000 | K12: 0
A13: 8 | B13: Captive Commercial Cuan | C13: 0.2088 | D13: 0.205 | E13: 0.2065 | F13: 0.2039 | H13: 0.15 | I13: 3500000 | J13: 4400000 | K13: 0
A14: 9 | B14: Reguler Passenger Referral | C14: 0.17253 | D14: 0.175 | E14: 0.18 | F14: 0.1869 | G14: 0.1907 | H14: 0.05 | I14: 3750000 | J14: 5350000 | K14: 0
A15: 10 | B15: Reguler Passenger TOMI Spesial Referral | C15: 0.1 | D15: 0.1025 | E15: 0.105 | F15: 0.1075 | G15: 0.11 | H15: 0.05 | I15: 3750000 | J15: 5350000 | K15: 0
A16: 11 | B16: Reguler Commercial Referral | C16: 0.2035 | D16: 0.1955 | E16: 0.1976 | F16: 0.1963 | H16: 0.15 | I16: 3750000 | J16: 5350000 | K16: 0
A17: 12 | B17: Reguler Passenger Sales Dealer | C17: 0.1847 | D17: 0.1733 | E17: 0.1766 | F17: 0.1805 | G17: 0.1926 | H17: 0.15 | I17: 3500000 | J17: 5350000 | K17: 0
A18: 13 | B18: Reguler Commercial Sales Dealer | C18: 0.2088 | D18: 0.205 | E18: 0.2065 | F18: 0.2039 | H18: 0.15 | I18: 3500000 | J18: 5350000 | K18: 0
A19: 14 | B19: Captive Passenger Authorized Showroom | C19: 0.14 | D19: 0.14 | E19: 0.14 | F19: 0.16 | G19: 0.16 | H19: 0.2 | I19: 4700000 | J19: 4700000 | K19: 0
A20: 15 | B20: Captive Passenger Low Rate | C20: 0.144699 | D20: 0.1468 | E20: 0.1455 | F20: 0.1623 | G20: 0.165 | H20: 0.1 | I20: 4700000 | J20: 4700000 | K20: 0
A21: 16 | B21: Captive Passenger Authorized Reguler | C21: 0.1622 | D21: 0.1643 | E21: 0.1624 | F21: 0.1751 | G21: 0.1766 | H21: 0.1 | I21: 4700000 | J21: 4700000 | K21: 0
A22: 17 | B22: Captive Passenger High Benefit | C22: 0.1797 | D22: 0.1816 | E22: 0.1792 | F22: 0.1943 | G22: 0.1918 | H22: 0.1 | I22: 4700000 | J22: 4700000 | K22: 0
A23: 18
A24: 19
A25: 20
B28: KONVERSI RATE
B29: ADDB | C29: =VLOOKUP($B$30,$B$6:$G$24,2,0) -> 0.1026 | D29: 0.12 | E29: =VLOOKUP($B$30,$B$6:$G$24,4,0) -> 0.0939 | F29: =VLOOKUP($B$30,$B$6:$G$24,5,0) -> 0.0966 | G29: =VLOOKUP($B$30,$B$6:$G$24,6,0) -> 0.1037
B30: Captive Passenger Khusus Karyawan Bank Mandiri | C30: =IF($B$29="ADDM",(((PMT($C$29/12,$C$5,1,0,1)*(-1))*$C$5)-1)*12/$C$5,IF($B$29="ADDB",(((PMT($C$29/12,$C$5,1,0,0)*(-1))*$C$5)-1)*12/$C$5," ")) -> 0.056442283 | D30: =IF($B$29="ADDM",(((PMT($D$29/12,$D$5,1,0,1)*(-1))*$D$5)-1)*12/$D$5,IF($B$29="ADDB",(((PMT($D$29/12,$D$5,1,0,0)*(-1))*$D$5)-1)*12/$D$5," ")) -> 0.064881667 | E30: =IF($B$29="ADDM",(((PMT($E$29/12,$E$5,1,0,1)*(-1))*$E$5)-1)*12/$E$5,IF($B$29="ADDB",(((PMT($E$29/12,$E$5,1,0,0)*(-1))*$E$5)-1)*12/$E$5," ")) -> 0.050445319 | F30: =IF($B$29="ADDM",(((PMT($F$29/12,$F$5,1,0,1)*(-1))*$F$5)-1)*12/$F$5,IF($B$29="ADDB",(((PMT($F$29/12,$F$5,1,0,0)*(-1))*$F$5)-1)*12/$F$5," ")) -> 0.052395351 | G30: =IF($B$29="ADDM",(((PMT($G$29/12,$G$5,1,0,1)*(-1))*$G$5)-1)*12/$G$5,IF($B$29="ADDB",(((PMT($G$29/12,$G$5,1,0,0)*(-1))*$G$5)-1)*12/$G$5," ")) -> 0.057154688

Sheet Data Ext
M2: REFERRAL | T2: Karyawan Perbankan | U2: Sales Dealer | V2: Karyawan Mandiri Cabang | W2: Karyawan Multifinance | X2: Karyawan Asuransi | Y2: Area Kyai Tapa | Z2: Area Daan Mogot | AA2: Area Green Ville | AC2: Graha Sultan
I3: ='Home Ext'!$C$91 -> Captive External | K3: ='Home Ext'!$C$93 -> SME & Private/Prioritas | M3: 1 | N3: 2 | O3: 3 | P3: 4 | Q3: 5 | R3: 6
C4: Referral | I4: =IF($I$3="Showroom Mobil Bekas",1,IF($I$3="Karyawan Internal",2,IF($I$3="Captive Internal",3,IF($I$3="Captive External",4,IF($I$3="Wira Agency Retail",5,IF($I$3="Wira Bisnis",6,0)))))) -> 4 | K4: =IF($K$3="Karyawan Perbankan",1,IF($K$3="Karyawan Authorized Dealer",2,IF($K$3="Karyawan Koperasi",3,IF($K$3="Karyawan Multifinance",4,IF($K$3="Karyawan Asuransi Rekanan",5,IF($K$3="Area Kyai Tapa",6,IF($K$3="Area Daan Mogot",7,IF($K$3="Area Green Ville",8,IF($K$3="Karyawan (Internal)",9,IF($K$3="Graha Sultan",10,0)))))))))) -> 0 | M4: Showroom Mobil Bekas | N4: Karyawan Internal | O4: Captive Internal | P4: Captive External | Q4: Wira Agency Retail | R4: Wira Bisnis | T4: 1 | U4: 2 | V4: 3 | W4: 4 | X4: 5 | Y4: 6 | Z4: 7 | AA4: 8 | AB4: 9 | AC4: 10
B5: 1 | C5: Showroom Mobil Bekas | D5: Reguler | E5: External | F5: Referral C2C | H5: 1 | I5: =IFERROR(HLOOKUP($I$4,$M$3:$R$22,H5+2,0),0) -> Area Kyai Tapa | J5: 1 | K5: =IF($I$3="Karyawan MTF","Kantor Cabang",IFERROR(HLOOKUP($K$4,$T$4:$AE$28,1+H5,0)," ")) | M5: Bursa Otomotif Sunter | N5: Pemegang WMK | O5: Area Kyai Tapa | P5: Area Kyai Tapa | Q5: Karyawan Perbankan | R5: Akasha | S5: 1 | T5: BCA | U5: Aion | W5: ACC | X5: AAB | Y5: Jakarta Kyai Tapa | Z5: Jakarta Daan Mogot | AA5: Jakarta Green Ville | AC5: Team A
B6: 2 | C6: Karyawan Internal | D6: Reguler | E6: Internal | F6: Referral | H6: 2 | I6: =IFERROR(HLOOKUP($I$4,$M$3:$R$22,H6+2,0),0) -> Area Green Ville | J6: 2 | K6: =IF($I$3="Karyawan MTF","Kantor Cabang",IFERROR(HLOOKUP($K$4,$T$4:$AE$28,1+H6,0)," ")) | M6: Bursa Otomotif Mall Glodok Kemayoran | N6: Team Operation | O6: Area Green Ville | P6: Area Green Ville | Q6: Karyawan Authorized Dealer | R6: Carsindo | S6: 2 | T6: BNI | U6: BMW | W6: ADIRA Finance | X6: ABDA | Y6: BMP Jakarta Kyai Tapa | Z6: BMP Jakarta Daan Mogot | AA6: Jakarta Gedung Pusri | AC6: Team B
B7: 3 | C7: Captive Internal | D7: Captive | E7: Internal | F7: Khusus Karyawan Bank Mandiri | H7: 3 | I7: =IFERROR(HLOOKUP($I$4,$M$3:$R$22,H7+2,0),0) -> Area Daan Mogot | J7: 3 | K7: =IF($I$3="Karyawan MTF","Kantor Cabang",IFERROR(HLOOKUP($K$4,$T$4:$AE$28,1+H7,0)," ")) | M7: Bursa Otomotif Mangga Dua Square | N7: Team AR | O7: Area Daan Mogot | P7: Area Daan Mogot | Q7: Karyawan Koperasi | R7: Empower | S7: 3 | T7: BRI | U7: BYD | W7: BCA Finance | X7: ACA | Y7: Jakarta Jelambar | Z7: Jakarta Cengkareng Pasar Ganefo (dh Jakarta Kalideres) | AA7: Jakarta AKR Gallery West (dh Jakarta Jalan Panjang) | AC7: Team C
B8: 4 | C8: Captive External | D8: Captive | E8: External | F8: =IF('Home Ext'!$C$93="SME & Private/Prioritas","Khusus SME & Private/Prioritas","Semangat") -> Khusus SME & Private/Prioritas | H8: 4 | I8: =IFERROR(HLOOKUP($I$4,$M$3:$R$22,H8+2,0),0) -> SME & Private/Prioritas | J8: 4 | K8: =IF($I$3="Karyawan MTF","Kantor Cabang",IFERROR(HLOOKUP($K$4,$T$4:$AE$28,1+H8,0)," ")) | M8: Bursa Otomotif Pasar Mobil Kemayoran | N8: Team Credit Risk | P8: =IF(J3="captive Internal"," ","SME & Private/Prioritas") -> SME & Private/Prioritas | Q8: Karyawan Multifinance | R8: Favorite | S8: 4 | T8: BSI | U8: Chery | W8: BFI Finance | X8: ADIRA | Y8: Jakarta Latumeten | Z8: Jakarta Puri Indah | AA8: Jakarta Slipi Jaya | AC8: Team D
B9: 5 | C9: Wira Agency Retail | D9: Reguler | E9: Agency | F9: Sales Dealer | H9: 5 | I9: =IFERROR(HLOOKUP($I$4,$M$3:$R$22,H9+2,0),0) -> 0 | J9: 5 | K9: =IF($I$3="Karyawan MTF","Kantor Cabang",IFERROR(HLOOKUP($K$4,$T$4:$AE$28,1+H9,0)," ")) | M9: Bursa Otomotif WTC Mangga Dua | N9: Graha Sultan | Q9: Karyawan Asuransi Rekanan | R9: FinGo | S9: 5 | T9: BTN | U9: Daihatsu | W9: BNI Finance | X9: ARINDO | Y9: Jakarta Grogol Muwardi | Z9: Jakarta Taman Palem Lestari | AA9: Jakarta Kemanggisan
B10: 6 | C10: Wira Bisnis | D10: Reguler | E10: External | F10: Referral | H10: 6 | I10: =IFERROR(HLOOKUP($I$4,$M$3:$R$22,H10+2,0),0) -> 0 | J10: 6 | K10: =IF($I$3="Karyawan MTF","Kantor Cabang",IFERROR(HLOOKUP($K$4,$T$4:$AE$28,1+H10,0)," ")) | M10: Bursa Otomotif Season City | R10: Good | S10: 6 | T10: BUKOPIN | U10: DFSK | W10: BRI Finance | X10: AWT | Y10: Jakarta Jelambar Baru | Z10: Jakarta Taman Semanan Indah | AA10: Jakarta Rawa Belong
B11: 7 | C11: Others | D11: Reguler | E11: External | F11: Referral | H11: 7 | I11: =IFERROR(HLOOKUP($I$4,$M$3:$R$22,H11+2,0),0) -> 0 | J11: 7 | K11: =IF($I$3="Karyawan MTF","Kantor Cabang",IFERROR(HLOOKUP($K$4,$T$4:$AE$28,1+H11,0)," ")) | M11: Bursa Otomotif Blok M | R11: Goona | S11: 7 | T11: CIMB NIAGA | U11: Hino | W11: CIMB Niaga Finance | X11: BESS | Y11: Jakarta Taman Duta Mas | Z11: Jakarta Daan Mogot Baru | AA11: Jakarta Taman Kebon Jeruk
H12: 8 | I12: =IFERROR(HLOOKUP($I$4,$M$3:$R$22,H12+2,0),0) -> 0 | J12: 8 | K12: =IF($I$3="Karyawan MTF","Kantor Cabang",IFERROR(HLOOKUP($K$4,$T$4:$AE$28,1+H12,0)," ")) | M12: Bursa Otomotif ITC Permata Hijau | R12: Pinjam Bagus | S12: 8 | T12: DANAMON | U12: Honda | W12: Clipan Finance | X12: CAKRAWALA | Y12: Jakarta Tomang | Z12: Jakarta Mal Puri Indah | AA12: Jakarta Kebon Jeruk Perjuangan
H13: 9 | I13: =IFERROR(HLOOKUP($I$4,$M$3:$R$22,H13+2,0),0) -> 0 | J13: 9 | K13: =IF($I$3="Karyawan MTF","Kantor Cabang",IFERROR(HLOOKUP($K$4,$T$4:$AE$28,1+H13,0)," ")) | M13: Bursa Otomotif Bintaro | R13: Porto | S13: 9 | T13: KEB HANA | U13: Hyundai | W13: Dipo Star Finance | X13: KRESNA | Y13: Jakarta R.S. Royal Taruma | Z13: Jakarta Puri Kencana | AA13: BMP Jakarta Kebon Jeruk
C14: ='Home Ext'!$C$149 -> Dana Tunai | E14: =IF(OR(C14="Dana Tunai",C14="Pembelian Mobil Bekas"),"Comprehensive 1 Tahun","Comprehensive All Tenor") -> Comprehensive 1 Tahun | H14: 10 | I14: =IFERROR(HLOOKUP($I$4,$M$3:$R$22,H14+2,0),0) -> 0 | J14: 10 | K14: =IF($I$3="Karyawan MTF","Kantor Cabang",IFERROR(HLOOKUP($K$4,$T$4:$AE$28,1+H14,0)," ")) | M14: Bursa Otomotif Serpong Summarecon | R14: Semesta | S14: 10 | T14: MAY BANK | U14: Isuzu | W14: FIF | X14: MAG | Y14: Jakarta Universitas Trisakti | Z14: Jakarta Citra Garden | AA14: Jakarta Kebon Jeruk
B15: 1 | C15: =IF(C14="Pembiayaan Emas / Logam Mulia","","Simulasi Kredit") -> Simulasi Kredit | E15: TLO All Tenor | H15: 11 | I15: =IFERROR(HLOOKUP($I$4,$M$3:$R$22,H15+2,0),0) -> 0 | J15: 11 | K15: =IF($I$3="Karyawan MTF","Kantor Cabang",IFERROR(HLOOKUP($K$4,$T$4:$AE$28,1+H15,0)," ")) | M15: Cluster Fatmawati | R15: Soehu | S15: 11 | T15: MAYAPADA | U15: Kia | W15: Kredit Plus | X15: MEGA | Y15: Jakarta Universitas Tarumanegara | Z15: Jakarta Palem City | AA15: Jakarta Taman Aries
B16: 2 | C16: Tracking Proses Approval Credit | H16: 12 | I16: =IFERROR(HLOOKUP($I$4,$M$3:$R$22,H16+2,0),0) -> 0 | J16: 12 | K16: =IF($I$3="Karyawan MTF","Kantor Cabang",IFERROR(HLOOKUP($K$4,$T$4:$AE$28,1+H16,0)," ")) | M16: Cluster Pondok Indah | R16: Taktis | S16: 12 | T16: MEGA | U16: Lexus | W16: May Bank Finance | X16: MNC | Y16: Jakarta KS Tubun (dh Jakarta R.S. Pelni) | Z16: Jakarta Ciputra Internasional | AA16: Jakarta Kelapa Dua (dh Jkt Kepa Duri)
B17: 3 | C17: =IF(C14="Pembiayaan Emas / Logam Mulia","Tabel Angsuran","") | H17: 13 | I17: =IFERROR(HLOOKUP($I$4,$M$3:$R$22,H17+2,0),0) -> 0 | J17: 13 | K17: =IF($I$3="Karyawan MTF","Kantor Cabang",IFERROR(HLOOKUP($K$4,$T$4:$AE$28,1+H17,0)," ")) | S17: 13 | T17: MUAMALAT | U17: Mazda | W17: Mega Finance | X17: MPM | Y17: Jakarta R.S. Harapan Kita | Z17: Jakarta Botanical Garden | AA17: Jakarta Kedoya
B18: 4 | C18: Actual Lending AO | H18: 14 | J18: 14 | K18: =IF($I$3="Karyawan MTF","Kantor Cabang",IFERROR(HLOOKUP($K$4,$T$4:$AE$28,1+H18,0)," ")) | S18: 14 | T18: OCBC | U18: Mercedes | W18: MNC Finance | X18: OONA | Y18: Jakarta R.S. Kanker Dharmais | Z18: Jakarta Taman Permata Buana | AA18: Jakarta Mal Taman Anggrek
B19: 5 | C19: Monitoring EPD & AR | H19: 15 | J19: 15 | K19: =IF($I$3="Karyawan MTF","Kantor Cabang",IFERROR(HLOOKUP($K$4,$T$4:$AE$28,1+H19,0)," ")) | S19: 15 | T19: PANIN | U19: Mitsubishi | W19: MUF | X19: RAKSA | Y19: Jakarta S. Parman | Z19: Jakarta Citra 2 Extention | AA19: Jakarta Mediterania Tanjung Duren
B20: 6 | H20: 16 | J20: 16 | K20: =IF($I$3="Karyawan MTF","Kantor Cabang",IFERROR(HLOOKUP($K$4,$T$4:$AE$28,1+H20,0)," ")) | S20: 16 | T20: PERMATA | U20: Neta | W20: NSC Finance | X20: RAMAYANA | Y20: Jakarta Mal Ciputra | Z20: Jakarta Pos Pengumben Raya | AA20: Jakarta Tanjung Duren
H21: 17 | J21: 17 | K21: =IF($I$3="Karyawan MTF","Kantor Cabang",IFERROR(HLOOKUP($K$4,$T$4:$AE$28,1+H21,0)," ")) | S21: 17 | T21: SINARMAS | U21: Nissan | W21: OTO Multiartha | X21: SIMAS | Y21: Jakarta Menara Citicon | Z21: Jakarta St. Moritz | AA21: Jakarta Pesanggrahan Raya
C22: Referral | H22: 18 | J22: 18 | K22: =IF($I$3="Karyawan MTF","Kantor Cabang",IFERROR(HLOOKUP($K$4,$T$4:$AE$28,1+H22,0)," ")) | S22: 18 | T22: UOB | U22: Suzuki | W22: Sinar Mas Finance | X22: SUNDAY | Z22: Jakarta Pasar Cengkareng | AA22: Jakarta Grand Slipi Tower
B23: 1 | C23: Showroom Mobil Bekas | D23: SRB | E23: Dana Tunai | F23: DTN | H23: 19 | J23: 19 | K23: =IF($I$3="Karyawan MTF","Kantor Cabang",IFERROR(HLOOKUP($K$4,$T$4:$AE$28,1+H23,0)," ")) | S23: 19 | U23: Toyota | W23: WOM Finance | X23: TOB | Z23: Jakarta Pasar Meruya Kembangan
B24: 2 | C24: Karyawan Internal | D24: KIN | E24: Pembiayaan Mobil Bekas | F24: UCF | H24: 20 | J24: 20 | K24: =IF($I$3="Karyawan MTF","Kantor Cabang",IFERROR(HLOOKUP($K$4,$T$4:$AE$28,1+H24,0)," ")) | S24: 20 | U24: Wuling | Z24: Jakarta Raya Kosambi
B25: 3 | C25: Captive Internal | D25: CIN | E25: Pembiayaan Emas / Logam Mulia | F25: LMF | H25: 21 | J25: 21 | M25: Referral | S25: 21
B26: 4 | C26: Captive External | D26: CEX | E26: Pembiayaan Mobil Baru | F26: NCF | H26: 22 | J26: 22 | S26: 22
B27: 5 | C27: Wira Agency Retail | D27: WAR | H27: 23 | I27: =IFERROR(HLOOKUP($I$4,$M$4:$R$26,1+H27,0)," ") | J27: 23 | S27: 23
B28: 6 | C28: Wira Bisnis | D28: WBS | S28: 24
B29: 7 | C29: Others | D29: OTH | S29: 25
O30: Khusus Karyawan Bank Mandiri
C31: =IF('Home Ext'!$C$55="Showroom Mobil Bekas","SRB",IF('Home Ext'!$C$55="Karyawan Internal","KIN",IF('Home Ext'!$C$55="Captive Internal","CIN",IF('Home Ext'!$C$55="Captive External","CEX",IF('Home Ext'!$C$55="Wira Agency Retail","WAR",IF('Home Ext'!C55="Wira Bisnis","WBS","OTH")))))) -> OTH | E31: ='UC Ext'!$I$6 -> Commercial | F31: Domisili | O31: Khusus SME & Private/Prioritas
C32: =IF('Home Ext'!$C$95="Refinancing / Dana Tunai","DTN",IF('Home Ext'!$C$95="Pembiayaan Mobil Bekas","UCF",IF('Home Ext'!$C$95="Pembiayaan Emas / Logam Mulia","LMF",IF('Home Ext'!$C$95="Pembiayaan Mobil Baru","NCF","")))) | E32: =IF(C14="Refinancing / Dana Tunai","TLO All Tenor","Comprehensive All Tenor") -> Comprehensive All Tenor | F32: Jakarta Utara | O32: Semangat
E33: =IF(E31="Passenger","Comprehensive 1 tahun","") | F33: Jakarta Selatan | O33: Tengah
F34: Jakarta Timur | O34: Cuan
B35: 1 | C35: =IF('Home Int'!$O$15="Badan Hukum Usaha"," ","Pasangan Bekerja dan memiliki penghasilan") -> Pasangan Bekerja dan memiliki penghasilan | D35: Karyawan | E35: =IF('Home Int'!$O$15="Badan Hukum Usaha"," ","Pasangan Bekerja dan memiliki penghasilan") -> Pasangan Bekerja dan memiliki penghasilan | F35: Jakarta Barat
B36: 2 | C36: =IF('Home Int'!$O$15="Badan Hukum Usaha"," ","Pasangan memiliki usaha lainnya dan memiliki penghasilan") -> Pasangan memiliki usaha lainnya dan memiliki penghasilan | D36: Wiraswasta | E36: =IF('Home Int'!$O$15="Badan Hukum Usaha"," ","Pasangan memiliki usaha lainnya dan memiliki penghasilan") -> Pasangan memiliki usaha lainnya dan memiliki penghasilan | F36: Jakarta Pusat
B37: 3 | C37: =IF('Home Int'!$O$15="Badan Hukum Usaha"," ","Pasangan adalah profesional dan memiliki penghasilan") -> Pasangan adalah profesional dan memiliki penghasilan | D37: Profesional | E37: =IF('Home Int'!$O$15="Badan Hukum Usaha"," ","Pasangan adalah profesional dan memiliki penghasilan") -> Pasangan adalah profesional dan memiliki penghasilan | F37: Kota Bogor
B38: 4 | C38: =IF('Home Int'!$O$15="Badan Hukum Usaha"," ","Tidak Ada") -> Tidak Ada | D38: Tidak Ada | E38: =IF('Home Int'!$O$15="Badan Hukum Usaha"," ","Tidak Ada") -> Tidak Ada | F38: Kabupaten Bogor
F39: Depok
F40: Kota Tanggerang
F41: Kabupaten Tanggerang
F42: Kota Tanggerang Selatan
F43: Kota Bekasi
F44: Kabupaten Bekasi
H69: 0.1
H70: 0.1
H71: 0.1
H72: 0.8
C78: Usia Debitur
C79: 18-35 tahun
C80: 36-45 tahun
C81: 46-50 tahun
C82: 51-60 tahun

Sheet Home Int
C5: Halooo… Sahabat Referral | E5: Karyawan Internal | I5: Dana Tunai & Pembiayaan Mobil Bekas | O5: Kelengkapan Dokumen & Tracking Aplikasi | W5: Pembiayaan Mobil Baru
E7: Karyawan Authorized Dealer | I7: Type Debitur | K7: Usia Debitur (Perorangan) saat ini | W7: Type Debitur
E9: Karyawan Perbankan | I9: Perorangan (Wiraswasta) | K9: 36-45 tahun | O9: Nama Debitur | W9: Perorangan
E11: Karyawan Asuransi Rekanan | I11: =IF($C$149="Pembiayaan Emas / Logam Mulia","","Type Kendaraan") -> Type Kendaraan | K11: =IF(C149="Pembiayaan Emas / Logam Mulia","","Merk Kendaraan") -> Merk Kendaraan | O11: AAAAAA | W11: Jika Debitur Perorangan, usia saat ini
E13: Agent Retail | I13: Passenger | K13: HONDA | O13: Type Debitur | W13: 36-45 tahun
E15: Showroom Mobil Bekas | I15: Type Kendaraan | K15: Model Kendaraan | O15: Perorangan (Non Wiraswasta) | W15: =IF($C$149="Pembiayaan Emas / Logam Mulia","","Type Kendaraan") -> Type Kendaraan
I17: BRV | K17: ALL NEW BRV E CVT PRESTIGE SENSING | O17: =IF($O$15="Badan Hukum Usaha"," ","Konfirmasi Sumber Penghasilan lainnya") -> Konfirmasi Sumber Penghasilan lainnya | W17: Passenger
I19: Tahun Kendaraan | O19: Pasangan Bekerja dan memiliki penghasilan
C21: Butuh Dana Tunai untuk? Dan kebutuhan? | E21: Pendidikan | I21: 2025 | O21: Referral | W21: HONDA
E23: Renovasi Rumah | O23: =CONCATENATE($C$91,"_",$C$93,"_",$C$95,"_",$C$97) -> Wira Agency Retail_Karyawan Authorized Dealer_Toyota_
E25: Liburan / Wisata Religi | I25: ASURANSI
C27: Debitur/ Nasabah, dengan jaminan BPKB Mobil | E27: Pernikahan / Persalinan | I27: Asuransi | W27: Type Kendaraan
E29: Modal Usaha | I29: Comprehensive 1 tahun | K29: BATAS BAWAH | W29: BRIO
I31: Gempa | K31: Banjir | W31: Model Kendaraan
C33: Cara Mudah Mendapatkan Simulasi Pembiayaan & | D33: Cara Mudah Mengajukan Pinjaman | E33: Cara Mudah Mengajukan Pinjaman | I33: Tidak | K33: Tidak | W33: ALL NEW BRIO RS CVT
C35: Tracking Proses Permohonan Pembiayaan Realtime | I35: Terorism | K35: Huru-hara | O35: Kelengkapan Dokumen Permohonan Pembiayaan | W35: Tahun Kendaraan
I37: Tidak | K37: Tidak | O37: 1 | Q37: =IF($O$15="Badan Hukum Usaha","KTP Komisaris","KTP Pemohon") -> KTP Pemohon | S37: 2 | W37: 2017
D39: 1 | E39: Registrasi | I39: TJH | K39: Pengemudi | O39: 2 | Q39: =IF($O$15="Badan Hukum Usaha","KTP Direksi","KTP Pasangan") -> KTP Pasangan | S39: 2
I41: 20000000 | K41: 0 | O41: 3 | Q41: =IF($O$15="Badan Hukum Usaha","NPWP Direksi","NPWP Pemohon") -> NPWP Pemohon | S41: 2
I43: Penumpang | K43: Jml Penumpang | O43: 4 | Q43: =IF($O$15="Badan Hukum Usaha","NPWP Usaha","Kartu Keluarga") -> Kartu Keluarga | S43: 2
I45: 0 | K45: 0 | O45: 5 | Q45: =IF($O$15="Badan Hukum Usaha","Akte Pendirian","Bukti Kepemilikan Rumah (SPPT PBB/AJB/SHM") -> Bukti Kepemilikan Rumah (SPPT PBB/AJB/SHM | S45: 1
D47: 2 | E47: Isi Form Online | O47: 6 | Q47: =IF($O$15="Badan Hukum Usaha","Akte Perubahan","Rek Koran 3 bulan terakhir") -> Rek Koran 3 bulan terakhir | S47: 1
I49: Upping | O49: 7 | Q49: =IF($O$15="Perorangan (Wiraswasta)","Legalitas Usaha (NIB/SKDU)",IF($O$15="Perorangan (Non Wiraswasta)","Slip Gaji Carbonized","SK Kemenkumham")) -> Slip Gaji Carbonized | S49: 1
I51: ACP | K51: Admin | O51: =IF(Q51=" "," ",8) | Q51: =IF($O$15="Perorangan (Wiraswasta)","Bon / Faktur Penjualan",IF($O$15="Perorangan (Non Wiraswasta)"," ","Legalitas Usaha (NIB & Ijin Usaha khusus)")) | S51: =T51 -> 0
I53: 0.3 | K53: 2000000 | O53: =IF(Q53=" "," ",9) | Q53: =IF($O$15="Perorangan (Wiraswasta)","Surat Ijin Profesi (khusus untuk tenaga profesional)",IF($O$15="Perorangan (Non Wiraswasta)"," ","Laporan Keuangan")) | S53: =T53 -> 0
D55: 3 | E55: Ajukan sesuai kebutuhan Debitur anda | I55: Rate | K55: Provisi | O55: =IF(Q55=" "," ",10) | Q55: =IF($O$15="Perorangan (Wiraswasta)"," ",IF($O$15="Perorangan (Non Wiraswasta)"," ","Rek Koran 3 Bulan terakhir")) | S55: =T55 -> 0 | W55: STNK atas nama
I57: 0 | K57: 0 | O57: =IF(Q57=" "," ",11) | Q57: =IF($O$15="Perorangan (Wiraswasta)"," ",IF($O$15="Perorangan (Non Wiraswasta)"," ","SPK /MOU")) | S57: =T57 -> 0 | W57: Pribadi (milik sendiri)
I59: Type angsuran | K59: STNK atas nama
I61: ADDB | K61: Pribadi (milik sendiri)
C63: Bosan dengan mobil anda, atau mau ganti yang lebih muda? | I63: Deposit sngsuran | K63: Pajak Tahunan (PKB) | O63: =IF($O$15="Badan Hukum Usaha"," ",IF($O$19="Tidak Ada"," ",$O$19)) -> Pasangan Bekerja dan memiliki penghasilan
C65: Atau ganti dengan Mobil Baru? | I65: 0 | K65: 0 | O65: =IF($O$15="Badan Hukum Usaha"," ",IF($O$19="Tidak Ada"," ",1)) -> 1 | Q65: =IF($O$15="Badan Hukum Usaha"," ",IF($O$19="Tidak Ada"," ","Rek Koran 3 bulan terakhir")) -> Rek Koran 3 bulan terakhir | S65: =T65 -> 0
C67: Atau mau lengkapi koleksi Logam Mulia anda, dengan cara mudah | I67: BBNKB | K67: Tidak ada Faktur | O67: =IF($O$15="Badan Hukum Usaha"," ",IF($O$19="Tidak Ada"," ",2)) -> 2 | Q67: =IF($O$15="Badan Hukum Usaha"," ",IF($O$19="Pasangan Bekerja dan memiliki penghasilan","Slip Gaji Carbonized",IF($O$19="Pasangan memiliki usaha lainnya dan memiliki penghasilan","Legalitas Usaha (NIB/SKDU)",IF($O$19="Pasangan adalah profesional dan memiliki penghasilan","Surat Ijin Profesi"," ")))) -> Slip Gaji Carbonized | S67: =T67 -> 0
C69: Kami hadir Mewujudkan mimpi anda, sekarang | I69: 10000000 | K69: 0 | O69: =IF(OR($O$15="Perorangan (Wiraswasta)",$Q$69="Bon / Faktur Penjualan"),3," ") | Q69: =IF($O$15="Badan Hukum Usaha"," ",IF($O$19="Pasangan Bekerja dan memiliki penghasilan"," ",IF($O$19="Pasangan memiliki usaha lainnya dan memiliki penghasilan","Bon / Faktur Penjualan",IF($O$19="Pasangan adalah profesional dan memiliki penghasilan"," "," ")))) | S69: =T69 -> 0
C71: menawarkan Solusi Cepat dan Mudah | I71: =CONCATENATE($K$13,"-",$I$17,"-",$K$17) -> HONDA-BRV-ALL NEW BRV E CVT PRESTIGE SENSING
I75: Simulasi Dana Tunai | O75: Tracking Aplikasi | W75: Harga OTR
C77: NAMA LENGKAP | I77: Harga Taksasi | K77: Harga PHPM | O77: 1 | Q77: Verifikasi, Validasi dan kelengkapan data permohonan | S77: =T77 -> 0 | W77: ='DT Ext'!$F$13 -> 140000000
I79: 210000000 | K79: =VLOOKUP('DT Int'!$B$10,'PHPM 1 DT Int'!$K$5:$L$848,2,0) -> 275000026 | O79: 2 | Q79: Survey Domisili & Tempat usaha/Kantor | S79: =T79 -> 0 | W79: Pencairan Maksimal | Y79: Angsuran perbulan
C81: ALAMAT EMAIL | I81: Pencairan Maksimal | K81: Angsuran perbulan | O81: 3 | Q81: Cek fisik Kendaraan | S81: =T81 -> 0 | W81: ='DT Ext'!$E$73 -> 122059100 | X81: =_xlfn.UNICHAR(9312) -> ① | Y81: ='DT Ext'!$G$73 -> 11926000
I83: ='DT Int'!$E$73 -> 179564500 | J83: =_xlfn.UNICHAR(9312) -> ① | K83: ='DT Int'!$G$73 -> 18335000 | O83: 4 | Q83: Laporan Hasil Survey. | S83: =T83 -> 0 | W83: ='DT Ext'!$E$74 -> 120594700 | X83: =_xlfn.UNICHAR(9313) -> ② | Y83: ='DT Ext'!$G$74 -> 6352000
C85: No. HAND PHONE | I85: ='DT Int'!$E$74 -> 176945400 | J85: =_xlfn.UNICHAR(9313) -> ② | K85: ='DT Int'!$G$74 -> 10006000 | O85: 5 | Q85: Proses Aplikasi | S85: =T85 -> 0 | W85: ='DT Ext'!$E$75 -> 118902100 | X85: =_xlfn.UNICHAR(9314) -> ③ | Y85: ='DT Ext'!$G$75 -> 4514000
I87: ='DT Int'!$E$75 -> 174311500 | J87: =_xlfn.UNICHAR(9314) -> ③ | K87: ='DT Int'!$G$75 -> 7260000 | O87: 6 | Q87: Konfirmasi Debitur by phone & Scoring Credit | S87: =T87 -> 0 | W87: ='DT Ext'!$E$76 -> 116972900 | X87: =_xlfn.UNICHAR(9315) -> ④ | Y87: ='DT Ext'!$G$76 -> 3700000
C89: REFERRAL | I89: ='DT Int'!$E$76 -> 171126400 | J89: =_xlfn.UNICHAR(9315) -> ④ | K89: ='DT Int'!$G$76 -> 5910000 | O89: 7 | Q89: Permohonan Persetujuan Pembiayaan | S89: =T89 -> 0 | W89: ='DT Ext'!$E$77 -> 115171100 | X89: =_xlfn.UNICHAR(9316) -> ⑤ | Y89: ='DT Ext'!$G$77 -> 3227000
C91: Wira Agency Retail | I91: ='DT Int'!$E$77 -> 168191600 | J91: =_xlfn.UNICHAR(9316) -> ⑤ | K91: ='DT Int'!$G$77 -> 5118000 | O91: 8 | Q91: Persetujuan Pembiayaan (PO) | S91: =T91 -> 0
C93: Karyawan Authorized Dealer | O93: 9 | Q93: Verifikasi, Validasi dan kelengkapan Jaminan (BPKB) | S93: =T93 -> 0
C95: Toyota | I95: Nominal pembiayaan bersifat Estimasi | O95: 10 | Q95: Kofirmasi Debitur by phone | S95: =T95 -> 0 | W95: Nominal pembiayaan bersifat Estimasi
I97: Besarnya pembiayaan berdasarkan hasil | O97: 11 | Q97: Golive & Payment | S97: =T97 -> 0 | W97: Besarnya pembiayaan berdasarkan hasil
I99: Verifikasi Profil Debitur dan kondisi Kendaraan | W99: Verifikasi Profil Debitur dan kondisi Kendaraan
C101: NAMA USER | I101: AJUKAN | W101: AJUKAN
C105: KATA SANDI | I105: Dana yang dibutuhkan | W105: Dana yang dibutuhkan
I107: 60000000 | W107: 60000000
C109: KONFIRMASI KATA SANDI | I109: Hitung | W109: Hitung
J111: =_xlfn.UNICHAR(9312) -> ① | K111: ='DT Int'!$O$73 -> 6428000 | X111: =_xlfn.UNICHAR(9312) -> ① | Y111: ='DT Ext'!$G$69 -> 6361000
J113: =_xlfn.UNICHAR(9313) -> ② | K113: ='DT Int'!$O$74 -> 3639000 | X113: =_xlfn.UNICHAR(9313) -> ② | Y113: ='DT Ext'!$O$74 -> 3458000
C115: Daftar | E115: Batal | J115: =_xlfn.UNICHAR(9314) -> ③ | K115: ='DT Int'!$O$75 -> 2737000 | X115: =_xlfn.UNICHAR(9314) -> ③ | Y115: ='DT Ext'!$O$75 -> 2515000
J117: =_xlfn.UNICHAR(9315) -> ④ | K117: ='DT Int'!$O$76 -> 2322000 | X117: =_xlfn.UNICHAR(9315) -> ④ | Y117: ='DT Ext'!$O$76 -> 2115000
J119: =_xlfn.UNICHAR(9316) -> ⑤ | K119: ='DT Int'!$O$77 -> 2086000 | X119: =_xlfn.UNICHAR(9316) -> ⑤ | Y119: ='DT Ext'!$O$77 -> 1889000
I121: Nominal pembiayaan bersifat Estimasi | W121: Nominal pembiayaan bersifat Estimasi
I123: Besarnya pembiayaan berdasarkan hasil | W123: Besarnya pembiayaan berdasarkan hasil
I125: Verifikasi Profil Debitur dan kondisi Kendaraan | W125: Verifikasi Profil Debitur dan kondisi Kendaraan
I127: AJUKAN | W127: AJUKAN
C131: NAMA USER | I131: Simulasi Pembiayaan Mobil Bekas
I133: Harga Pasar
C135: KATA SANDI | I135: 210000000
I137: Pencairan All In | K137: Angsuran perbulan
I139: ='UC Int'!$E$78 -> 134567000 | J139: =_xlfn.UNICHAR(9312) -> ① | K139: ='UC Int'!$G$78 -> 13232000
C141: Masuk | E141: Batal | I141: ='UC Int'!$E$79 -> 132370400 | J141: =_xlfn.UNICHAR(9313) -> ② | K141: ='UC Int'!$G$79 -> 7091000
C143: Simulasi / Tracking | I143: ='UC Int'!$E$80 -> 130184300 | J143: =_xlfn.UNICHAR(9314) -> ③ | K143: ='UC Int'!$G$80 -> 5058000
C145: Simulasi Kredit | I145: ='UC Int'!$E$81 -> 127599200 | J145: =_xlfn.UNICHAR(9315) -> ④ | K145: ='UC Int'!$G$81 -> 4052000
C147: Jenis Pembiayaan | I147: ='UC Int'!$E$82 -> 125205200 | J147: =_xlfn.UNICHAR(9316) -> ⑤ | K147: ='UC Int'!$G$82 -> 3457000
C149: Dana Tunai | I149: Nominal pembiayaan bersifat Estimasi
C151: Domisili Debitur | I151: Besarnya pembiayaan berdasarkan hasil
C153: Jakarta Barat | I153: Verifikasi Profil Debitur dan kondisi Kendaraan
I155: AJUKAN
I159: Total DP Dikehendaki
I161: 35000000
I163: Hitung
J165: =_xlfn.UNICHAR(9312) -> ① | K165: ='UC Int'!$O$78 -> 0
J167: =_xlfn.UNICHAR(9313) -> ② | K167: ='UC Int'!$O$79 -> 0
J169: =_xlfn.UNICHAR(9314) -> ③ | K169: ='UC Int'!$O$80 -> 0
J171: =_xlfn.UNICHAR(9315) -> ④ | K171: ='UC Int'!$O$81 -> 0
J173: =_xlfn.UNICHAR(9316) -> ⑤ | K173: ='UC Int'!$O$7882 -> 0
I175: Nominal pembiayaan bersifat Estimasi
I177: Besarnya pembiayaan berdasarkan hasil
I179: Verifikasi Profil Debitur dan kondisi Kendaraan
I181: AJUKAN

Sheet DT Int
B4: Merk | D4: ='Home Int'!$K$13 -> HONDA | G4: Type Kendaraan | I4: ='Home Int'!$I$17 -> BRV | N4: Deposit Angsuran | P4: ='Home Int'!$I$65 -> 0 | Q4: Up ACP | S4: ='Home Int'!$I$53 -> 0.3
B5: Type Debitur | D5: ='Home Int'!$I$9 -> Perorangan (Wiraswasta) | G5: Model Kendaraan | I5: ='Home Int'!$K$17 -> ALL NEW BRV E CVT PRESTIGE SENSING | N5: BBNKB | O5: ='Home Int'!$I$69 -> 10000000 | Q5: Up Rate | S5: ='Home Int'!$I$57 -> 0
B6: Type Angsuran | D6: ='Home Int'!$I$61 -> ADDB | G6: Penggunaan Unit | I6: ='Home Int'!$I$13 -> Passenger | N6: PKB | O6: ='Home Int'!$K$65 -> 0 | Q6: Up Adm | S6: ='Home Int'!$K$53 -> 2000000
B7: Type Unit | D7: =VLOOKUP('Home Int'!$K$13,'PHPM 2 DT Int'!$D$4:$E$54,2,0) -> Japan | G7: Product | I7: =CONCATENATE(VLOOKUP('Home Int'!$C$91,'Data Int'!$C$5:$F$12,2,0)," ",'Home Int'!$I$13," ",VLOOKUP('Home Int'!$C$91,'Data Int'!$C$5:$F$12,4,0)) -> Reguler Passenger Sales Dealer | N7: FAKTUR | O7: ='Home Int'!$K$69 -> 0 | Q7: Up Provisi | S7: ='Home Int'!$K$57 -> 0
B8: Thn (NIK) | D8: ='Home Int'!$I$21 -> 2025 | F8: =15-(2026-D8) -> 14 | G8: Asuransi | I8: ='Home Int'!$I$29 -> Comprehensive 1 tahun | N8: Asuransi | O8: ='Home Int'!$K$29 -> BATAS BAWAH | Q8: Usia Debitur | S8: ='Home Int'!$K$9 -> 36-45 tahun
B9: TENOR | F9: 1 | G9: =F9*12 -> 12 | I9: 2 | J9: =I9*12 -> 24 | L9: 3 | M9: =L9*12 -> 36 | O9: 4 | P9: =O9*12 -> 48 | R9: 5 | S9: =R9*12 -> 60
B10: =CONCATENATE('Home Int'!$K$13,"-",'Home Int'!$I$17,"-",'Home Int'!$K$17) -> HONDA-BRV-ALL NEW BRV E CVT PRESTIGE SENSING | F10: =(16-F9)-(2026-$D$8) -> 14 | I10: =(16-I9)-(2026-$D$8) -> 13 | L10: =(16-L9)-(2026-$D$8) -> 12 | O10: =(16-O9)-(2026-$D$8) -> 11 | R10: =(16-R9)-(2026-$D$8) -> 10
B11: Harga OTR | D11: PASAR | F11: ='Home Int'!$I$79 -> 210000000 | I11: ='Home Int'!$I$79 -> 210000000 | L11: ='Home Int'!$I$79 -> 210000000 | O11: ='Home Int'!$I$79 -> 210000000 | R11: ='Home Int'!$I$79 -> 210000000
D12: PHPM | F12: =IF(F10>=1,VLOOKUP($B$10,'PHPM 1 DT Int'!$K$5:$L$848,2,0),0) -> 275000026 | I12: =IF(I10>=1,VLOOKUP($B$10,'PHPM 1 DT Int'!$K$5:$L$848,2,0),0) -> 275000026 | L12: =IF(L10>=1,VLOOKUP($B$10,'PHPM 1 DT Int'!$K$5:$L$848,2,0),0) -> 275000026 | O12: =IF(O10>=1,VLOOKUP($B$10,'PHPM 1 DT Int'!$K$5:$L$848,2,0),0) -> 275000026 | R12: =IF(R10>=1,VLOOKUP($B$10,'PHPM 1 DT Int'!$K$5:$L$848,2,0),0) -> 275000026
D13: ROUNDDOWN PHPM | F13: =IF(F12=0,F11,ROUNDDOWN(F12,-2)) -> 275000000 | I13: =IF(I12=0,I11,ROUNDDOWN(I12,-2)) -> 275000000 | L13: =IF(L12=0,L11,ROUNDDOWN(L12,-2)) -> 275000000 | O13: =IF(O12=0,O11,ROUNDDOWN(O12,-2)) -> 275000000 | R13: =IF(R12=0,R11,ROUNDDOWN(R12,-2)) -> 275000000
B14: Deviasi (%) | D14: (Rp.) | F14: =IFERROR(G14/F11,0) -> 0 | G14: =IF(F11<=F12,0,F11-F12) -> 0 | I14: =IFERROR(J14/I11,0) -> 0 | J14: =IF(I11<=I12,0,I11-I12) -> 0 | L14: =IFERROR(M14/L11,0) -> 0 | M14: =IF(L11<=L12,0,L11-L12) -> 0 | O14: =IFERROR(P14/O11,0) -> 0 | P14: =IF(O11<=O12,0,O11-O12) -> 0 | R14: =IFERROR(S14/R11,0) -> 0 | S14: =IF(R11<=R12,0,R11-R12) -> 0
B15: Sum Insured | D15: % | E15: Rp. | F15: 1 | G15: =F11*F15 -> 210000000 | I15: 0.9 | J15: =I11*I15 -> 189000000 | L15: 0.8 | M15: =L11*L15 -> 168000000 | O15: 0.7 | P15: =O11*O15 -> 147000000 | R15: 0.7 | S15: =R11*R15 -> 147000000
B16: Net DP | D16: % | E16: Rp. | F16: =IF('Home Int'!$K$61="Orang lain",15%,IF(OR($I$6="Commercial",$D$7="Non Japan"),15%,5%))+F14 -> 0.05 | G16: =ROUNDUP(F11*F16,-3) -> 10500000 | I16: =IF('Home Int'!$K$61="Orang lain",15%,IF(OR($I$6="Commercial",$D$7="Non Japan"),15%,5%))+I14 -> 0.05 | J16: =ROUNDUP(I11*I16,-3) -> 10500000 | L16: =IF('Home Int'!$K$61="Orang lain",15%,IF(OR($I$6="Commercial",$D$7="Non Japan"),15%,5%))+L14 -> 0.05 | M16: =ROUNDUP(L11*L16,-3) -> 10500000 | O16: =IF('Home Int'!$K$61="Orang lain",15%,IF(OR($I$6="Commercial",$D$7="Non Japan"),15%,5%))+O14 -> 0.05 | P16: =ROUNDUP(O11*O16,-3) -> 10500000 | R16: =IF('Home Int'!$K$61="Orang lain",15%,IF(OR($I$6="Commercial",$D$7="Non Japan"),15%,5%))+R14 -> 0.05 | S16: =ROUNDUP(R11*R16,-3) -> 10500000
B17: LTV | D17: % | E17: Rp. | F17: =100%-F16 -> 0.95 | G17: =F11-G16 -> 199500000 | I17: =100%-I16 -> 0.95 | J17: =I11-J16 -> 199500000 | L17: =100%-L16 -> 0.95 | M17: =L11-M16 -> 199500000 | O17: =100%-O16 -> 0.95 | P17: =O11-P16 -> 199500000 | R17: =100%-R16 -> 0.95 | S17: =R11-S16 -> 199500000
B18: RATE p.a (%) | D18: Eff R | E18: Flat Rate | F18: =VLOOKUP($I$7,Product!$B$6:$K$25,2,0) -> 0.1847 | G18: =IF($D$6="ADDM",(((PMT(F18/12,G9,1,0,1)*(-1))*G9)-1)*12/G9,IF($D$6="ADDB",(((PMT(F18/12,G9,1,0,0)*(-1))*G9)-1)*12/G9," ")) -> 0.10284585 | H18: =G18+$S$5 -> 0.10284585 | I18: =VLOOKUP($I$7,Product!$B$6:$K$25,2,0) -> 0.1847 | J18: =IF($D$6="ADDM",(((PMT(I18/12,J9,1,0,1)*(-1))*J9)-1)*12/J9,IF($D$6="ADDB",(((PMT(I18/12,J9,1,0,0)*(-1))*J9)-1)*12/J9," ")) -> 0.10181789 | K18: =J18+$S$5 -> 0.10181789 | L18: =VLOOKUP($I$7,Product!$B$6:$K$25,2,0) -> 0.1847 | M18: =IF($D$6="ADDM",(((PMT(L18/12,M9,1,0,1)*(-1))*M9)-1)*12/M9,IF($D$6="ADDB",(((PMT(L18/12,M9,1,0,0)*(-1))*M9)-1)*12/M9," ")) -> 0.10332995 | N18: =M18+$S$5 -> 0.10332995 | O18: =VLOOKUP($I$7,Product!$B$6:$K$25,2,0) -> 0.1847 | P18: =IF($D$6="ADDM",(((PMT(O18/12,P9,1,0,1)*(-1))*P9)-1)*12/P9,IF($D$6="ADDB",(((PMT(O18/12,P9,1,0,0)*(-1))*P9)-1)*12/P9," ")) -> 0.10545398 | Q18: =P18+$S$5 -> 0.10545398 | R18: =VLOOKUP($I$7,Product!$B$6:$K$25,2,0) -> 0.1847 | S18: =IF($D$6="ADDM",(((PMT(R18/12,S9,1,0,1)*(-1))*S9)-1)*12/S9,IF($D$6="ADDB",(((PMT(R18/12,S9,1,0,0)*(-1))*S9)-1)*12/S9," ")) -> 0.10779758 | T18: =S18+$S$5 -> 0.10779758
B19: Bunga Jual | D19: % | E19: Rp. | F19: =(H18*F9) -> 0.10284585 | G19: =G17*F19 -> 20517747 | I19: =(K18*I9) -> 0.20363579 | J19: =J17*I19 -> 40625339 | L19: =(N18*L9) -> 0.30998986 | M19: =M17*L19 -> 61842978 | O19: =(Q18*O9) -> 0.4218159 | P19: =P17*O19 -> 84152273 | R19: =(T18*R9) -> 0.53898789 | S19: =S17*R19 -> 1.0752808e+08
B20: TOTAL A/R | G20: =G17+G19 -> 2.2001775e+08 | J20: =J17+J19 -> 2.4012534e+08 | M20: =M17+M19 -> 2.6134298e+08 | P20: =P17+P19 -> 2.8365227e+08 | S20: =S17+S19 -> 3.0702808e+08
B21: ANGSURAN | F21: =ROUNDUP(G20/G9,-3) -> 18335000 | I21: =ROUNDUP(J20/J9,-3) -> 10006000 | L21: =ROUNDUP(M20/M9,-3) -> 7260000 | O21: =ROUNDUP(P20/P9,-3) -> 5910000 | R21: =ROUNDUP(S20/S9,-3) -> 5118000
B22: TOTAL BAYAR PERTAMA
B23: ASURANSI | F23: =IF(OR($I$8="Comprehensive 1 tahun, sisanya TLO",I8="Comprehensive All Tenor"),"Comprehensive","TLO") -> TLO | I23: =IF($I$8="Comprehensive All Tenor","Comprehensive","TLO") -> TLO | L23: =IF($I$8="Comprehensive All Tenor","Comprehensive","TLO") -> TLO | O23: =IF($I$8="Comprehensive All Tenor","Comprehensive","TLO") -> TLO | R23: =IF($I$8="Comprehensive All Tenor","Comprehensive","TLO") -> TLO
C24: Casco | F24: =IF(F23="Comprehensive",IF(AND(G15>=1,G15<=125000000),'Asr Int'!$C$22,IF(AND(G15>125000000,G15<=200000000),'Asr Int'!$C$23,IF(AND(G15>200000000,G15<=400000000),'Asr Int'!$C$24,IF(AND(G15>400000000,G15<=800000000),'Asr Int'!$C$25,'Asr Int'!$C$26)))),IF(AND(G15>=1,G15<=125000000),'Asr Int'!$D$22,IF(AND(G15>125000000,G15<=200000000),'Asr Int'!$D$23,IF(AND(G15>200000000,G15<=400000000),'Asr Int'!$D$24,IF(AND(G15>400000000,G15<=800000000),'Asr Int'!$D$25,'Asr Int'!$D$26))))) -> 0.0038 | G24: =F24*G15 -> 798000 | I24: =IF(I23="Comprehensive",IF(AND(J15>=1,J15<=125000000),'Asr Int'!$C$22,IF(AND(J15>125000000,J15<=200000000),'Asr Int'!$C$23,IF(AND(J15>200000000,J15<=400000000),'Asr Int'!$C$24,IF(AND(J15>400000000,J15<=800000000),'Asr Int'!$C$25,'Asr Int'!$C$26)))),IF(AND(J15>=1,J15<=125000000),'Asr Int'!$D$22,IF(AND(J15>125000000,J15<=200000000),'Asr Int'!$D$23,IF(AND(J15>200000000,J15<=400000000),'Asr Int'!$D$24,IF(AND(J15>400000000,J15<=800000000),'Asr Int'!$D$25,'Asr Int'!$D$26))))) -> 0.0044 | J24: =(I24*J15)+G24 -> 1629600 | L24: =IF(L23="Comprehensive",IF(AND(M15>=1,M15<=125000000),'Asr Int'!$C$22,IF(AND(M15>125000000,M15<=200000000),'Asr Int'!$C$23,IF(AND(M15>200000000,M15<=400000000),'Asr Int'!$C$24,IF(AND(M15>400000000,M15<=800000000),'Asr Int'!$C$25,'Asr Int'!$C$26)))),IF(AND(M15>=1,M15<=125000000),'Asr Int'!$D$22,IF(AND(M15>125000000,M15<=200000000),'Asr Int'!$D$23,IF(AND(M15>200000000,M15<=400000000),'Asr Int'!$D$24,IF(AND(M15>400000000,M15<=800000000),'Asr Int'!$D$25,'Asr Int'!$D$26))))) -> 0.0044 | M24: =(L24*M15)+J24 -> 2368800 | O24: =IF(O23="Comprehensive",IF(AND(P15>=1,P15<=125000000),'Asr Int'!$C$22,IF(AND(P15>125000000,P15<=200000000),'Asr Int'!$C$23,IF(AND(P15>200000000,P15<=400000000),'Asr Int'!$C$24,IF(AND(P15>400000000,P15<=800000000),'Asr Int'!$C$25,'Asr Int'!$C$26)))),IF(AND(P15>=1,P15<=125000000),'Asr Int'!$D$22,IF(AND(P15>125000000,P15<=200000000),'Asr Int'!$D$23,IF(AND(P15>200000000,P15<=400000000),'Asr Int'!$D$24,IF(AND(P15>400000000,P15<=800000000),'Asr Int'!$D$25,'Asr Int'!$D$26))))) -> 0.0044 | P24: =(O24*P15)+M24 -> 3015600 | R24: =IF(R23="Comprehensive",IF(AND(S15>=1,S15<=125000000),'Asr Int'!$C$22,IF(AND(S15>125000000,S15<=200000000),'Asr Int'!$C$23,IF(AND(S15>200000000,S15<=400000000),'Asr Int'!$C$24,IF(AND(S15>400000000,S15<=800000000),'Asr Int'!$C$25,'Asr Int'!$C$26)))),IF(AND(S15>=1,S15<=125000000),'Asr Int'!$D$22,IF(AND(S15>125000000,S15<=200000000),'Asr Int'!$D$23,IF(AND(S15>200000000,S15<=400000000),'Asr Int'!$D$24,IF(AND(S15>400000000,S15<=800000000),'Asr Int'!$D$25,'Asr Int'!$D$26))))) -> 0.0044 | S24: =(R24*S15)+P24 -> 3662400
C25: Loading | F25: =IFERROR(IF(F23="Comprehensive",VLOOKUP($D$8,'Asr Int'!$L$6:$N$20,3,0),0),0) -> 0 | G25: =G24*F25 -> 0 | I25: =IFERROR(IF(I23="Comprehensive",VLOOKUP($D$8,'Asr Int'!$L$6:$N$20,3,0),0),0) -> 0 | J25: =(J24*I25)+G25 -> 0 | L25: =IFERROR(IF(L23="Comprehensive",VLOOKUP($D$8,'Asr Int'!$L$6:$N$20,3,0),0),0) -> 0 | M25: =(M24*L25)+J25 -> 0 | O25: =IFERROR(IF(O23="Comprehensive",VLOOKUP($D$8,'Asr Int'!$L$6:$N$20,3,0),0),0) -> 0 | P25: =(P24*O25)+M25 -> 0 | R25: =IFERROR(IF(R23="Comprehensive",VLOOKUP($D$8,'Asr Int'!$L$6:$N$20,3,0),0),0) -> 0 | S25: =(S24*R25)+P25 -> 0
C26: Banjir | E26: TIDAK | F26: =IF($E$26="YA",IF(F23="Comprehensive",0.1%,0%),0) -> 0 | G26: =F26*G15 -> 0 | I26: =IF($E$26="YA",IF(I23="Comprehensive",0.1%,0%),0) -> 0 | J26: =(I26*J15)+G26 -> 0 | L26: =IF($E$26="YA",IF(L23="Comprehensive",0.1%,0%),0) -> 0 | M26: =(L26*M15)+J26 -> 0 | O26: =IF($E$26="YA",IF(O23="Comprehensive",0.1%,0%),0) -> 0 | P26: =(O26*P15)+M26 -> 0 | R26: =IF($E$26="YA",IF(R23="Comprehensive",0.1%,0%),0) -> 0 | S26: =(R26*S15)+P26 -> 0
C27: Gempa | E27: TIDAK | F27: =IF($E$27="YA",IF(F23="Comprehensive",0.1%,0%),0) -> 0 | G27: =F27*G15 -> 0 | I27: =IF($E$27="YA",IF(I23="Comprehensive",0.1%,0%),0) -> 0 | J27: =(I27*J15)+G27 -> 0 | L27: =IF($E$27="YA",IF(L23="Comprehensive",0.1%,0%),0) -> 0 | M27: =(L27*M15)+J27 -> 0 | O27: =IF($E$27="YA",IF(O23="Comprehensive",0.1%,0%),0) -> 0 | P27: =(O27*P15)+M27 -> 0 | R27: =IF($E$27="YA",IF(R23="Comprehensive",0.1%,0%),0) -> 0 | S27: =(R27*S15)+P27 -> 0
C28: Huru-hara | E28: TIDAK | F28: =IF($E$28="YA",IF(F23="Comprehensive",0.05%,0%),0) -> 0 | G28: =F28*G15 -> 0 | I28: =IF($E$28="YA",IF(I23="Comprehensive",0.05%,0%),0) -> 0 | J28: =(I28*J15)+G28 -> 0 | L28: =IF($E$28="YA",IF(L23="Comprehensive",0.05%,0%),0) -> 0 | M28: =(L28*M15)+J28 -> 0 | O28: =IF($E$28="YA",IF(O23="Comprehensive",0.05%,0%),0) -> 0 | P28: =(O28*P15)+M28 -> 0 | R28: =IF($E$28="YA",IF(R23="Comprehensive",0.05%,0%),0) -> 0 | S28: =(R28*S15)+P28 -> 0
C29: Teroris | E29: TIDAK | F29: =IF($E$29="YA",IF(F23="Comprehensive",0.05%,0%),0) -> 0 | G29: =F29*G15 -> 0 | I29: =IF($E$29="YA",IF(I23="Comprehensive",0.05%,0%),0) -> 0 | J29: =(I29*J15)+G29 -> 0 | L29: =IF($E$29="YA",IF(L23="Comprehensive",0.05%,0%),0) -> 0 | M29: =(L29*M15)+J29 -> 0 | O29: =IF($E$29="YA",IF(O23="Comprehensive",0.05%,0%),0) -> 0 | P29: =(O29*P15)+M29 -> 0 | R29: =IF($E$29="YA",IF(R23="Comprehensive",0.05%,0%),0) -> 0 | S29: =(R29*S15)+P29 -> 0
C30: ASURANSI CASCO + PERLUASAN | G30: =SUM(G24:H29) -> 798000 | J30: =SUM(J24:K29) -> 1629600 | M30: =SUM(M24:N29) -> 2368800 | P30: =SUM(P24:Q29) -> 3015600 | S30: =SUM(S24:T29) -> 3662400
C31: GAP | E31: TIDAK
C32: HIC | E32: TIDAK
C33: TJH | D33: 0 | E33: TIDAK | G33: =IF(F23="Comprehensive",VLOOKUP(F9,'Asr Int'!$G$32:$M$36,7,0),0) -> 0 | J33: =IF(I23="Comprehensive",VLOOKUP(I9,'Asr Int'!$G$32:$M$36,7,0),0)+G33 -> 0 | M33: =IF(L23="Comprehensive",VLOOKUP(L9,'Asr Int'!$G$32:$M$36,7,0),0)+J33 -> 0 | P33: =IF(O23="Comprehensive",VLOOKUP(O9,'Asr Int'!$G$32:$M$36,7,0),0)+M33 -> 0 | S33: =IF(R23="Comprehensive",VLOOKUP(R9,'Asr Int'!$G$32:$M$36,7,0),0)+P33 -> 0
C34: Pengemudi | D34: 0 | E34: TIDAK | F34: =IF($E$34="YA",IF(F23="Comprehensive",0.5%,0%),0) -> 0 | G34: =$D$34*F34 -> 0 | I34: =IF($E$34="YA",IF(I23="Comprehensive",0.5%,0%),0) -> 0 | J34: =(I34*$D$34)+G34 -> 0 | L34: =IF($E$34="YA",IF(L23="Comprehensive",0.5%,0%),0) -> 0 | M34: =(L34*$D$34)+J34 -> 0 | O34: =IF($E$34="YA",IF(O23="Comprehensive",0.5%,0%),0) -> 0 | P34: =(O34*$D$34)+M34 -> 0 | R34: =IF($E$34="YA",IF(R23="Comprehensive",0.5%,0%),0) -> 0 | S34: =(R34*$D$34)+P34 -> 0
C35: Penumpang | D35: 0 | E35: 0 | F35: =IF(AND(F23="Comprehensive",$E$35>0),0.1%,0%)*E35 -> 0 | G35: =F35*$D$35 -> 0 | I35: =IF(AND(I23="Comprehensive",$E$35>0),0.1%,0%)*H35 -> 0 | J35: =(I35*$D$35)+G35 -> 0 | L35: =IF(AND(L23="Comprehensive",$E$35>0),0.1%,0%)*K35 -> 0 | M35: =(L35*$D$35)+J35 -> 0 | O35: =IF(AND(O23="Comprehensive",$E$35>0),0.1%,0%)*N35 -> 0 | P35: =(O35*$D$35)+M35 -> 0 | R35: =IF(AND(R23="Comprehensive",$E$35>0),0.1%,0%)*Q35 -> 0 | S35: =(R35*$D$35)+P35 -> 0
C36: ACP | E36: =IF('Home Int'!$I$9="Badan Hukum Usaha","Tidak","Ya") -> Ya | F36: =IF($E$36="Ya",IF(OR($I$6="Passenger",G17<1000000000),VLOOKUP($S$8,'Asr Int'!$C$70:$H$73,F9+1,0),0),) -> 0.0065 | G36: =F12*F36 -> 1787500.2 | I36: =IF($E$36="Ya",IF(OR($I$6="Passenger",J17<1000000000),VLOOKUP($S$8,'Asr Int'!$C$70:$H$73,I9+1,0),0),) -> 0.013 | J36: =I12*I36 -> 3575000.3 | L36: =IF($E$36="Ya",IF(OR($I$6="Passenger",M17<1000000000),VLOOKUP($S$8,'Asr Int'!$C$70:$H$73,L9+1,0),0),) -> 0.01989 | M36: =L12*L36 -> 5469750.5 | O36: =IF($E$36="Ya",IF(OR($I$6="Passenger",P17<1000000000),VLOOKUP($S$8,'Asr Int'!$C$70:$H$73,O9+1,0),0),) -> 0.02912 | P36: =O12*O36 -> 8008000.8 | R36: =IF($E$36="Ya",IF(OR($I$6="Passenger",S17<1000000000),VLOOKUP($S$8,'Asr Int'!$C$70:$H$73,R9+1,0),0),) -> 0.03744 | S36: =R12*R36 -> 10296001
C37: GARANSI MESIN | E37: YA | G37: =IF($E$37="ya",1500000,0) -> 1500000 | J37: =IF($E$37="ya",1500000,0) -> 1500000 | M37: =IF($E$37="ya",1500000,0) -> 1500000 | P37: =IF($E$37="ya",1500000,0) -> 1500000 | S37: =IF($E$37="ya",1500000,0) -> 1500000
B38: TOTAL ASURANSI | G38: =ROUNDDOWN(SUM(G31:H37)+G30,-2) -> 4085500 | J38: =ROUNDDOWN(SUM(J31:K37)+J30,-2) -> 6704600 | M38: =ROUNDDOWN(SUM(M31:N37)+M30,-2) -> 9338500 | P38: =ROUNDDOWN(SUM(P31:Q37)+P30,-2) -> 12523600 | S38: =ROUNDDOWN(SUM(S31:T37)+S30,-2) -> 15458400
B39: PROVISI | E39: =S7 -> 0 | F39: =VLOOKUP($I$7,Product!$B$6:$K$25,10,0)+$E$39 -> 0 | G39: =F39*G17 -> 0 | I39: =VLOOKUP($I$7,Product!$B$6:$K$25,10,0)+$E$39 -> 0 | J39: =I39*J17 -> 0 | L39: =VLOOKUP($I$7,Product!$B$6:$K$25,10,0)+$E$39 -> 0 | M39: =L39*M17 -> 0 | O39: =VLOOKUP($I$7,Product!$B$6:$K$25,10,0)+$E$39 -> 0 | P39: =O39*P17 -> 0 | R39: =VLOOKUP($I$7,Product!$B$6:$K$25,10,0)+$E$39 -> 0 | S39: =R39*S17 -> 0
B40: ADMINISTRASI | F40: =VLOOKUP($I$7,Product!$B$6:$K$25,9,0) -> 5350000 | I40: =VLOOKUP($I$7,Product!$B$6:$K$25,9,0) -> 5350000 | L40: =VLOOKUP($I$7,Product!$B$6:$K$25,9,0) -> 5350000 | O40: =VLOOKUP($I$7,Product!$B$6:$K$25,9,0) -> 5350000 | R40: =VLOOKUP($I$7,Product!$B$6:$K$25,9,0) -> 5350000
B41: FIDUCIA | F41: =IF(AND(F11>0,F11<=25000000),350000,IF(AND(F11>25000000,F11<=50000000),375000,IF(AND(F11>50000000,F11<=100000000),400000,IF(AND(F11>100000000,F11<=250000000),500000,IF(AND(F11>250000000,F11<=500000000),750000,IF(AND(F11>500000000,F11<=1000000000),1150000,2250000)))))) -> 500000 | I41: =IF(AND(I11>0,I11<=25000000),350000,IF(AND(I11>25000000,I11<=50000000),375000,IF(AND(I11>50000000,I11<=100000000),400000,IF(AND(I11>100000000,I11<=250000000),500000,IF(AND(I11>250000000,I11<=500000000),750000,IF(AND(I11>500000000,I11<=1000000000),1150000,2250000)))))) -> 500000 | L41: =IF(AND(L11>0,L11<=25000000),350000,IF(AND(L11>25000000,L11<=50000000),375000,IF(AND(L11>50000000,L11<=100000000),400000,IF(AND(L11>100000000,L11<=250000000),500000,IF(AND(L11>250000000,L11<=500000000),750000,IF(AND(L11>500000000,L11<=1000000000),1150000,2250000)))))) -> 500000 | O41: =IF(AND(O11>0,O11<=25000000),350000,IF(AND(O11>25000000,O11<=50000000),375000,IF(AND(O11>50000000,O11<=100000000),400000,IF(AND(O11>100000000,O11<=250000000),500000,IF(AND(O11>250000000,O11<=500000000),750000,IF(AND(O11>500000000,O11<=1000000000),1150000,2250000)))))) -> 500000 | R41: =IF(AND(R11>0,R11<=25000000),350000,IF(AND(R11>25000000,R11<=50000000),375000,IF(AND(R11>50000000,R11<=100000000),400000,IF(AND(R11>100000000,R11<=250000000),500000,IF(AND(R11>250000000,R11<=500000000),750000,IF(AND(R11>500000000,R11<=1000000000),1150000,2250000)))))) -> 500000
B42: ANGSURAN | F42: =IF($D$6="ADDM",11,12) -> 12 | G42: =ROUNDUP(IF($D$6="ADDM",G20/G9,0),-3) -> 0 | I42: =IF($D$6="ADDM",23,24) -> 24 | J42: =ROUNDUP(IF($D$6="ADDM",J20/J9,0),-3) -> 0 | L42: =IF($D$6="ADDM",35,36) -> 36 | M42: =ROUNDUP(IF($D$6="ADDM",M20/M9,0),-3) -> 0 | O42: =IF($D$6="ADDM",47,48) -> 48 | P42: =ROUNDUP(IF($D$6="ADDM",P20/P9,0),-3) -> 0 | R42: =IF($D$6="ADDM",59,60) -> 60 | S42: =ROUNDUP(IF($D$6="ADDM",S20/S9,0),-3) -> 0
B43: TOTAL BAYAR PERTAMA | F43: =G16+G38+G39+F40+F41 -> 20435500 | I43: =J16+J38+J39+I40+I41 -> 23054600 | L43: =M16+M38+M39+L40+L41 -> 25688500 | O43: =P16+P38+P39+O40+O41 -> 28873600 | R43: =S16+S38+S39+R40+R41 -> 31808400
B44: PENCAIRAN GROSS | F44: =F11-F43 -> 189564500 | I44: =I11-I43 -> 186945400 | L44: =L11-L43 -> 184311500 | O44: =O11-O43 -> 181126400 | R44: =R11-R43 -> 178191600
B45: BBNKB | G45: =$O$5 -> 10000000 | J45: =$O$5 -> 10000000 | M45: =$O$5 -> 10000000 | P45: =$O$5 -> 10000000 | S45: =$O$5 -> 10000000
B46: PKB | G46: =$O$6 -> 0 | J46: =$O$6 -> 0 | M46: =$O$6 -> 0 | P46: =$O$6 -> 0 | S46: =$O$6 -> 0
B47: FAKTUR | G47: =$O$7 -> 0 | J47: =$O$7 -> 0 | M47: =$O$7 -> 0 | P47: =$O$7 -> 0 | S47: =$O$7 -> 0
B48: NILAI TITIPAN ANGSURAN | F48: =$P$4 -> 0 | G48: =G42*F48 -> 0 | I48: =$P$4 -> 0 | J48: =J42*I48 -> 0 | L48: =$P$4 -> 0 | M48: =M42*L48 -> 0 | O48: =$P$4 -> 0 | P48: =P42*O48 -> 0 | R48: =$P$4 -> 0 | S48: =S42*R48 -> 0
B49: PECAIRAN NETO | F49: =IF(F12=0,0,F44-(G45+G46+G47+G48)) -> 179564500 | I49: =IF(I12=0,0,I44-(J45+J46+J47+J48)) -> 176945400 | L49: =IF(L12=0,0,L44-(M45+M46+M47+M48)) -> 174311500 | O49: =IF(O12=0,0,O44-(P45+P46+P47+P48)) -> 171126400 | R49: =IF(R12=0,0,R44-(S45+S46+S47+S48)) -> 168191600
B51: REFUND ASURANSI
B52: REFUND BUNGA
B53: REFUND PROVISI
B54: REFUND ADMIN
B55: TOTAL REFUND
B56: PENCAIRAN ALL IN
B60: TENOR | F60: 1 | G60: =F60*12 -> 12 | I60: 2 | J60: =I60*12 -> 24 | L60: 3 | M60: =L60*12 -> 36 | O60: 4 | P60: =O60*12 -> 48 | R60: 5 | S60: =R60*12 -> 60
B62: PHPM | F62: =ROUNDDOWN(IF(F10>=1,VLOOKUP($B$10,'PHPM 1 DT Int'!$K$5:$L$848,2,0),0),-2) -> 275000000 | I62: =ROUNDDOWN(IF(I10>=1,VLOOKUP($B$10,'PHPM 1 DT Int'!$K$5:$L$848,2,0),0),-2) -> 275000000 | L62: =ROUNDDOWN(IF(L10>=1,VLOOKUP($B$10,'PHPM 1 DT Int'!$K$5:$L$848,2,0),0),-2) -> 275000000 | O62: =ROUNDDOWN(IF(O10>=1,VLOOKUP($B$10,'PHPM 1 DT Int'!$K$5:$L$848,2,0),0),-2) -> 275000000 | R62: =ROUNDDOWN(IF(R10>=1,VLOOKUP($B$10,'PHPM 1 DT Int'!$K$5:$L$848,2,0),0),-2) -> 275000000
B63: PENCAIRAN | F63: ='Home Int'!$I$107 -> 60000000 | I63: ='Home Int'!$I$107 -> 60000000 | L63: ='Home Int'!$I$107 -> 60000000 | O63: ='Home Int'!$I$107 -> 60000000 | R63: ='Home Int'!$I$107 -> 60000000
B64: TOTAL DP | F64: =$G$38+$G$39+$F$40+$F$41 -> 9935500 | I64: =$J$38+$J$39+$I$40+$I$41 -> 12554600 | L64: =$M$38+$M$39+$L$40+$L$41 -> 15188500 | O64: =$P$38+$P$39+$O$40+$O$41 -> 18373600 | R64: =$S$38+$S$39+$R$40+$R$41 -> 21308400
B65: DP NET | F65: =G65/F62 -> 0.74568909 | G65: =F62-(F63+F64) -> 205064500 | I65: =J65/I62 -> 0.73616509 | J65: =I62-(I63+I64) -> 202445400 | L65: =M65/L62 -> 0.72658727 | M65: =L62-(L63+L64) -> 199811500 | O65: =P65/O62 -> 0.71500509 | P65: =O62-(O63+O64) -> 196626400 | R65: =S65/R62 -> 0.70433309 | S65: =R62-(R63+R64) -> 193691600
B66: LTV | F66: =IF(F65>=F16,(100%-(G65/F62)),0%) -> 0.25431091 | G66: =F62*F66 -> 69935500 | I66: =IF(I65>=I16,(100%-(J65/I62)),0%) -> 0.26383491 | J66: =I62*I66 -> 72554600 | L66: =IF(L65>=L16,(100%-(M65/L62)),0%) -> 0.27341273 | M66: =L62*L66 -> 75188500 | O66: =IF(O65>=O16,(100%-(P65/O62)),0%) -> 0.28499491 | P66: =O62*O66 -> 78373600 | R66: =IF(R65>=R16,(100%-(S65/R62)),0%) -> 0.29566691 | S66: =R62*R66 -> 81308400
B67: BUNGA JUAL | F67: =$F$19 -> 0.10284585 | G67: =G66*F67 -> 7192575.8 | I67: =$I$19 -> 0.20363579 | J67: =J66*I67 -> 14774713 | L67: =$L$19 -> 0.30998986 | M67: =M66*L67 -> 23307673 | O67: =$O$19 -> 0.4218159 | P67: =P66*O67 -> 33059231 | R67: =$R$19 -> 0.53898789 | S67: =S66*R67 -> 43824243
B68: TOTAL AR | F68: =G66+G67 -> 77128076 | I68: =J66+J67 -> 87329313 | L68: =M66+M67 -> 98496173 | O68: =P66+P67 -> 1.1143283e+08 | R68: =S66+S67 -> 1.2513264e+08
B69: ANGSURAN | F69: =$G$9 -> 12 | G69: =IFERROR(ROUNDUP(F68/G9,-3),0) -> 6428000 | I69: =$J$9 -> 24 | J69: =IFERROR(ROUNDUP(I68/J9,-3),0) -> 3639000 | L69: =$M$9 -> 36 | M69: =IFERROR(ROUNDUP(L68/M9,-3),0) -> 2737000 | O69: =$P$9 -> 48 | P69: =IFERROR(ROUNDUP(O68/P9,-3),0) -> 2322000 | R69: =$S$9 -> 60 | S69: =IFERROR(ROUNDUP(R68/S9,-3),0) -> 2086000
B71: Pencairan | F71: Maksimal | J71: Pencairan | N71: ='Home Int'!$I$107 -> 60000000
B72: Tenor | E72: Pencairan | G72: Angsuran | J72: Tenor | M72: Pencairan | O72: Angsuran
B73: =$F$42 -> 12 | C73: Bulan | D73: =CONCATENATE($B$73," ",$C$73) -> 12 Bulan | E73: =IFERROR($F$49,0) -> 179564500 | G73: =IFERROR($F$21,0) -> 18335000 | J73: =$F$42 -> 12 | K73: Bulan | L73: =CONCATENATE($B$73," ",$C$73) -> 12 Bulan | M73: =IFERROR('Home Ext'!$I$75,0) -> 60000000 | O73: =IFERROR($G$69,0) -> 6428000
B74: =$I$42 -> 24 | C74: Bulan | D74: =CONCATENATE($B$74," ",$C$74) -> 24 Bulan | E74: =IFERROR($I$49,0) -> 176945400 | G74: =IFERROR($I$21,0) -> 10006000 | J74: =$I$42 -> 24 | K74: Bulan | L74: =CONCATENATE($B$74," ",$C$74) -> 24 Bulan | M74: =IFERROR('Home Ext'!$I$75,0) -> 60000000 | O74: =IFERROR($J$69,0) -> 3639000
B75: =$L$42 -> 36 | C75: Bulan | D75: =CONCATENATE($B$75," ",$C$75) -> 36 Bulan | E75: =IFERROR($L$49,0) -> 174311500 | G75: =IFERROR($L$21,0) -> 7260000 | J75: =$L$42 -> 36 | K75: Bulan | L75: =CONCATENATE($B$75," ",$C$75) -> 36 Bulan | M75: =IFERROR('Home Ext'!$I$75,0) -> 60000000 | O75: =IFERROR($M$69,) -> 2737000
B76: =$O$42 -> 48 | C76: Bulan | D76: =CONCATENATE($B$76," ",$C$76) -> 48 Bulan | E76: =IFERROR($O$49,0) -> 171126400 | G76: =IFERROR($O$21,0) -> 5910000 | J76: =$O$42 -> 48 | K76: Bulan | L76: =CONCATENATE($B$76," ",$C$76) -> 48 Bulan | M76: =IFERROR('Home Ext'!$I$75,0) -> 60000000 | O76: =IFERROR($P$69,0) -> 2322000
B77: =$R$42 -> 60 | C77: Bulan | D77: =CONCATENATE($B$77," ",$C$77) -> 60 Bulan | E77: =IFERROR($R$49,0) -> 168191600 | G77: =IFERROR($R$21,0) -> 5118000 | J77: =$R$42 -> 60 | K77: Bulan | L77: =CONCATENATE($B$77," ",$C$77) -> 60 Bulan | M77: =IFERROR('Home Ext'!$I$75,0) -> 60000000 | O77: =IFERROR($S$69,0) -> 2086000

Sheet UC Int
B4: Merk | D4: ='Home Int'!$K$13 -> HONDA | G4: Type Kendaraan | I4: ='Home Int'!$I$17 -> BRV | N4: Deposit Angsuran | P4: 0 | Q4: Up ACP | S4: 0.3
B5: Type Debitur | D5: ='Home Int'!$I$9 -> Perorangan (Wiraswasta) | G5: Model Kendaraan | I5: ='Home Int'!$K$17 -> ALL NEW BRV E CVT PRESTIGE SENSING | N5: BBNKB | O5: 0 | Q5: Up Rate | S5: 0
B6: Type Angsuran | D6: ='Home Int'!$I$61 -> ADDB | G6: Penggunaan Unit | I6: ='Home Int'!$I$13 -> Passenger | N6: PKB | O6: 0 | Q6: Up Adm | S6: 0
B7: Type Unit | D7: =VLOOKUP('Home Int'!$K$13,'PHPM 2 DT Ext'!$D$4:$E$54,2,0) -> Japan | G7: Product | I7: =CONCATENATE("Captive"," ",'Home Int'!$I$13," ","Low Rate") -> Captive Passenger Low Rate | N7: FAKTUR | O7: 0 | Q7: Up Provisi | S7: 0
B8: Thn (NIK) | D8: ='Home Int'!$I$21 -> 2025 | F8: =15-(2026-D8) -> 14 | G8: Asuransi | I8: ='Home Int'!$I$29 -> Comprehensive 1 tahun | N8: Asuransi | O8: BATAS BAWAH | Q8: Usia Debitur | S8: ='Home Int'!$K$9 -> 36-45 tahun
B9: TENOR | F9: 1 | G9: =F9*12 -> 12 | I9: 2 | J9: =I9*12 -> 24 | L9: 3 | M9: =L9*12 -> 36 | O9: 4 | P9: =O9*12 -> 48 | R9: 5 | S9: =R9*12 -> 60
B10: =CONCATENATE('Home Int'!$K$13,"-",'Home Int'!$I$17,"-",'Home Int'!$K$17) -> HONDA-BRV-ALL NEW BRV E CVT PRESTIGE SENSING | F10: =(16-F9)-(2026-$D$8) -> 14 | I10: =(16-I9)-(2026-$D$8) -> 13 | L10: =(16-L9)-(2026-$D$8) -> 12 | O10: =(16-O9)-(2026-$D$8) -> 11 | R10: =(16-R9)-(2026-$D$8) -> 10
B11: Harga OTR | D11: Showroom | F11: ='Home Int'!$I$135 -> 210000000 | I11: ='Home Int'!$I$135 -> 210000000 | L11: ='Home Int'!$I$135 -> 210000000 | O11: ='Home Int'!$I$135 -> 210000000 | R11: ='Home Int'!$I$135 -> 210000000
D12: PHPM | F12: =IF(F10>=1,VLOOKUP($B$10,'PHPM 1 DT Int'!$K$5:$L$848,2,0),0) -> 275000026 | I12: =IF(I10>=1,VLOOKUP($B$10,'PHPM 1 DT Int'!$K$5:$L$848,2,0),0) -> 275000026 | L12: =IF(L10>=1,VLOOKUP($B$10,'PHPM 1 DT Int'!$K$5:$L$848,2,0),0) -> 275000026 | O12: =IF(O10>=1,VLOOKUP($B$10,'PHPM 1 DT Int'!$K$5:$L$848,2,0),0) -> 275000026 | R12: =IF(R10>=1,VLOOKUP($B$10,'PHPM 1 DT Int'!$K$5:$L$848,2,0),0) -> 275000026
D13: ROUNDDOWN PHPM | F13: =ROUNDDOWN(F12,-2) -> 275000000 | I13: =ROUNDDOWN(I12,-2) -> 275000000 | L13: =ROUNDDOWN(L12,-2) -> 275000000 | O13: =ROUNDDOWN(O12,-2) -> 275000000 | R13: =ROUNDDOWN(R12,-2) -> 275000000
B14: Deviasi (%) | D14: (Rp.) | F14: =IFERROR(G14/F11,0) -> 0 | G14: =IF(F11<=F12,0,F11-F13) -> 0 | I14: =IFERROR(J14/I11,0) -> 0 | J14: =IF(I11<=I12,0,I11-I13) -> 0 | L14: =IFERROR(M14/L11,0) -> 0 | M14: =IF(L11<=L12,0,L11-L13) -> 0 | O14: =IFERROR(P14/O11,0) -> 0 | P14: =IF(O11<=O12,0,O11-O13) -> 0 | R14: =IFERROR(S14/R11,0) -> 0 | S14: =IF(R11<=R12,0,R11-R13) -> 0
B15: Sum Insured | D15: % | E15: Rp. | F15: 1 | G15: =F11*F15 -> 210000000 | I15: 0.9 | J15: =I11*I15 -> 189000000 | L15: 0.8 | M15: =L11*L15 -> 168000000 | O15: 0.7 | P15: =O11*O15 -> 147000000 | R15: 0.7 | S15: =R11*R15 -> 147000000
B16: Net DP | D16: % | E16: Rp. | F16: =IF('Home Int'!$I$9="Perorangan (Wiraswasta)",30%+F14,IF(AND($I$6="Commercial",$D$7="Non Japan"),20%,10%)+F14) -> 0.3 | G16: =F11*F16 -> 63000000 | I16: =IF('Home Int'!$I$9="Perorangan (Wiraswasta)",30%+I14,IF(AND($I$6="Commercial",$D$7="Non Japan"),20%,10%)+I14) -> 0.3 | J16: =I11*I16 -> 63000000 | L16: =IF('Home Int'!$I$9="Perorangan (Wiraswasta)",30%+L14,IF(AND($I$6="Commercial",$D$7="Non Japan"),20%,10%)+L14) -> 0.3 | M16: =L11*L16 -> 63000000 | O16: =IF('Home Int'!$I$9="Perorangan (Wiraswasta)",30%+O14,IF(AND($I$6="Commercial",$D$7="Non Japan"),20%,10%)+O14) -> 0.3 | P16: =O11*O16 -> 63000000 | R16: =IF('Home Int'!$I$9="Perorangan (Wiraswasta)",30%+R14,IF(AND($I$6="Commercial",$D$7="Non Japan"),20%,10%)+R14) -> 0.3 | S16: =R11*R16 -> 63000000
B17: LTV | D17: % | E17: Rp. | F17: =100%-F16 -> 0.7 | G17: =F11-G16 -> 147000000 | I17: =100%-I16 -> 0.7 | J17: =I11-J16 -> 147000000 | L17: =100%-L16 -> 0.7 | M17: =L11-M16 -> 147000000 | O17: =100%-O16 -> 0.7 | P17: =O11-P16 -> 147000000 | R17: =100%-R16 -> 0.7 | S17: =R11-S16 -> 147000000
B18: RATE p.a (%) | D18: Eff R | E18: Flat Rate | F18: =VLOOKUP($I$7,Product!$B$6:$K$25,2,0) -> 0.144699 | G18: =IF($D$6="ADDM",(((PMT(F18/12,G9,1,0,1)*(-1))*G9)-1)*12/G9,IF($D$6="ADDB",(((PMT(F18/12,G9,1,0,0)*(-1))*G9)-1)*12/G9," ")) -> 0.080100364 | H18: =G18+$S$5 -> 0.080100364 | I18: =VLOOKUP($I$7,Product!$B$6:$K$25,2,0) -> 0.144699 | J18: =IF($D$6="ADDM",(((PMT(I18/12,J9,1,0,1)*(-1))*J9)-1)*12/J9,IF($D$6="ADDB",(((PMT(I18/12,J9,1,0,0)*(-1))*J9)-1)*12/J9," ")) -> 0.078822027 | K18: =J18+$S$5 -> 0.078822027 | L18: =VLOOKUP($I$7,Product!$B$6:$K$25,2,0) -> 0.144699 | M18: =IF($D$6="ADDM",(((PMT(L18/12,M9,1,0,1)*(-1))*M9)-1)*12/M9,IF($D$6="ADDB",(((PMT(L18/12,M9,1,0,0)*(-1))*M9)-1)*12/M9," ")) -> 0.079542261 | N18: =M18+$S$5 -> 0.079542261 | O18: =VLOOKUP($I$7,Product!$B$6:$K$25,2,0) -> 0.144699 | P18: =IF($D$6="ADDM",(((PMT(O18/12,P9,1,0,1)*(-1))*P9)-1)*12/P9,IF($D$6="ADDB",(((PMT(O18/12,P9,1,0,0)*(-1))*P9)-1)*12/P9," ")) -> 0.080753319 | Q18: =P18+$S$5 -> 0.080753319 | R18: =VLOOKUP($I$7,Product!$B$6:$K$25,2,0) -> 0.144699 | S18: =IF($D$6="ADDM",(((PMT(R18/12,S9,1,0,1)*(-1))*S9)-1)*12/S9,IF($D$6="ADDB",(((PMT(R18/12,S9,1,0,0)*(-1))*S9)-1)*12/S9," ")) -> 0.082150977 | T18: =S18+$S$5 -> 0.082150977
B19: Bunga Jual | D19: % | E19: Rp. | F19: =(H18*F9) -> 0.080100364 | G19: =G17*F19 -> 11774753 | I19: =(K18*I9) -> 0.15764405 | J19: =J17*I19 -> 23173676 | L19: =(N18*L9) -> 0.23862678 | M19: =M17*L19 -> 35078137 | O19: =(Q18*O9) -> 0.32301328 | P19: =P17*O19 -> 47482952 | R19: =(T18*R9) -> 0.41075488 | S19: =S17*R19 -> 60380968
B20: TOTAL A/R | G20: =G17+G19 -> 1.5877475e+08 | J20: =J17+J19 -> 1.7017368e+08 | M20: =M17+M19 -> 1.8207814e+08 | P20: =P17+P19 -> 1.9448295e+08 | S20: =S17+S19 -> 2.0738097e+08
B21: ANGSURAN | F21: =IF(F12=0,0,ROUNDUP(G20/G9,-3)) -> 13232000 | I21: =IF(I12=0,0,ROUNDUP(J20/J9,-3)) -> 7091000 | L21: =IF(L12=0,0,ROUNDUP(M20/M9,-3)) -> 5058000 | O21: =IF(O12=0,0,ROUNDUP(P20/P9,-3)) -> 4052000 | R21: =IF(R12=0,0,ROUNDUP(S20/S9,-3)) -> 3457000
B22: TOTAL BAYAR PERTAMA
B23: ASURANSI | F23: =IF(OR($I$8="Comprehensive 1 tahun",$I$8="Comprehensive All Tenor"),"Comprehensive","TLO") -> Comprehensive | I23: =IF($I$8="Comprehensive All Tenor","Comprehensive","TLO") -> TLO | L23: =IF($I$8="Comprehensive All Tenor","Comprehensive","TLO") -> TLO | O23: =IF($I$8="Comprehensive All Tenor","Comprehensive","TLO") -> TLO | R23: =IF($I$8="Comprehensive All Tenor","Comprehensive","TLO") -> TLO
C24: Casco | F24: =IF(F23="Comprehensive",IF(AND(G15>=1,G15<=125000000),'Asr Int'!$C$22,IF(AND(G15>125000000,G15<=200000000),'Asr Int'!$C$23,IF(AND(G15>200000000,G15<=400000000),'Asr Int'!$C$24,IF(AND(G15>400000000,G15<=800000000),'Asr Int'!$C$25,'Asr Int'!$C$26)))),IF(AND(G15>=1,G15<=125000000),'Asr Int'!$D$22,IF(AND(G15>125000000,G15<=200000000),'Asr Int'!$D$23,IF(AND(G15>200000000,G15<=400000000),'Asr Int'!$D$24,IF(AND(G15>400000000,G15<=800000000),'Asr Int'!$D$25,'Asr Int'!$D$26))))) -> 0.0208 | G24: =F24*G15 -> 4368000 | I24: =IF(I23="Comprehensive",IF(AND(J15>=1,J15<=125000000),'Asr Int'!$C$22,IF(AND(J15>125000000,J15<=200000000),'Asr Int'!$C$23,IF(AND(J15>200000000,J15<=400000000),'Asr Int'!$C$24,IF(AND(J15>400000000,J15<=800000000),'Asr Int'!$C$25,'Asr Int'!$C$26)))),IF(AND(J15>=1,J15<=125000000),'Asr Int'!$D$22,IF(AND(J15>125000000,J15<=200000000),'Asr Int'!$D$23,IF(AND(J15>200000000,J15<=400000000),'Asr Int'!$D$24,IF(AND(J15>400000000,J15<=800000000),'Asr Int'!$D$25,'Asr Int'!$D$26))))) -> 0.0044 | J24: =(I24*J15)+G24 -> 5199600 | L24: =IF(L23="Comprehensive",IF(AND(M15>=1,M15<=125000000),'Asr Int'!$C$22,IF(AND(M15>125000000,M15<=200000000),'Asr Int'!$C$23,IF(AND(M15>200000000,M15<=400000000),'Asr Int'!$C$24,IF(AND(M15>400000000,M15<=800000000),'Asr Int'!$C$25,'Asr Int'!$C$26)))),IF(AND(M15>=1,M15<=125000000),'Asr Int'!$D$22,IF(AND(M15>125000000,M15<=200000000),'Asr Int'!$D$23,IF(AND(M15>200000000,M15<=400000000),'Asr Int'!$D$24,IF(AND(M15>400000000,M15<=800000000),'Asr Int'!$D$25,'Asr Int'!$D$26))))) -> 0.0044 | M24: =(L24*M15)+J24 -> 5938800 | O24: =IF(O23="Comprehensive",IF(AND(P15>=1,P15<=125000000),'Asr Int'!$C$22,IF(AND(P15>125000000,P15<=200000000),'Asr Int'!$C$23,IF(AND(P15>200000000,P15<=400000000),'Asr Int'!$C$24,IF(AND(P15>400000000,P15<=800000000),'Asr Int'!$C$25,'Asr Int'!$C$26)))),IF(AND(P15>=1,P15<=125000000),'Asr Int'!$D$22,IF(AND(P15>125000000,P15<=200000000),'Asr Int'!$D$23,IF(AND(P15>200000000,P15<=400000000),'Asr Int'!$D$24,IF(AND(P15>400000000,P15<=800000000),'Asr Int'!$D$25,'Asr Int'!$D$26))))) -> 0.0044 | P24: =(O24*P15)+M24 -> 6585600 | R24: =IF(R23="Comprehensive",IF(AND(S15>=1,S15<=125000000),'Asr Int'!$C$22,IF(AND(S15>125000000,S15<=200000000),'Asr Int'!$C$23,IF(AND(S15>200000000,S15<=400000000),'Asr Int'!$C$24,IF(AND(S15>400000000,S15<=800000000),'Asr Int'!$C$25,'Asr Int'!$C$26)))),IF(AND(S15>=1,S15<=125000000),'Asr Int'!$D$22,IF(AND(S15>125000000,S15<=200000000),'Asr Int'!$D$23,IF(AND(S15>200000000,S15<=400000000),'Asr Int'!$D$24,IF(AND(S15>400000000,S15<=800000000),'Asr Int'!$D$25,'Asr Int'!$D$26))))) -> 0.0044 | S24: =(R24*S15)+P24 -> 7232400
C25: Loading | F25: =IFERROR(IF(F23="Comprehensive",VLOOKUP($D$8,'Asr Ext'!$L$6:$N$20,3,0),0),0) -> 0 | G25: =G24*F25 -> 0 | I25: =IFERROR(IF(I23="Comprehensive",VLOOKUP($D$8,'Asr Ext'!$L$6:$N$20,3,0),0),0) -> 0 | J25: =(J24*I25)+G25 -> 0 | L25: =IFERROR(IF(L23="Comprehensive",VLOOKUP($D$8,'Asr Ext'!$L$6:$N$20,3,0),0),0) -> 0 | M25: =(M24*L25)+J25 -> 0 | O25: =IFERROR(IF(O23="Comprehensive",VLOOKUP($D$8,'Asr Ext'!$L$6:$N$20,3,0),0),0) -> 0 | P25: =(P24*O25)+M25 -> 0 | R25: =IFERROR(IF(R23="Comprehensive",VLOOKUP($D$8,'Asr Ext'!$L$6:$N$20,3,0),0),0) -> 0 | S25: =(S24*R25)+P25 -> 0
C26: Banjir | E26: TIDAK | F26: =IF($E$26="YA",IF(F23="Comprehensive",0.1%,0%),0) -> 0 | G26: =F26*G15 -> 0 | I26: =IF($E$26="YA",IF(I23="Comprehensive",0.1%,0%),0) -> 0 | J26: =(I26*J15)+G26 -> 0 | L26: =IF($E$26="YA",IF(L23="Comprehensive",0.1%,0%),0) -> 0 | M26: =(L26*M15)+J26 -> 0 | O26: =IF($E$26="YA",IF(O23="Comprehensive",0.1%,0%),0) -> 0 | P26: =(O26*P15)+M26 -> 0 | R26: =IF($E$26="YA",IF(R23="Comprehensive",0.1%,0%),0) -> 0 | S26: =(R26*S15)+P26 -> 0
C27: Gempa | E27: TIDAK | F27: =IF($E$27="YA",IF(F23="Comprehensive",0.1%,0%),0) -> 0 | G27: =F27*G15 -> 0 | I27: =IF($E$27="YA",IF(I23="Comprehensive",0.1%,0%),0) -> 0 | J27: =(I27*J15)+G27 -> 0 | L27: =IF($E$27="YA",IF(L23="Comprehensive",0.1%,0%),0) -> 0 | M27: =(L27*M15)+J27 -> 0 | O27: =IF($E$27="YA",IF(O23="Comprehensive",0.1%,0%),0) -> 0 | P27: =(O27*P15)+M27 -> 0 | R27: =IF($E$27="YA",IF(R23="Comprehensive",0.1%,0%),0) -> 0 | S27: =(R27*S15)+P27 -> 0
C28: Huru-hara | E28: TIDAK | F28: =IF($E$28="YA",IF(F23="Comprehensive",0.05%,0%),0) -> 0 | G28: =F28*G15 -> 0 | I28: =IF($E$28="YA",IF(I23="Comprehensive",0.05%,0%),0) -> 0 | J28: =(I28*J15)+G28 -> 0 | L28: =IF($E$28="YA",IF(L23="Comprehensive",0.05%,0%),0) -> 0 | M28: =(L28*M15)+J28 -> 0 | O28: =IF($E$28="YA",IF(O23="Comprehensive",0.05%,0%),0) -> 0 | P28: =(O28*P15)+M28 -> 0 | R28: =IF($E$28="YA",IF(R23="Comprehensive",0.05%,0%),0) -> 0 | S28: =(R28*S15)+P28 -> 0
C29: Teroris | E29: TIDAK | F29: =IF($E$29="YA",IF(F23="Comprehensive",0.05%,0%),0) -> 0 | G29: =F29*G15 -> 0 | I29: =IF($E$29="YA",IF(I23="Comprehensive",0.05%,0%),0) -> 0 | J29: =(I29*J15)+G29 -> 0 | L29: =IF($E$29="YA",IF(L23="Comprehensive",0.05%,0%),0) -> 0 | M29: =(L29*M15)+J29 -> 0 | O29: =IF($E$29="YA",IF(O23="Comprehensive",0.05%,0%),0) -> 0 | P29: =(O29*P15)+M29 -> 0 | R29: =IF($E$29="YA",IF(R23="Comprehensive",0.05%,0%),0) -> 0 | S29: =(R29*S15)+P29 -> 0
C30: ASURANSI CASCO + PERLUASAN | F30: =SUM(G24:H29) -> 4368000 | I30: =SUM(J24:K29) -> 5199600 | L30: =SUM(M24:N29) -> 5938800 | O30: =SUM(P24:Q29) -> 6585600 | R30: =SUM(S24:T29) -> 7232400
C31: GAP | E31: TIDAK
C32: HIC | E32: TIDAK
C33: TJH | D33: 0 | E33: TIDAK | G33: =IF(F23="Comprehensive",VLOOKUP(F9,'Asr Int'!$G$40:$M$44,7,0),0) -> 0 | J33: =IF(I23="Comprehensive",VLOOKUP(I9,'Asr Int'!$G$40:$M$44,7,0),0)+G33 -> 0 | M33: =IF(L23="Comprehensive",VLOOKUP(L9,'Asr Int'!$G$40:$M$44,7,0),0)+J33 -> 0 | P33: =IF(O23="Comprehensive",VLOOKUP(O9,'Asr Int'!$G$40:$M$44,7,0),0)+M33 -> 0 | S33: =IF(R23="Comprehensive",VLOOKUP(R9,'Asr Int'!$G$40:$M$44,7,0),0)+P33 -> 0
C34: Pengemudi | D34: 0 | E34: TIDAK | F34: =IF($E$34="YA",IF(F23="Comprehensive",0.5%,0%),0) -> 0 | G34: =$D$34*F34 -> 0 | I34: =IF($E$34="YA",IF(I23="Comprehensive",0.5%,0%),0) -> 0 | J34: =(I34*$D$34)+G34 -> 0 | L34: =IF($E$34="YA",IF(L23="Comprehensive",0.5%,0%),0) -> 0 | M34: =(L34*$D$34)+J34 -> 0 | O34: =IF($E$34="YA",IF(O23="Comprehensive",0.5%,0%),0) -> 0 | P34: =(O34*$D$34)+M34 -> 0 | R34: =IF($E$34="YA",IF(R23="Comprehensive",0.5%,0%),0) -> 0 | S34: =(R34*$D$34)+P34 -> 0
C35: Penumpang | D35: 0 | E35: 0 | F35: =IF(AND(F23="Comprehensive",$E$35>0),0.1%,0%)*E35 -> 0 | G35: =F35*$D$35 -> 0 | I35: =IF(AND(I23="Comprehensive",$E$35>0),0.1%,0%)*H35 -> 0 | J35: =(I35*$D$35)+G35 -> 0 | L35: =IF(AND(L23="Comprehensive",$E$35>0),0.1%,0%)*K35 -> 0 | M35: =(L35*$D$35)+J35 -> 0 | O35: =IF(AND(O23="Comprehensive",$E$35>0),0.1%,0%)*N35 -> 0 | P35: =(O35*$D$35)+M35 -> 0 | R35: =IF(AND(R23="Comprehensive",$E$35>0),0.1%,0%)*Q35 -> 0 | S35: =(R35*$D$35)+P35 -> 0
C36: ACP | E36: =IF('Home Int'!$I$9="Badan Hukum Usaha","Tidak","Ya") -> Ya | F36: =IF($E$36="Ya",IF(OR($I$6="Passenger",G17<1000000000),VLOOKUP($S$8,'Asr Int'!$K$70:$P$73,F9+1,0),0),0) -> 0.0065 | G36: =F11*F36 -> 1365000 | I36: =IF($E$36="Ya",IF(OR($I$6="Passenger",J17<1000000000),VLOOKUP($S$8,'Asr Int'!$K$70:$P$73,I9+1,0),0),0) -> 0.013 | J36: =I11*I36 -> 2730000 | L36: =IF($E$36="Ya",IF(OR($I$6="Passenger",M17<1000000000),VLOOKUP($S$8,'Asr Int'!$K$70:$P$73,L9+1,0),0),0) -> 0.01989 | M36: =L11*L36 -> 4176900 | O36: =IF($E$36="Ya",IF(OR($I$6="Passenger",P17<1000000000),VLOOKUP($S$8,'Asr Int'!$K$70:$P$73,O9+1,0),0),0) -> 0.02912 | P36: =O11*O36 -> 6115200 | R36: =IF($E$36="Ya",IF(OR($I$6="Passenger",S17<1000000000),VLOOKUP($S$8,'Asr Int'!$K$70:$P$73,R9+1,0),0),0) -> 0.03744 | S36: =R11*R36 -> 7862400
C37: GARANSI MESIN | E37: YA | G37: =IF($E$37="ya",1500000,0) -> 1500000 | J37: =IF($E$37="ya",1500000,0) -> 1500000 | M37: =IF($E$37="ya",1500000,0) -> 1500000 | P37: =IF($E$37="ya",1500000,0) -> 1500000 | S37: =IF($E$37="ya",1500000,0) -> 1500000
B38: TOTAL ASURANSI | F38: =ROUNDUP(SUM(G31:H37)+F30,-2) -> 7233000 | I38: =ROUNDUP(SUM(J31:K37)+I30,-2) -> 9429600 | L38: =ROUNDUP(SUM(M31:N37)+L30,-2) -> 11615700 | O38: =ROUNDUP(SUM(P31:Q37)+O30,-2) -> 14200800 | R38: =ROUNDUP(SUM(S31:T37)+R30,-2) -> 16594800
B39: PROVISI | E39: =S7 -> 0 | F39: =VLOOKUP($I$7,Product!$B$6:$K$25,10,0)+$E$39 -> 0 | G39: =ROUNDUP(F39*G17,-2) -> 0 | I39: =VLOOKUP($I$7,Product!$B$6:$K$25,10,0)+$E$39 -> 0 | J39: =I39*J17 -> 0 | L39: =VLOOKUP($I$7,Product!$B$6:$K$25,10,0)+$E$39 -> 0 | M39: =L39*M17 -> 0 | O39: =VLOOKUP($I$7,Product!$B$6:$K$25,10,0)+$E$39 -> 0 | P39: =O39*P17 -> 0 | R39: =VLOOKUP($I$7,Product!$B$6:$K$25,10,0)+$E$39 -> 0 | S39: =R39*S17 -> 0
B40: ADMINISTRASI | F40: =VLOOKUP($I$7,Product!$B$6:$K$25,9,0) -> 4700000 | I40: =VLOOKUP($I$7,Product!$B$6:$K$25,9,0) -> 4700000 | L40: =VLOOKUP($I$7,Product!$B$6:$K$25,9,0) -> 4700000 | O40: =VLOOKUP($I$7,Product!$B$6:$K$25,9,0) -> 4700000 | R40: =VLOOKUP($I$7,Product!$B$6:$K$25,9,0) -> 4700000
B41: FIDUCIA | F41: =IF(AND(F11>0,F11<=25000000),350000,IF(AND(F11>25000000,F11<=50000000),375000,IF(AND(F11>50000000,F11<=100000000),400000,IF(AND(F11>100000000,F11<=250000000),500000,IF(AND(F11>250000000,F11<=500000000),750000,IF(AND(F11>500000000,F11<=1000000000),1150000,2250000)))))) -> 500000 | I41: =IF(AND(I11>0,I11<=25000000),350000,IF(AND(I11>25000000,I11<=50000000),375000,IF(AND(I11>50000000,I11<=100000000),400000,IF(AND(I11>100000000,I11<=250000000),500000,IF(AND(I11>250000000,I11<=500000000),750000,IF(AND(I11>500000000,I11<=1000000000),1150000,2250000)))))) -> 500000 | L41: =IF(AND(L11>0,L11<=25000000),350000,IF(AND(L11>25000000,L11<=50000000),375000,IF(AND(L11>50000000,L11<=100000000),400000,IF(AND(L11>100000000,L11<=250000000),500000,IF(AND(L11>250000000,L11<=500000000),750000,IF(AND(L11>500000000,L11<=1000000000),1150000,2250000)))))) -> 500000 | O41: =IF(AND(O11>0,O11<=25000000),350000,IF(AND(O11>25000000,O11<=50000000),375000,IF(AND(O11>50000000,O11<=100000000),400000,IF(AND(O11>100000000,O11<=250000000),500000,IF(AND(O11>250000000,O11<=500000000),750000,IF(AND(O11>500000000,O11<=1000000000),1150000,2250000)))))) -> 500000 | R41: =IF(AND(R11>0,R11<=25000000),350000,IF(AND(R11>25000000,R11<=50000000),375000,IF(AND(R11>50000000,R11<=100000000),400000,IF(AND(R11>100000000,R11<=250000000),500000,IF(AND(R11>250000000,R11<=500000000),750000,IF(AND(R11>500000000,R11<=1000000000),1150000,2250000)))))) -> 500000
B42: ANGSURAN PERTAMA | F42: =IF($D$6="ADDM",11,12) -> 12 | G42: =IF($D$6="ADDM",ROUNDUP(G20/G9,-3),0) -> 0 | I42: =IF($D$6="ADDM",23,24) -> 24 | J42: =IF($D$6="ADDM",ROUNDUP(J20/J9,-3),0) -> 0 | L42: =IF($D$6="ADDM",35,36) -> 36 | M42: =IF($D$6="ADDM",ROUNDUP(M20/M9,-3),0) -> 0 | O42: =IF($D$6="ADDM",47,48) -> 48 | P42: =IF($D$6="ADDM",ROUNDUP(P20/P9,-3),0) -> 0 | R42: =IF($D$6="ADDM",59,60) -> 60 | S42: =IF($D$6="ADDM",ROUNDUP(S20/S9,-3),0) -> 0
B43: TOTAL BAYAR PERTAMA | F43: =(G16+F38+G39+F40+F41+G42) -> 75433000 | I43: =(J16+I38+J39+I40+I41+J42) -> 77629600 | L43: =(M16+L38+M39+L40+L41+M42) -> 79815700 | O43: =(P16+O38+P39+O40+O41+P42) -> 82400800 | R43: =(S16+R38+S39+R40+R41+S42) -> 84794800
B44: PENCAIRAN GROSS | F44: =F11-F43 -> 134567000 | I44: =I11-I43 -> 132370400 | L44: =L11-L43 -> 130184300 | O44: =O11-O43 -> 127599200 | R44: =R11-R43 -> 125205200
B45: BBNKB | G45: =$O$5 -> 0 | J45: =$O$5 -> 0 | M45: =$O$5 -> 0 | P45: =$O$5 -> 0 | S45: =$O$5 -> 0
B46: PKB | G46: =$O$6 -> 0 | J46: =$O$6 -> 0 | M46: =$O$6 -> 0 | P46: =$O$6 -> 0 | S46: =$O$6 -> 0
B47: FAKTUR | G47: =$O$7 -> 0 | J47: =$O$7 -> 0 | M47: =$O$7 -> 0 | P47: =$O$7 -> 0 | S47: =$O$7 -> 0
B48: DEPOSIT ANGSURAN | E48: =P4 -> 0 | F48: =F21*$E$48 -> 0 | I48: =I21*$E$48 -> 0 | L48: =L21*$E$48 -> 0 | O48: =O21*$E$48 -> 0 | R48: =R21*$E$48 -> 0
B49: PECAIRAN NETO | F49: =IF(F12=0,0,(F44-(G45+G46+G47+F48))) -> 134567000 | I49: =IF(I12=0,0,(I44-(J45+J46+J47+I48))) -> 132370400 | L49: =IF(L12=0,0,(L44-(M45+M46+M47+L48))) -> 130184300 | O49: =IF(O12=0,0,(O44-(P45+P46+P47+O48))) -> 127599200 | R49: =IF(R12=0,0,(R44-(S45+S46+S47+R48))) -> 125205200
B51: REFUND ASURANSI | D51: 0.25 | E51: 0 | F51: =(F30*$D$51)*$E$51 -> 0 | I51: =(I30*$D$51)*$E$51 -> 0 | L51: =(L30*$D$51)*$E$51 -> 0 | O51: =(O30*$D$51)*$E$51 -> 0 | R51: =(R30*$D$51)*$E$51 -> 0
B52: REFUND BUNGA | D52: =$S$5 -> 0 | E52: 0.8 | F52: =((G17*($D$52*F9))/((1+F19))*$E$52) -> 0 | I52: =((J17*($D$52*I9))/((1+I19))*$E$52) -> 0 | L52: =((M17*($D$52*L9))/((1+L19))*$E$52) -> 0 | O52: =((P17*($D$52*O9))/((1+O19))*$E$52) -> 0 | R52: =((S17*($D$52*R9))/((1+R19))*$E$52) -> 0
B53: REFUND PROVISI | D53: =$S$7 -> 0 | E53: 0.8 | F53: =G39*$E$53 -> 0 | I53: =J39*$E$53 -> 0 | L53: =M39*$E$53 -> 0 | O53: =P39*$E$53 -> 0 | R53: =S39*$E$53 -> 0
B54: REFUND ADMIN | D54: =$S$6 -> 0 | E54: 0.8 | F54: =$D$54*$E$54 -> 0 | I54: =$D$54*$E$54 -> 0 | L54: =$D$54*$E$54 -> 0 | O54: =$D$54*$E$54 -> 0 | R54: =$D$54*$E$54 -> 0
B55: TOTAL REFUND | F55: =ROUNDDOWN(SUM(F51:H54),-3) -> 0 | I55: =ROUNDDOWN(SUM(I51:K54),-3) -> 0 | L55: =ROUNDDOWN(SUM(L51:N54),-3) -> 0 | O55: =ROUNDDOWN(SUM(O51:Q54),-3) -> 0 | R55: =ROUNDDOWN(SUM(R51:T54),-3) -> 0
B56: PENCAIRAN ALL IN | F56: =$F$49+$F$55 -> 134567000 | I56: =$I$49+$I$55 -> 132370400 | L56: =$L$49+$L$55 -> 130184300 | O56: =$O$49+$O$55 -> 127599200 | R56: =$R$49+$R$55 -> 125205200
B60: TENOR | F60: 1 | G60: =F60*12 -> 12 | I60: 2 | J60: =I60*12 -> 24 | L60: 3 | M60: =L60*12 -> 36 | O60: 4 | P60: =O60*12 -> 48 | R60: 5 | S60: =R60*12 -> 60
B61: Harga Pasar | F61: =F11 -> 210000000 | I61: =I11 -> 210000000 | L61: =L11 -> 210000000 | O61: =O11 -> 210000000 | R61: =R11 -> 210000000
B62: PHPM | F62: =ROUNDDOWN(IF(F10>=1,VLOOKUP($B$10,'PHPM 1 DT Int'!$K$5:$L$848,2,0),0),-2) -> 275000000 | I62: =ROUNDDOWN(IF(I10>=1,VLOOKUP($B$10,'PHPM 1 DT Int'!$K$5:$L$848,2,0),0),-2) -> 275000000 | L62: =ROUNDDOWN(IF(L10>=1,VLOOKUP($B$10,'PHPM 1 DT Int'!$K$5:$L$848,2,0),0),-2) -> 275000000 | O62: =ROUNDDOWN(IF(O10>=1,VLOOKUP($B$10,'PHPM 1 DT Int'!$K$5:$L$848,2,0),0),-2) -> 275000000 | R62: =ROUNDDOWN(IF(R10>=1,VLOOKUP($B$10,'PHPM 1 DT Int'!$K$5:$L$848,2,0),0),-2) -> 275000000
B63: Total DP | F63: ='Home Int'!$I$161 -> 35000000 | I63: ='Home Int'!$I$161 -> 35000000 | L63: ='Home Int'!$I$161 -> 35000000 | O63: ='Home Int'!$I$161 -> 35000000 | R63: ='Home Int'!$I$161 -> 35000000
B64: TOTAL BAYAR PERTAMA | F64: =F65+F66+F67+F68 -> 12433000 | I64: =I65+I66+I67+I68 -> 14629600 | L64: =L65+L66+L67+L68 -> 16815700 | O64: =O65+O66+O67+O68 -> 19400800 | R64: =R65+R66+R67+R68 -> 21794800
C65: ASURANSI | F65: =F38 -> 7233000 | I65: =I38 -> 9429600 | L65: =L38 -> 11615700 | O65: =O38 -> 14200800 | R65: =R38 -> 16594800
C66: PROVISI | F66: =G39 -> 0 | I66: =J39 -> 0 | L66: =M39 -> 0 | O66: =P39 -> 0 | R66: =S39 -> 0
C67: ADMINISTRASI | F67: =F40 -> 4700000 | I67: =I40 -> 4700000 | L67: =L40 -> 4700000 | O67: =O40 -> 4700000 | R67: =R40 -> 4700000
C68: FIDUCIA | F68: =F41 -> 500000 | I68: =I41 -> 500000 | L68: =L41 -> 500000 | O68: =O41 -> 500000 | R68: =R41 -> 500000
C69: ANGSURAN PERBULAN | F69: =ROUNDUP(IF('Home Int'!$I$61="ADDM",((F61-(F63-F64))*(1+F19))/(G9-(1+F19)),((F61-(F63-F64))*(1+F19))/G9),-3) -> 16871000 | I69: =ROUNDUP(IF('Home Int'!$I$61="ADDM",((I61-(I63-I64))*(1+I19))/(J9-(1+I19)),((I61-(I63-I64))*(1+I19))/J9),-3) -> 9147000 | L69: =ROUNDUP(IF('Home Int'!$I$61="ADDM",((L61-(L63-L64))*(1+L19))/(M9-(1+L19)),((L61-(L63-L64))*(1+L19))/M9),-3) -> 6600000 | O69: =ROUNDUP(IF('Home Int'!$I$61="ADDM",((O61-(O63-O64))*(1+O19))/(P9-(1+O19)),((O61-(O63-O64))*(1+O19))/P9),-3) -> 5359000 | R69: =ROUNDUP(IF('Home Int'!$I$61="ADDM",((R61-(R63-R64))*(1+R19))/(S9-(1+R19)),((R61-(R63-R64))*(1+R19))/S9),-3) -> 4628000
B70: DP NET | F70: =G70/F61 -> 0.1074619 | G70: =IF('Home Int'!$I$61="ADDM",F63-(F64+F69),F63-F64) -> 22567000 | I70: =J70/I61 -> 0.097001905 | J70: =IF('Home Int'!$I$61="ADDM",I63-(I64+I69),I63-I64) -> 20370400 | L70: =M70/L61 -> 0.086591905 | M70: =IF('Home Int'!$I$61="ADDM",L63-(L64+L69),L63-L64) -> 18184300 | O70: =P70/O61 -> 0.074281905 | P70: =IF('Home Int'!$I$61="ADDM",O63-(O64+O69),O63-O64) -> 15599200 | R70: =S70/R61 -> 0.062881905 | S70: =IF('Home Int'!$I$61="ADDM",R63-(R64+R69),R63-R64) -> 13205200
B71: LTV | F71: =IF(F70>=F16,(100%-(G70/F61)),0%) -> 0 | G71: =F61-G70 -> 187433000 | I71: =IF(I70>=I16,(100%-(J70/I61)),0%) -> 0 | J71: =I61-J70 -> 189629600 | L71: =IF(L70>=L16,(100%-(M70/L61)),0%) -> 0 | M71: =L61-M70 -> 191815700 | O71: =IF(O70>=O16,(100%-(P70/O61)),0%) -> 0 | P71: =O61-P70 -> 194400800 | R71: =IF(R70>=R16,(100%-(S70/R61)),0%) -> 0 | S71: =R61-S70 -> 196794800
B72: BUNGA JUAL | F72: =$F$19 -> 0.080100364 | G72: =G71*F72 -> 15013451 | I72: =$I$19 -> 0.15764405 | J72: =J71*I72 -> 29893979 | L72: =$L$19 -> 0.23862678 | M72: =M71*L72 -> 45772363 | O72: =$O$19 -> 0.32301328 | P72: =P71*O72 -> 62794040 | R72: =$R$19 -> 0.41075488 | S72: =S71*R72 -> 80834425
B73: TOTAL AR | F73: =G71+G72 -> 2.0244645e+08 | I73: =J71+J72 -> 2.1952358e+08 | L73: =M71+M72 -> 2.3758806e+08 | O73: =P71+P72 -> 2.5719484e+08 | R73: =S71+S72 -> 2.7762923e+08
B74: ANGSURAN | F74: =$G$9 -> 12 | G74: =IF(F71=0%,0,ROUNDUP((G71*(1+F19))/G9,-3)) -> 0 | I74: =$J$9 -> 24 | J74: =IF(I71=0%,0,ROUNDUP((J71*(1+I19))/J9,-3)) -> 0 | L74: =$M$9 -> 36 | M74: =IF(L71=0%,0,ROUNDUP((M71*(1+L19))/M9,-3)) -> 0 | O74: =$P$9 -> 48 | P74: =IF(O71=0%,0,ROUNDUP((P71*(1+O19))/P9,-3)) -> 0 | R74: =$S$9 -> 60 | S74: =IF(R71=0%,0,ROUNDUP((S71*(1+R19))/S9,-3)) -> 0
B76: Pencairan All In | F76: Maksimal | J76: Total DP | N76: ='Home Int'!$I$161 -> 35000000
B77: Tenor | E77: Pencairan | G77: Angsuran | J77: Tenor | M77: Pencairan | O77: Angsuran
B78: =$F$42 -> 12 | C78: Bulan | D78: =CONCATENATE($B$78," ",$C$78) -> 12 Bulan | E78: =IFERROR(F56,0) -> 134567000 | G78: =IFERROR($F$21,0) -> 13232000 | J78: =$F$42 -> 12 | K78: Bulan | L78: =CONCATENATE($B$78," ",$C$78) -> 12 Bulan | M78: =IFERROR('Home Ext'!$I$75,0) -> 60000000 | O78: =IFERROR($G$74,0) -> 0
B79: =$I$42 -> 24 | C79: Bulan | D79: =CONCATENATE($B$79," ",$C$79) -> 24 Bulan | E79: =IFERROR($I$56,0) -> 132370400 | G79: =IFERROR($I$21,0) -> 7091000 | J79: =$I$42 -> 24 | K79: Bulan | L79: =CONCATENATE($B$79," ",$C$79) -> 24 Bulan | M79: =IFERROR('Home Ext'!$I$75,0) -> 60000000 | O79: =IFERROR($J$74,0) -> 0
B80: =$L$42 -> 36 | C80: Bulan | D80: =CONCATENATE($B$80," ",$C$80) -> 36 Bulan | E80: =IFERROR($L$56,0) -> 130184300 | G80: =IFERROR($L$21,0) -> 5058000 | J80: =$L$42 -> 36 | K80: Bulan | L80: =CONCATENATE($B$80," ",$C$80) -> 36 Bulan | M80: =IFERROR('Home Ext'!$I$75,0) -> 60000000 | O80: =IFERROR($M$74,) -> 0
B81: =$O$42 -> 48 | C81: Bulan | D81: =CONCATENATE($B$81," ",$C$81) -> 48 Bulan | E81: =IFERROR($O$56,0) -> 127599200 | G81: =IFERROR($O$21,0) -> 4052000 | J81: =$O$42 -> 48 | K81: Bulan | L81: =CONCATENATE($B$81," ",$C$81) -> 48 Bulan | M81: =IFERROR('Home Ext'!$I$75,0) -> 60000000 | O81: =IFERROR($P$74,0) -> 0
B82: =$R$42 -> 60 | C82: Bulan | D82: =CONCATENATE($B$82," ",$C$82) -> 60 Bulan | E82: =IFERROR($R$56,0) -> 125205200 | G82: =IFERROR($R$21,0) -> 3457000 | J82: =$R$42 -> 60 | K82: Bulan | L82: =CONCATENATE($B$82," ",$C$82) -> 60 Bulan | M82: =IFERROR('Home Ext'!$I$75,0) -> 60000000 | O82: =IFERROR($S$74,0) -> 0

Sheet Data Int
T2: Karyawan Perbankan | U2: Sales Dealer | V2: Karyawan Mandiri Cabang | W2: Karyawan Multifinance | X2: Karyawan Asuransi | Y2: Area Kyai Tapa | Z2: Area Daan Mogot | AA2: Area Green Ville | AC2: Graha Sultan
I3: ='Home Int'!$C$91 -> Wira Agency Retail | K3: ='Home Int'!$C$93 -> Karyawan Authorized Dealer | M3: REFERRAL
C4: Referral | I4: =IF(OR(I3="Captive Internal",I3="Captive External"),3,IF($I$3="Showroom Mobil Bekas",1,IF($I$3="Karyawan Internal",2,IF($I$3="Wira Agency Retail",4,IF($I$3="Wira Bisnis",5,0))))) -> 4 | K4: =IF($K$3="Karyawan Perbankan",1,IF($K$3="Karyawan Authorized Dealer",2,IF($K$3="Karyawan Koperasi",3,IF($K$3="Karyawan Multifinance",4,IF($K$3="Karyawan Asuransi Rekanan",5,IF($K$3="Area Kyai Tapa",6,IF($K$3="Area Daan Mogot",7,IF($K$3="Area Green Ville",8,IF($K$3="Karyawan (Internal)",9,IF($K$3="Graha Sultan",10,0)))))))))) -> 2 | M4: 1 | N4: 2 | O4: 3 | P4: 4 | Q4: 5 | R4: 6 | T4: 1 | U4: 2 | V4: 3 | W4: 4 | X4: 5 | Y4: 6 | Z4: 7 | AA4: 8 | AB4: 9 | AC4: 10
B5: 1 | C5: Showroom Mobil Bekas | D5: Reguler | E5: External | F5: Referral C2C | H5: 1 | I5: =IFERROR(HLOOKUP($I$4,$M$4:$Q$26,1+H5,0)," ") -> Karyawan Perbankan | J5: 1 | K5: =IF($I$3="Karyawan MTF","Kantor Cabang",IFERROR(HLOOKUP($K$4,$T$4:$AE$28,1+H5,0)," ")) -> Aion | M5: Bursa Otomotif Sunter | N5: Pemegang WMK | O5: Area Kyai Tapa | P5: Karyawan Perbankan | Q5: Akasha | R5: Area Kyai Tapa | S5: 1 | T5: BCA | U5: Aion | W5: ACC | X5: AAB | Y5: Jakarta Kyai Tapa | Z5: Jakarta Daan Mogot | AA5: Jakarta Green Ville | AC5: Team A
B6: 2 | C6: Karyawan Internal | D6: Reguler | E6: Internal | F6: Referral | H6: 2 | I6: =IFERROR(HLOOKUP($I$4,$M$4:$Q$26,1+H6,0)," ") -> Karyawan Authorized Dealer | J6: 2 | K6: =IF($I$3="Karyawan MTF","Kantor Cabang",IFERROR(HLOOKUP($K$4,$T$4:$AE$28,1+H6,0)," ")) -> BMW | M6: Bursa Otomotif Mall Glodok Kemayoran | N6: Team Operation | O6: Area Green Ville | P6: Karyawan Authorized Dealer | Q6: Carsindo | R6: Area Green Ville | S6: 2 | T6: BNI | U6: BMW | W6: ADIRA Finance | X6: ABDA | Y6: BMP Jakarta Kyai Tapa | Z6: BMP Jakarta Daan Mogot | AA6: Jakarta Gedung Pusri | AC6: Team B
B7: 3 | C7: Captive Internal | D7: Captive | E7: Internal | F7: Khusus Karyawan Bank Mandiri | H7: 3 | I7: =IFERROR(HLOOKUP($I$4,$M$4:$Q$26,1+H7,0)," ") -> Karyawan Koperasi | J7: 3 | K7: =IF($I$3="Karyawan MTF","Kantor Cabang",IFERROR(HLOOKUP($K$4,$T$4:$AE$28,1+H7,0)," ")) -> BYD | M7: Bursa Otomotif Mangga Dua Square | N7: Team AR | O7: Area Daan Mogot | P7: Karyawan Koperasi | Q7: Empower | R7: Area Daan Mogot | S7: 3 | T7: BRI | U7: BYD | W7: BCA Finance | X7: ACA | Y7: Jakarta Jelambar | Z7: Jakarta Cengkareng Pasar Ganefo (dh Jakarta Kalideres) | AA7: Jakarta AKR Gallery West (dh Jakarta Jalan Panjang) | AC7: Team C
B8: 4 | C8: Captive External | D8: Captive | E8: External | F8: =IF('Home Ext'!$C$57="SME & Private/Prioritas","Khusus SME & Private/Prioritas","Semangat") -> Semangat | H8: 4 | I8: =IFERROR(HLOOKUP($I$4,$M$4:$Q$26,1+H8,0)," ") -> Karyawan Multifinance | J8: 4 | K8: =IF($I$3="Karyawan MTF","Kantor Cabang",IFERROR(HLOOKUP($K$4,$T$4:$AE$28,1+H8,0)," ")) -> Chery | M8: Bursa Otomotif Pasar Mobil Kemayoran | N8: Team Credit Risk | O8: =IF(I3="captive Internal"," ","SME & Private/Prioritas") -> SME & Private/Prioritas | P8: Karyawan Multifinance | Q8: Favorite | S8: 4 | T8: BSI | U8: Chery | W8: BFI Finance | X8: ADIRA | Y8: Jakarta Latumeten | Z8: Jakarta Puri Indah | AA8: Jakarta Slipi Jaya | AC8: Team D
B9: 5 | C9: Wira Agency Retail | D9: Reguler | E9: Agency | F9: Sales Dealer | H9: 5 | I9: =IFERROR(HLOOKUP($I$4,$M$4:$Q$26,1+H9,0)," ") -> Karyawan Asuransi Rekanan | J9: 5 | K9: =IF($I$3="Karyawan MTF","Kantor Cabang",IFERROR(HLOOKUP($K$4,$T$4:$AE$28,1+H9,0)," ")) -> Daihatsu | M9: Bursa Otomotif WTC Mangga Dua | N9: Graha Sultan | P9: Karyawan Asuransi Rekanan | Q9: FinGo | S9: 5 | T9: BTN | U9: Daihatsu | W9: BNI Finance | X9: ARINDO | Y9: Jakarta Grogol Muwardi | Z9: Jakarta Taman Palem Lestari | AA9: Jakarta Kemanggisan
B10: 6 | C10: Wira Bisnis | D10: Reguler | E10: External | F10: Referral | H10: 6 | I10: =IFERROR(HLOOKUP($I$4,$M$4:$Q$26,1+H10,0)," ") -> 0 | J10: 6 | K10: =IF($I$3="Karyawan MTF","Kantor Cabang",IFERROR(HLOOKUP($K$4,$T$4:$AE$28,1+H10,0)," ")) -> DFSK | M10: Bursa Otomotif Season City | Q10: Good | S10: 6 | T10: BUKOPIN | U10: DFSK | W10: BRI Finance | X10: AWT | Y10: Jakarta Jelambar Baru | Z10: Jakarta Taman Semanan Indah | AA10: Jakarta Rawa Belong
B11: 7 | C11: Others | D11: Reguler | E11: External | F11: Referral | H11: 7 | I11: =IFERROR(HLOOKUP($I$4,$M$4:$Q$26,1+H11,0)," ") -> 0 | J11: 7 | K11: =IF($I$3="Karyawan MTF","Kantor Cabang",IFERROR(HLOOKUP($K$4,$T$4:$AE$28,1+H11,0)," ")) -> Hino | M11: Bursa Otomotif Blok M | Q11: Goona | S11: 7 | T11: CIMB NIAGA | U11: Hino | W11: CIMB Niaga Finance | X11: BESS | Y11: Jakarta Taman Duta Mas | Z11: Jakarta Daan Mogot Baru | AA11: Jakarta Taman Kebon Jeruk
H12: 8 | I12: =IFERROR(HLOOKUP($I$4,$M$4:$Q$26,1+H12,0)," ") -> 0 | J12: 8 | K12: =IF($I$3="Karyawan MTF","Kantor Cabang",IFERROR(HLOOKUP($K$4,$T$4:$AE$28,1+H12,0)," ")) -> Honda | M12: Bursa Otomotif ITC Permata Hijau | Q12: Pinjam Bagus | S12: 8 | T12: DANAMON | U12: Honda | W12: Clipan Finance | X12: CAKRAWALA | Y12: Jakarta Tomang | Z12: Jakarta Mal Puri Indah | AA12: Jakarta Kebon Jeruk Perjuangan
H13: 9 | I13: =IFERROR(HLOOKUP($I$4,$M$4:$Q$26,1+H13,0)," ") -> 0 | J13: 9 | K13: =IF($I$3="Karyawan MTF","Kantor Cabang",IFERROR(HLOOKUP($K$4,$T$4:$AE$28,1+H13,0)," ")) -> Hyundai | M13: Bursa Otomotif Bintaro | Q13: Porto | S13: 9 | T13: KEB HANA | U13: Hyundai | W13: Dipo Star Finance | X13: KRESNA | Y13: Jakarta R.S. Royal Taruma | Z13: Jakarta Puri Kencana | AA13: BMP Jakarta Kebon Jeruk
C14: ='Home Int'!$C$149 -> Dana Tunai | D14: Usia Debitur | E14: 0.1 | H14: 10 | I14: =IFERROR(HLOOKUP($I$4,$M$4:$Q$26,1+H14,0)," ") -> 0 | J14: 10 | K14: =IF($I$3="Karyawan MTF","Kantor Cabang",IFERROR(HLOOKUP($K$4,$T$4:$AE$28,1+H14,0)," ")) -> Isuzu | M14: Bursa Otomotif Serpong Summarecon | Q14: Semesta | S14: 10 | T14: MAY BANK | U14: Isuzu | W14: FIF | X14: MAG | Y14: Jakarta Universitas Trisakti | Z14: Jakarta Citra Garden | AA14: Jakarta Kebon Jeruk
B15: 1 | C15: =IF(C14="Pembiayaan Emas / Logam Mulia","","Simulasi Kredit") -> Simulasi Kredit | D15: 18-35 tahun | E15: 0.1 | H15: 11 | I15: =IFERROR(HLOOKUP($I$4,$M$4:$Q$26,1+H15,0)," ") -> 0 | J15: 11 | K15: =IF($I$3="Karyawan MTF","Kantor Cabang",IFERROR(HLOOKUP($K$4,$T$4:$AE$28,1+H15,0)," ")) -> Kia | M15: Cluster Fatmawati | Q15: Soehu | S15: 11 | T15: MAYAPADA | U15: Kia | W15: Kredit Plus | X15: MEGA | Y15: Jakarta Universitas Tarumanegara | Z15: Jakarta Palem City | AA15: Jakarta Taman Aries
B16: 2 | C16: Tracking Proses Approval Credit | D16: 36-45 tahun | E16: 0.1 | H16: 12 | I16: =IFERROR(HLOOKUP($I$4,$M$4:$Q$26,1+H16,0)," ") -> 0 | J16: 12 | K16: =IF($I$3="Karyawan MTF","Kantor Cabang",IFERROR(HLOOKUP($K$4,$T$4:$AE$28,1+H16,0)," ")) -> Lexus | M16: Cluster Pondok Indah | Q16: Taktis | S16: 12 | T16: MEGA | U16: Lexus | W16: May Bank Finance | X16: MNC | Y16: Jakarta KS Tubun (dh Jakarta R.S. Pelni) | Z16: Jakarta Ciputra Internasional | AA16: Jakarta Kelapa Dua (dh Jkt Kepa Duri)
B17: 3 | C17: =IF(C14="Pembiayaan Emas / Logam Mulia","Tabel Angsuran","") | D17: 46-50 tahun | E17: 0.8 | H17: 13 | I17: =IFERROR(HLOOKUP($I$4,$M$4:$Q$26,1+H17,0)," ") -> 0 | J17: 13 | K17: =IF($I$3="Karyawan MTF","Kantor Cabang",IFERROR(HLOOKUP($K$4,$T$4:$AE$28,1+H17,0)," ")) -> Mazda | S17: 13 | T17: MUAMALAT | U17: Mazda | W17: Mega Finance | X17: MPM | Y17: Jakarta R.S. Harapan Kita | Z17: Jakarta Botanical Garden | AA17: Jakarta Kedoya
B18: 4 | C18: Actual Lending AO | D18: 51-60 tahun | H18: 14 | I18: =IFERROR(HLOOKUP($I$4,$M$4:$Q$26,1+H18,0)," ") -> 0 | J18: 14 | K18: =IF($I$3="Karyawan MTF","Kantor Cabang",IFERROR(HLOOKUP($K$4,$T$4:$AE$28,1+H18,0)," ")) -> Mercedes | S18: 14 | T18: OCBC | U18: Mercedes | W18: MNC Finance | X18: OONA | Y18: Jakarta R.S. Kanker Dharmais | Z18: Jakarta Taman Permata Buana | AA18: Jakarta Mal Taman Anggrek
B19: 5 | C19: Monitoring EPD & AR | H19: 15 | I19: =IFERROR(HLOOKUP($I$4,$M$4:$Q$26,1+H19,0)," ") -> 0 | J19: 15 | K19: =IF($I$3="Karyawan MTF","Kantor Cabang",IFERROR(HLOOKUP($K$4,$T$4:$AE$28,1+H19,0)," ")) -> Mitsubishi | S19: 15 | T19: PANIN | U19: Mitsubishi | W19: MUF | X19: RAKSA | Y19: Jakarta S. Parman | Z19: Jakarta Citra 2 Extention | AA19: Jakarta Mediterania Tanjung Duren
B20: 6 | H20: 16 | I20: =IFERROR(HLOOKUP($I$4,$M$4:$Q$26,1+H20,0)," ") -> 0 | J20: 16 | K20: =IF($I$3="Karyawan MTF","Kantor Cabang",IFERROR(HLOOKUP($K$4,$T$4:$AE$28,1+H20,0)," ")) -> Neta | S20: 16 | T20: PERMATA | U20: Neta | W20: NSC Finance | X20: RAMAYANA | Y20: Jakarta Mal Ciputra | Z20: Jakarta Pos Pengumben Raya | AA20: Jakarta Tanjung Duren
H21: 17 | I21: =IFERROR(HLOOKUP($I$4,$M$4:$Q$26,1+H21,0)," ") -> 0 | J21: 17 | K21: =IF($I$3="Karyawan MTF","Kantor Cabang",IFERROR(HLOOKUP($K$4,$T$4:$AE$28,1+H21,0)," ")) -> Nissan | S21: 17 | T21: SINARMAS | U21: Nissan | W21: OTO Multiartha | X21: SIMAS | Y21: Jakarta Menara Citicon | Z21: Jakarta St. Moritz | AA21: Jakarta Pesanggrahan Raya
C22: Referral | H22: 18 | I22: =IFERROR(HLOOKUP($I$4,$M$4:$Q$26,1+H22,0)," ") -> 0 | J22: 18 | K22: =IF($I$3="Karyawan MTF","Kantor Cabang",IFERROR(HLOOKUP($K$4,$T$4:$AE$28,1+H22,0)," ")) -> Suzuki | S22: 18 | T22: UOB | U22: Suzuki | W22: Sinar Mas Finance | X22: SUNDAY | Z22: Jakarta Pasar Cengkareng | AA22: Jakarta Grand Slipi Tower
B23: 1 | C23: Showroom Mobil Bekas | D23: SRB | E23: Dana Tunai | F23: DTN | H23: 19 | I23: =IFERROR(HLOOKUP($I$4,$M$4:$Q$26,1+H23,0)," ") -> 0 | J23: 19 | K23: =IF($I$3="Karyawan MTF","Kantor Cabang",IFERROR(HLOOKUP($K$4,$T$4:$AE$28,1+H23,0)," ")) -> Toyota | S23: 19 | U23: Toyota | W23: WOM Finance | X23: TOB | Z23: Jakarta Pasar Meruya Kembangan
B24: 2 | C24: Karyawan Internal | D24: KIN | E24: Pembiayaan Mobil Bekas | F24: UCF | H24: 20 | I24: =IFERROR(HLOOKUP($I$4,$M$4:$Q$26,1+H24,0)," ") -> 0 | J24: 20 | K24: =IF($I$3="Karyawan MTF","Kantor Cabang",IFERROR(HLOOKUP($K$4,$T$4:$AE$28,1+H24,0)," ")) -> Wuling | S24: 20 | U24: Wuling | Z24: Jakarta Raya Kosambi
B25: 3 | C25: Captive Internal | D25: CIN | E25: Pembiayaan Emas / Logam Mulia | F25: LMF | H25: 21 | I25: =IFERROR(HLOOKUP($I$4,$M$4:$Q$26,1+H25,0)," ") -> 0 | J25: 21 | K25: =IF($I$3="Karyawan MTF","Kantor Cabang",IFERROR(HLOOKUP($K$4,$T$4:$AE$28,1+H25,0)," ")) -> 0 | S25: 21
B26: 4 | C26: Captive External | D26: CEX | E26: Pembiayaan Mobil Baru | F26: NCF | H26: 22 | I26: =IFERROR(HLOOKUP($I$4,$M$4:$Q$26,1+H26,0)," ") -> 0 | J26: 22 | K26: =IF($I$3="Karyawan MTF","Kantor Cabang",IFERROR(HLOOKUP($K$4,$T$4:$AE$28,1+H26,0)," ")) -> 0 | S26: 22
B27: 5 | C27: Wira Agency Retail | D27: WAR | H27: 23 | I27: =IFERROR(HLOOKUP($I$4,$M$4:$Q$26,1+H27,0)," ") | J27: 23 | K27: =IF($I$3="Karyawan MTF","Kantor Cabang",IFERROR(HLOOKUP($K$4,$T$4:$AE$28,1+H27,0)," ")) -> 0 | S27: 23
B28: 6 | C28: Wira Bisnis | D28: WBS | S28: 24
B29: 7 | C29: Others | D29: OTH | S29: 25
C31: =IF('Home Int'!$C$91="Showroom Mobil Bekas","SRB",IF('Home Int'!$C$91="Karyawan Internal","KIN",IF('Home Int'!$C$91="Captive Internal","CIN",IF('Home Ext'!$C$55="Captive External","CEX",IF('Home Ext'!$C$55="Wira Agency Retail","WAR",IF('Home Ext'!C55="Wira Bisnis","WBS","OTH")))))) -> OTH | E31: ='UC Ext'!$I$6 -> Commercial | F31: Domisili
C32: =IF('Home Ext'!$C$95="Refinancing / Dana Tunai","DTN",IF('Home Ext'!$C$95="Pembiayaan Mobil Bekas","UCF",IF('Home Ext'!$C$95="Pembiayaan Emas / Logam Mulia","LMF",IF('Home Ext'!$C$95="Pembiayaan Mobil Baru","NCF","")))) | E32: =IF(C14="Refinancing / Dana Tunai","TLO All Tenor","Comprehensive All Tenor") -> Comprehensive All Tenor | F32: Jakarta Utara
E33: =IF(E31="Passenger","Comprehensive 1 tahun","") | F33: Jakarta Selatan
F34: Jakarta Timur | O34: Khusus Karyawan Bank Mandiri
F35: Jakarta Barat | O35: Khusus SME & Private/Prioritas
F36: Jakarta Pusat | O36: Semangat
F37: Kota Bogor | O37: Tengah
F38: Kabupaten Bogor | O38: Cuan
F39: Depok
F40: Kota Tanggerang
F41: Kabupaten Tanggerang
F42: Kota Tanggerang Selatan
F43: Kota Bekasi
F44: Kabupaten Bekasi
C45: =IF('Home Int'!$O$15="Perorangan (Non Wiraswasta)",1,IF('Home Int'!$O$15="Perorangan (Wiraswasta)",2,3)) -> 1 | D45: 1 | E45: 2 | F45: 3
D46: Perorangan (Non Wirasasta) | E46: Perorangan (Wirasasta) | F46: Badan Hukum Usaha
B47: 1 | C47: =IFERROR(HLOOKUP($C$45,$D$45:$F$56,2+B47,0)," ") -> KTP Debitur | D47: KTP Debitur | E47: KTP Debitur | F47: Akte Pendirian Usaha
B48: 2 | C48: =IFERROR(HLOOKUP($C$45,$D$45:$F$56,2+B48,0)," ") -> KTP Pasangan | D48: KTP Pasangan | E48: KTP Pasangan | F48: Akte Perubahan Usaha
B49: 3 | C49: =IFERROR(HLOOKUP($C$45,$D$45:$F$56,2+B49,0)," ") -> Kartu Keluarga | D49: Kartu Keluarga | E49: Kartu Keluarga | F49: NPWP Usaha
B50: 4 | C50: =IFERROR(HLOOKUP($C$45,$D$45:$F$56,2+B50,0)," ") -> NPWP | D50: NPWP | E50: NPWP | F50: KTP Komisaris & NPWP
B51: 5 | C51: =IFERROR(HLOOKUP($C$45,$D$45:$F$56,2+B51,0)," ") -> Bukti Kepemilikan Rumah | D51: Bukti Kepemilikan Rumah | E51: Bukti Kepemilikan Rumah | F51: KTP Direktur & NPWP
B52: 6 | C52: =IFERROR(HLOOKUP($C$45,$D$45:$F$56,2+B52,0)," ") -> Rek Koran 3 bulan terakhir | D52: Rek Koran 3 bulan terakhir | E52: Rek Koran 3 bulan terakhir | F52: NIB
B53: 7 | C53: =IFERROR(HLOOKUP($C$45,$D$45:$F$56,2+B53,0)," ") -> Slip Gaji | D53: Slip Gaji | E53: Legalitas/Bukti Usaha | F53: Ijin Usaha khusus (dari Dinas atau kementerian terkait)
B54: 8 | C54: =IFERROR(HLOOKUP($C$45,$D$45:$F$56,2+B54,0)," ") -> Rek Koran 3 bulan terakhir/Bon/Faktur Penjualan | D54: =IF($C$74="Pasangan Bekerja dan memiliki penghasilan","Rek Koran 3 bulan terakhir","Rek Koran 3 bulan terakhir/Bon/Faktur Penjualan") -> Rek Koran 3 bulan terakhir/Bon/Faktur Penjualan | E54: =IF($C$74="Pasangan Bekerja dan memiliki penghasilan","Rek Koran 3 bulan terakhir","Rek Koran 3 bulan terakhir/Bon/Faktur Penjualan") -> Rek Koran 3 bulan terakhir/Bon/Faktur Penjualan | F54: Laporan Keuangan 2 Tahun terakhir
B55: 9 | C55: =IFERROR(HLOOKUP($C$45,$D$45:$F$56,2+B55,0)," ") -> Legalitas/Bukti Usaha | D55: =IF($C$74="Pasangan Bekerja dan memiliki penghasilan","Slip Gaji","Legalitas/Bukti Usaha") -> Legalitas/Bukti Usaha | E55: =IF($C$74="Pasangan Bekerja dan memiliki penghasilan","Slip Gaji","Legalitas/Bukti Usaha") -> Legalitas/Bukti Usaha | F55: Rek Koran 3 Bulan Terakhir
B56: 10 | C56: =IFERROR(HLOOKUP($C$45,$D$45:$F$56,2+B56,0)," ") -> 0
B68: 1 | C68: =IF('Home Int'!$O$15="Badan Hukum Usaha"," ","Pasangan Bekerja dan memiliki penghasilan") -> Pasangan Bekerja dan memiliki penghasilan | D68: Karyawan | E68: =IF('Home Int'!$O$15="Badan Hukum Usaha"," ","Pasangan Bekerja dan memiliki penghasilan") -> Pasangan Bekerja dan memiliki penghasilan
B69: 2 | C69: =IF('Home Int'!$O$15="Badan Hukum Usaha"," ","Pasangan memiliki usaha lainnya dan memiliki penghasilan") -> Pasangan memiliki usaha lainnya dan memiliki penghasilan | D69: Wiraswasta | E69: =IF('Home Int'!$O$15="Badan Hukum Usaha"," ","Pasangan memiliki usaha lainnya dan memiliki penghasilan") -> Pasangan memiliki usaha lainnya dan memiliki penghasilan
B70: 3 | C70: =IF('Home Int'!$O$15="Badan Hukum Usaha"," ","Pasangan adalah profesional dan memiliki penghasilan") -> Pasangan adalah profesional dan memiliki penghasilan | D70: Profesional | E70: =IF('Home Int'!$O$15="Badan Hukum Usaha"," ","Pasangan adalah profesional dan memiliki penghasilan") -> Pasangan adalah profesional dan memiliki penghasilan
B71: 4 | C71: =IF('Home Int'!$O$15="Badan Hukum Usaha"," ","Tidak Ada") -> Tidak Ada | D71: Tidak Ada | E71: =IF('Home Int'!$O$15="Badan Hukum Usaha"," ","Tidak Ada") -> Tidak Ada

Sheet Data in out
AO8: 15 | AP8: 220 | AQ8: 221 | AR8: 222 | AS8: 223 | BP8: Graha Sultan | BQ8: 15
AO9: 14 | AP9: 214 | AQ9: 215 | AR9: 216 | AS9: 217 | AT9: 218 | AU9: 219 | BP9: Kosong | BQ9: 14
AO10: 13 | AP10: 194 | AQ10: 195 | AR10: 196 | AS10: 197 | AT10: 198 | AU10: 199 | AV10: 200 | AW10: 201 | AX10: 202 | AY10: 203 | AZ10: 204 | BA10: 205 | BB10: 206 | BC10: 207 | BD10: 208 | BE10: 209 | BF10: 210 | BG10: 211 | BH10: 212 | BI10: 213 | BP10: Area Green Ville | BQ10: 13
AO11: 12 | AP11: 172 | AQ11: 173 | AR11: 174 | AS11: 175 | AT11: 176 | AU11: 177 | AV11: 178 | AW11: 179 | AX11: 180 | AY11: 181 | AZ11: 182 | BA11: 183 | BB11: 184 | BC11: 185 | BD11: 186 | BE11: 187 | BF11: 188 | BG11: 189 | BH11: 190 | BI11: 191 | BJ11: 192 | BK11: 193 | BP11: Area Daan Mogot | BQ11: 12
AO12: 11 | AP12: 150 | AQ12: 151 | AR12: 152 | AS12: 153 | AT12: 154 | AU12: 155 | AV12: 156 | AW12: 157 | AX12: 158 | AY12: 159 | AZ12: 160 | BA12: 161 | BB12: 162 | BC12: 163 | BD12: 164 | BE12: 165 | BF12: 166 | BG12: 167 | BH12: 168 | BI12: 169 | BJ12: 170 | BK12: 171 | BP12: Area Kyai Tapa | BQ12: 11
AO13: 10 | AP13: 128 | AQ13: 129 | AR13: 130 | AS13: 131 | AT13: 132 | AU13: 133 | AV13: 134 | AW13: 135 | AX13: 136 | AY13: 137 | AZ13: 138 | BA13: 139 | BB13: 140 | BC13: 141 | BD13: 142 | BE13: 143 | BF13: 144 | BG13: 145 | BH13: 146 | BI13: 147 | BJ13: 148 | BK13: 149 | BP13: Karyawan Asuransi | BQ13: 10
AO14: 9 | AP14: 107 | AQ14: 108 | AR14: 109 | AS14: 110 | AT14: 111 | AU14: 112 | AV14: 113 | AW14: 114 | AX14: 115 | AY14: 116 | AZ14: 117 | BA14: 118 | BB14: 119 | BC14: 120 | BD14: 121 | BE14: 122 | BF14: 123 | BG14: 124 | BH14: 125 | BI14: 126 | BJ14: 127 | BP14: Karyawan Multifinance | BQ14: 9
AO15: 8 | AP15: 100 | AQ15: 101 | AR15: 102 | AS15: 103 | AT15: 104 | AU15: 105 | AV15: 106 | BP15: Karyawan Mandiri Cabang | BQ15: 8
AO16: 7 | AP16: 77 | AQ16: 78 | AR16: 79 | AS16: 80 | AT16: 81 | AU16: 82 | AV16: 83 | AW16: 84 | AX16: 85 | AY16: 86 | AZ16: 87 | BA16: 88 | BB16: 89 | BC16: 90 | BD16: 91 | BE16: 92 | BF16: 93 | BG16: 94 | BH16: 95 | BI16: 96 | BJ16: 97 | BK16: 98 | BL16: 99 | BP16: Karyawan Authorized Dealer | BQ16: 7
AO17: 6 | AP17: 57 | AQ17: 58 | AR17: 59 | AS17: 60 | AT17: 61 | AU17: 62 | AV17: 63 | AW17: 64 | AX17: 65 | AY17: 66 | AZ17: 67 | BA17: 68 | BB17: 69 | BC17: 70 | BD17: 71 | BE17: 72 | BF17: 73 | BG17: 74 | BH17: 75 | BI17: 76 | BP17: Karyawan Perbankan | BQ17: 6
B18: 1 | C18: =B18+1 -> 2 | D18: =C18+1 -> 3 | E18: =D18+1 -> 4 | F18: =E18+1 -> 5 | G18: =F18+1 -> 6 | H18: =G18+1 -> 7 | I18: =H18+1 -> 8 | J18: =I18+1 -> 9 | ... AK18: =AJ18+1 -> 36 | AO18: 5 | AP18: 51 | AQ18: 52 | AR18: 53 | AS18: 54 | AT18: 55 | AU18: 56 | BP18: Bank Mandiri | BQ18: 5
I19: KTP | N19: Karyawan | P19: Wiraswasta | R19: Profesional | T19: Pasangan Joint Income dgn Pemohon | W19: No | X19: 1 | Y19: =X19+1 -> 2 | Z19: =Y19+1 -> 3 | AA19: =Z19+1 -> 4 | AB19: =AA19+1 -> 5 | AC19: =AB19+1 -> 6 | AD19: =AC19+1 -> 7 | AE19: =AD19+1 -> 8 | AF19: =AE19+1 -> 9 | ... AH19: =AG19+1 -> 11 | AO19: 4 | AP19: 37 | AQ19: 38 | AR19: 39 | AS19: 40 | AT19: 41 | AU19: 42 | AV19: 43 | AW19: 44 | AX19: 45 | AY19: 46 | AZ19: 47 | BA19: 48 | BB19: 49 | BC19: 50 | BP19: Wira Bisnis | BQ19: 4
A20: No | B20: Kode Aplikasi Referral | C20: Nama | E20: Referral | G20: Perorangan | H20: Pasangan (Jika Joint Income) | I20: Debitur | J20: Pasangan | K20: NPWP Pemohon | L20: Kartu Keluarga | M20: SPPT PBB/AJB/SHM | N20: Slip Gaji Carbonized | O20: RK 3 bln terakhir | P20: Legalitas Usaha /Ijin Profesi | Q20: Bon / Faktur Penjualan | T20: RK 3 bln terakhir | U20: Slip Gaji Carbonize / Legalitas Usaha / Ijin Profesi | V20: Bon / Faktur Penjualan | X20: Verifikasi, Validasi dan kelengkapan data permohonan | Y20: Survey Domisili & Tempat usaha/Kantor | Z20: Cek fisik Kendaraan | AA20: Laporan Hasil Survey. | AB20: Proses Aplikasi | AC20: Konfirmasi Debitur by phone & Scoring Credit | AD20: Permohonan Persetujuan Pembiayaan | AE20: Persetujuan Pembiayaan (PO) | AF20: Verifikasi, Validasi dan kelengkapan Jaminan (BPKB) | AG20: Kofirmasi Debitur by phone | AH20: Golive & Payment | AO20: 3 | AP20: 28 | AQ20: 29 | AR20: 30 | AS20: 31 | AT20: 32 | AU20: 33 | AV20: 34 | AW20: 35 | AX20: 36 | BP20: Karyawan Perbankan | BQ20: 3 | KF20: a | KG20: b | KH20: c | KI20: d | KJ20: e
AO21: 2 | AP21: 21 | AQ21: 22 | AR21: 23 | AS21: 24 | AT21: 25 | AU21: 26 | AV21: 27 | BP21: Karyawan Internal | BQ21: 2 | BT21: 1 | BU21: =1+BT21 -> 2 | BV21: =1+BU21 -> 3 | BW21: =1+BV21 -> 4 | BX21: =1+BW21 -> 5 | BY21: =1+BX21 -> 6 | BZ21: =1+BY21 -> 7 | CA21: =1+BZ21 -> 8 | CB21: =1+CA21 -> 9 | ... KH21: =1+KG21 -> 223
C22: Debitur | D22: AO | G22: Badan Hukum Usaha | I22: Komisaris | J22: Direktur | K22: NPWP Direktur | L22: NPWP Usaha | M22: Akte Pendirian | N22: Akte Perubahan | O22: SK Kemenkumham | P22: NIB & Ijin Usaha Khusus | Q22: Laporan Keuangan | R22: RK 3 bln terakhir | S22: SPK/MOU Kerja | AO22: 1 | AP22: 1 | AQ22: 2 | AR22: 3 | AS22: 4 | AT22: 5 | AU22: 6 | AV22: 7 | AW22: 8 | AX22: 9 | AY22: 10 | AZ22: 11 | BA22: 12 | BB22: 13 | BC22: 14 | BD22: 15 | BE22: 16 | BF22: 17 | BG22: 18 | BH22: 19 | BI22: 20 | BP22: showroom mobil Bekas | BQ22: 1 | BT22: Showroom Mobil Bekas | CN22: Karyawan Internal | CU22: Karyawan Perbankan | DD22: Wira Bisnis | DR22: Bank Mandiri | DX22: Karyawan Perbankan | ER22: Karyawan Authorized Dealer | FO22: Karyawan Mandiri Cabang | FV22: Karyawan Multifinance | GQ22: Karyawan Asuransi | HM22: Area Kyai Tapa | II22: Area Daan Mogot | JE22: Area Green Ville | JY22: Kosong | KE22: Graha Sultan
AN23: =IF(OR(AN24="Captive Internal",AN24="Captive External"),5,IF(AN24="Showroom Mobil Bekas",1,IF(AN24="Karyawan Internal",2,IF(AN24="Wira Agency Retail",3,IF(AN24="Wira Bisnis",4,0))))) -> 0 | BT23: 1 | CN23: 2 | CU23: 3 | DD23: 4 | DR23: 5 | DX23: 6 | ER23: 7 | FO23: 8 | FV23: 9 | GQ23: 10 | HM23: 11 | II23: 12 | JE23: 13 | JY23: 14 | KE23: 15
A24: =ROWS($A$24:A24) -> 1 | B24: 9anxfq | C24: AAAAAA | D24: Ade | E24: ='Home Int'!$O$23 -> Wira Agency Retail_Karyawan Authorized Dealer_Toyota_ | G24: ='Home Int'!$O$15 -> Perorangan (Non Wiraswasta) | H24: ='Home Int'!$O$19 -> Pasangan Bekerja dan memiliki penghasilan | I24: 2 | J24: 2 | K24: 2 | L24: 2 | M24: 2 | N24: 2 | O24: 2 | P24: 2 | Q24: 2 | R24: 2 | S24: 0 | T24: 2 | U24: 2 | V24: 0 | W24: =ROWS($W$24:W24) -> 1 | X24: 2 | Y24: 2 | Z24: 2 | AA24: 2 | AB24: 2 | AC24: 2 | AD24: 2 | AE24: 1 | AF24: 1 | AG24: 1 | AH24: 1 | AI24: 0 | AJ24: 0 | AK24: 0 | AN24: =E24 -> Wira Agency Retail_Karyawan Authorized Dealer_Toyota_ | BT24: Bursa Otomotif Sunter | BU24: Bursa Otomotif Mall Glodok Kemayoran | BV24: Bursa Otomotif Mangga Dua Square | BW24: Bursa Otomotif Pasar Mobil Kemayoran | BX24: Bursa Otomotif WTC Mangga Dua | BY24: Bursa Otomotif Season City | BZ24: Bursa Otomotif Blok M | CA24: Bursa Otomotif ITC Permata Hijau | CB24: Bursa Otomotif Bintaro | CC24: Bursa Otomotif Serpong Summarecon | CD24: Cluster Fatmawati | CE24: Cluster Pondok Indah | CN24: Pemegang WMK | CO24: Team Operation | CP24: Team AR | CQ24: Team Credit Risk | CR24: Graha Sultan | CU24: Karyawan Perbankan | CV24: Karyawan Authorized Dealer | CW24: Karyawan Koperasi | CX24: Karyawan Multifinance | CY24: Karyawan Asuransi Rekanan | DD24: Akasha | DE24: Carsindo | DF24: Empower | DG24: Favorite | DH24: FinGo | DI24: Good | DJ24: Goona | DK24: Pinjam Bagus | DL24: Porto | DM24: Semesta | DN24: Soehu | DO24: Taktis | DR24: Area Kyai Tapa | DS24: Area Green Ville | DT24: Area Daan Mogot | DX24: BCA | DY24: BNI | DZ24: BRI | EA24: BSI | EB24: BTN | EC24: BUKOPIN | ED24: CIMB NIAGA | EE24: DANAMON | EF24: KEB HANA | EG24: MAY BANK | EH24: MAYAPADA | EI24: MEGA | EJ24: MUAMALAT | EK24: OCBC | EL24: PANIN | EM24: PERMATA | EN24: SINARMAS | EO24: UOB | ER24: BYD | ES24: Chery | ET24: Daihatsu | EU24: DFSK | EV24: Hino | EW24: Honda | EX24: Hyundai | EY24: Isuzu | EZ24: Kia | FA24: Lexus | FB24: Mazda | FC24: Mercedes | FD24: Mitsubishi | FE24: Neta | FF24: Nissan | FG24: Suzuki | FH24: Toyota | FI24: Wuling | FV24: ACC | FW24: ADIRA Finance | FX24: BCA Finance | FY24: BFI Finance | FZ24: BNI Finance | GA24: BRI Finance | GB24: CIMB Niaga Finance | GC24: Clipan Finance | GD24: Dipo Star Finance | GE24: FIF | GF24: Kredit Plus | GG24: May Bank Finance | GH24: Mega Finance | GI24: MNC Finance | GJ24: MUF | GK24: NSC Finance | GL24: OTO Multiartha | GM24: Sinar Mas Finance | GN24: WOM Finance | GQ24: AAB | GR24: ABDA | GS24: ACA | GT24: ADIRA | GU24: ARINDO | GV24: AWT | GW24: BESS | GX24: CAKRAWALA | GY24: KRESNA | GZ24: MAG | HA24: MEGA | HB24: MNC | HC24: MPM | HD24: OONA | HE24: RAKSA | HF24: RAMAYANA | HG24: SIMAS | HH24: SUNDAY | HI24: TOB | HM24: Jakarta Kyai Tapa | HN24: BMP Jakarta Kyai Tapa | HO24: Jakarta Jelambar | HP24: Jakarta Latumeten | HQ24: Jakarta Grogol Muwardi | HR24: Jakarta Jelambar Baru | HS24: Jakarta Taman Duta Mas | HT24: Jakarta Tomang | HU24: Jakarta R.S. Royal Taruma | HV24: Jakarta Universitas Trisakti | HW24: Jakarta Universitas Tarumanegara | HX24: Jakarta KS Tubun (dh Jakarta R.S. Pelni) | HY24: Jakarta R.S. Harapan Kita | HZ24: Jakarta R.S. Kanker Dharmais | IA24: Jakarta S. Parman | IB24: Jakarta Mal Ciputra | IC24: Jakarta Menara Citicon | II24: Jakarta Daan Mogot | IJ24: BMP Jakarta Daan Mogot | IK24: Jakarta Cengkareng Pasar Ganefo (dh Jakarta Kalideres) | IL24: Jakarta Puri Indah | IM24: Jakarta Taman Palem Lestari | IN24: Jakarta Taman Semanan Indah | IO24: Jakarta Daan Mogot Baru | IP24: Jakarta Mal Puri Indah | IQ24: Jakarta Puri Kencana | IR24: Jakarta Citra Garden | IS24: Jakarta Palem City | IT24: Jakarta Ciputra Internasional | IU24: Jakarta Botanical Garden | IV24: Jakarta Taman Permata Buana | IW24: Jakarta Citra 2 Extention | IX24: Jakarta Pos Pengumben Raya | IY24: Jakarta St. Moritz | IZ24: Jakarta Pasar Cengkareng | JA24: Jakarta Pasar Meruya Kembangan | JB24: Jakarta Raya Kosambi | JE24: Jakarta Green Ville | JF24: Jakarta Gedung Pusri | JG24: Jakarta AKR Gallery West (dh Jakarta Jalan Panjang) | JH24: Jakarta Slipi Jaya | JI24: Jakarta Kemanggisan | JJ24: Jakarta Rawa Belong | JK24: Jakarta Taman Kebon Jeruk | JL24: Jakarta Kebon Jeruk Perjuangan | JM24: BMP Jakarta Kebon Jeruk | JN24: Jakarta Kebon Jeruk | JO24: Jakarta Taman Aries | JP24: Jakarta Kelapa Dua (dh Jkt Kepa Duri) | JQ24: Jakarta Kedoya | JR24: Jakarta Mal Taman Anggrek | JS24: Jakarta Mediterania Tanjung Duren | JT24: Jakarta Tanjung Duren | JU24: Jakarta Pesanggrahan Raya | JV24: Jakarta Grand Slipi Tower | JY24: a | JZ24: b | KA24: c | KB24: d | KC24: e | KD24: f | KE24: Team A | KF24: Team B | KG24: Team C | KH24: Team D
A25: =ROWS($A$24:A25) -> 2 | B25: mCgwDj | C25: BBBBBB | D25: Alfiansyah | G25: ='Home Int'!$O$15 -> Perorangan (Non Wiraswasta) | H25: ='Home Int'!$O$19 -> Pasangan Bekerja dan memiliki penghasilan | I25: 2 | J25: 2 | K25: 2 | L25: 2 | M25: 2 | N25: 0 | O25: 2 | P25: 2 | Q25: 0 | R25: 0 | S25: 0 | T25: 0 | U25: 2 | V25: 2 | W25: =ROWS($W$24:W25) -> 2 | X25: 2 | Y25: 2 | Z25: 2 | AA25: 2 | AB25: 2 | AC25: 2 | AD25: 1 | AE25: 1 | AF25: 1 | AG25: 1 | AH25: 1 | AI25: 0 | AJ25: 0 | AK25: 0
A26: =ROWS($A$24:A26) -> 3 | B26: gZAX6q | C26: PT. CCCCCC | D26: Angga | G26: ='Home Int'!$O$15 -> Perorangan (Non Wiraswasta) | H26: ='Home Int'!$O$19 -> Pasangan Bekerja dan memiliki penghasilan | I26: 2 | J26: 2 | K26: 2 | L26: 2 | M26: 2 | N26: 2 | O26: 2 | P26: 2 | Q26: 0 | R26: 2 | S26: 0 | T26: 0 | U26: 0 | V26: 0 | W26: =ROWS($W$24:W26) -> 3 | X26: 2 | Y26: 2 | Z26: 2 | AA26: 2 | AB26: 2 | AC26: 1 | AD26: 1 | AE26: 1 | AF26: 1 | AG26: 1 | AH26: 1 | AI26: 0 | AJ26: 0 | AK26: 0
A27: =ROWS($A$24:A27) -> 4 | B27: kMzgvl | C27: DDDDD | D27: Kharis | G27: ='Home Int'!$O$15 -> Perorangan (Non Wiraswasta) | H27: ='Home Int'!$O$19 -> Pasangan Bekerja dan memiliki penghasilan | I27: 2 | J27: 2 | K27: 2 | L27: 2 | M27: 2 | N27: 2 | O27: 2 | P27: 0 | Q27: 0 | R27: 0 | S27: 0 | T27: 2 | U27: 1 | V27: 0 | W27: =ROWS($W$24:W27) -> 4 | X27: 2 | Y27: 2 | Z27: 2 | AA27: 2 | AB27: 1 | AC27: 1 | AD27: 1 | AE27: 1 | AF27: 1 | AG27: 1 | AH27: 1 | AI27: 0 | AJ27: 0 | AK27: 0
A28: =ROWS($A$24:A28) -> 5 | B28: ShDqX4 | C28: EEEEEE | D28: Risanto | G28: ='Home Int'!$O$15 -> Perorangan (Non Wiraswasta) | H28: ='Home Int'!$O$19 -> Pasangan Bekerja dan memiliki penghasilan | I28: 2 | J28: 2 | K28: 0 | L28: 0 | M28: 2 | N28: 0 | O28: 0 | P28: 0 | Q28: 0 | R28: 0 | S28: 0 | T28: 0 | U28: 2 | V28: 2 | W28: =ROWS($W$24:W28) -> 5 | X28: 2 | Y28: 2 | Z28: 2 | AA28: 1 | AB28: 1 | AC28: 1 | AD28: 1 | AE28: 1 | AF28: 1 | AG28: 1 | AH28: 1 | AI28: 0 | AJ28: 0 | AK28: 0 | BP28: 1 | BQ28: showroom mobil Bekas | BR28: 1
A29: =ROWS($A$24:A29) -> 6 | B29: IoacDF | C29: PT. FFFFFF | D29: Samuel | G29: ='Home Int'!$O$15 -> Perorangan (Non Wiraswasta) | H29: ='Home Int'!$O$19 -> Pasangan Bekerja dan memiliki penghasilan | I29: 2 | J29: 2 | K29: 2 | L29: 2 | M29: 2 | N29: 2 | O29: 2 | P29: 0 | Q29: 0 | R29: 0 | S29: 0 | T29: 0 | U29: 0 | V29: 0 | W29: =ROWS($W$24:W29) -> 6 | X29: 2 | Y29: 2 | Z29: 1 | AA29: 1 | AB29: 1 | AC29: 1 | AD29: 1 | AE29: 1 | AF29: 1 | AG29: 1 | AH29: 1 | AI29: 0 | AJ29: 0 | AK29: 0 | BP29: 2 | BQ29: =CN22 -> Karyawan Internal | BR29: 21
A30: =ROWS($A$24:A30) -> 7 | B30: RaEXe5 | G30: ='Home Int'!$O$15 -> Perorangan (Non Wiraswasta) | H30: ='Home Int'!$O$19 -> Pasangan Bekerja dan memiliki penghasilan | I30: 0 | J30: 0 | K30: 0 | L30: 0 | M30: 0 | N30: 0 | O30: 0 | P30: 0 | Q30: 0 | R30: 0 | S30: 0 | T30: 0 | U30: 0 | V30: 0 | W30: =ROWS($W$24:W30) -> 7 | X30: 0 | Y30: 0 | Z30: 0 | AA30: 0 | AB30: 0 | AC30: 0 | AD30: 0 | AE30: 0 | AF30: 0 | AG30: 0 | AH30: 0 | AI30: 0 | AJ30: 0 | AK30: 0 | BP30: 3 | BQ30: =CU22 -> Karyawan Perbankan | BR30: 28
A31: =ROWS($A$24:A31) -> 8 | B31: eoSbgr | G31: ='Home Int'!$O$15 -> Perorangan (Non Wiraswasta) | H31: ='Home Int'!$O$19 -> Pasangan Bekerja dan memiliki penghasilan | I31: 0 | J31: 0 | K31: 0 | L31: 0 | M31: 0 | N31: 0 | O31: 0 | P31: 0 | Q31: 0 | R31: 0 | S31: 0 | T31: 0 | U31: 0 | V31: 0 | W31: =ROWS($W$24:W31) -> 8 | X31: 0 | Y31: 0 | Z31: 0 | AA31: 0 | AB31: 0 | AC31: 0 | AD31: 0 | AE31: 0 | AF31: 0 | AG31: 0 | AH31: 0 | AI31: 0 | AJ31: 0 | AK31: 0 | BP31: 4 | BQ31: =DD22 -> Wira Bisnis | BR31: 37
A32: =ROWS($A$24:A32) -> 9 | B32: DFh78J | G32: ='Home Int'!$O$15 -> Perorangan (Non Wiraswasta) | H32: ='Home Int'!$O$19 -> Pasangan Bekerja dan memiliki penghasilan | I32: 0 | J32: 0 | K32: 0 | L32: 0 | M32: 0 | N32: 0 | O32: 0 | P32: 0 | Q32: 0 | R32: 0 | S32: 0 | T32: 0 | U32: 0 | V32: 0 | W32: =ROWS($W$24:W32) -> 9 | X32: 0 | Y32: 0 | Z32: 0 | AA32: 0 | AB32: 0 | AC32: 0 | AD32: 0 | AE32: 0 | AF32: 0 | AG32: 0 | AH32: 0 | AI32: 0 | AJ32: 0 | AK32: 0 | BP32: 5 | BQ32: =DR22 -> Bank Mandiri | BR32: 51
A33: =ROWS($A$24:A33) -> 10 | B33: tNweyc | G33: ='Home Int'!$O$15 -> Perorangan (Non Wiraswasta) | H33: ='Home Int'!$O$19 -> Pasangan Bekerja dan memiliki penghasilan | I33: 0 | J33: 0 | K33: 0 | L33: 0 | M33: 0 | N33: 0 | O33: 0 | P33: 0 | Q33: 0 | R33: 0 | S33: 0 | T33: 0 | U33: 0 | V33: 0 | W33: =ROWS($W$24:W33) -> 10 | X33: 0 | Y33: 0 | Z33: 0 | AA33: 0 | AB33: 0 | AC33: 0 | AD33: 0 | AE33: 0 | AF33: 0 | AG33: 0 | AH33: 0 | AI33: 0 | AJ33: 0 | AK33: 0 | BP33: 6 | BQ33: =DX22 -> Karyawan Perbankan | BR33: 57
A34: =ROWS($A$24:A34) -> 11 | B34: wyLqfZ | G34: ='Home Int'!$O$15 -> Perorangan (Non Wiraswasta) | H34: ='Home Int'!$O$19 -> Pasangan Bekerja dan memiliki penghasilan | I34: 0 | J34: 0 | K34: 0 | L34: 0 | M34: 0 | N34: 0 | O34: 0 | P34: 0 | Q34: 0 | R34: 0 | S34: 0 | T34: 0 | U34: 0 | V34: 0 | W34: =ROWS($W$24:W34) -> 11 | X34: 0 | Y34: 0 | Z34: 0 | AA34: 0 | AB34: 0 | AC34: 0 | AD34: 0 | AE34: 0 | AF34: 0 | AG34: 0 | AH34: 0 | AI34: 0 | AJ34: 0 | AK34: 0 | BP34: 7 | BQ34: =ER22 -> Karyawan Authorized Dealer | BR34: 77
A35: =ROWS($A$24:A35) -> 12 | B35: xc4UBY | G35: ='Home Int'!$O$15 -> Perorangan (Non Wiraswasta) | H35: ='Home Int'!$O$19 -> Pasangan Bekerja dan memiliki penghasilan | I35: 0 | J35: 0 | K35: 0 | L35: 0 | M35: 0 | N35: 0 | O35: 0 | P35: 0 | Q35: 0 | R35: 0 | S35: 0 | T35: 0 | U35: 0 | V35: 0 | W35: =ROWS($W$24:W35) -> 12 | X35: 0 | Y35: 0 | Z35: 0 | AA35: 0 | AB35: 0 | AC35: 0 | AD35: 0 | AE35: 0 | AF35: 0 | AG35: 0 | AH35: 0 | AI35: 0 | AJ35: 0 | AK35: 0 | BP35: 8 | BQ35: =FO22 -> Karyawan Mandiri Cabang | BR35: 100
A36: =ROWS($A$24:A36) -> 13 | B36: PDnxj7 | G36: ='Home Int'!$O$15 -> Perorangan (Non Wiraswasta) | H36: ='Home Int'!$O$19 -> Pasangan Bekerja dan memiliki penghasilan | I36: 0 | J36: 0 | K36: 0 | L36: 0 | M36: 0 | N36: 0 | O36: 0 | P36: 0 | Q36: 0 | R36: 0 | S36: 0 | T36: 0 | U36: 0 | V36: 0 | W36: =ROWS($W$24:W36) -> 13 | X36: 0 | Y36: 0 | Z36: 0 | AA36: 0 | AB36: 0 | AC36: 0 | AD36: 0 | AE36: 0 | AF36: 0 | AG36: 0 | AH36: 0 | AI36: 0 | AJ36: 0 | AK36: 0 | BP36: 9 | BQ36: =FV22 -> Karyawan Multifinance | BR36: 107
A37: =ROWS($A$24:A37) -> 14 | B37: JlFCND | G37: ='Home Int'!$O$15 -> Perorangan (Non Wiraswasta) | H37: ='Home Int'!$O$19 -> Pasangan Bekerja dan memiliki penghasilan | I37: 0 | J37: 0 | K37: 0 | L37: 0 | M37: 0 | N37: 0 | O37: 0 | P37: 0 | Q37: 0 | R37: 0 | S37: 0 | T37: 0 | U37: 0 | V37: 0 | W37: =ROWS($W$24:W37) -> 14 | X37: 0 | Y37: 0 | Z37: 0 | AA37: 0 | AB37: 0 | AC37: 0 | AD37: 0 | AE37: 0 | AF37: 0 | AG37: 0 | AH37: 0 | AI37: 0 | AJ37: 0 | AK37: 0 | BP37: 10 | BQ37: =GQ22 -> Karyawan Asuransi | BR37: 128
A38: =ROWS($A$24:A38) -> 15 | B38: WFHcOz | G38: ='Home Int'!$O$15 -> Perorangan (Non Wiraswasta) | H38: ='Home Int'!$O$19 -> Pasangan Bekerja dan memiliki penghasilan | I38: 0 | J38: 0 | K38: 0 | L38: 0 | M38: 0 | N38: 0 | O38: 0 | P38: 0 | Q38: 0 | R38: 0 | S38: 0 | T38: 0 | U38: 0 | V38: 0 | W38: =ROWS($W$24:W38) -> 15 | X38: 0 | Y38: 0 | Z38: 0 | AA38: 0 | AB38: 0 | AC38: 0 | AD38: 0 | AE38: 0 | AF38: 0 | AG38: 0 | AH38: 0 | AI38: 0 | AJ38: 0 | AK38: 0 | BP38: 11 | BQ38: =HM22 -> Area Kyai Tapa | BR38: 150
A39: =ROWS($A$24:A39) -> 16 | B39: IuZw6E | G39: ='Home Int'!$O$15 -> Perorangan (Non Wiraswasta) | H39: ='Home Int'!$O$19 -> Pasangan Bekerja dan memiliki penghasilan | I39: 0 | J39: 0 | K39: 0 | L39: 0 | M39: 0 | N39: 0 | O39: 0 | P39: 0 | Q39: 0 | R39: 0 | S39: 0 | T39: 0 | U39: 0 | V39: 0 | W39: =ROWS($W$24:W39) -> 16 | X39: 0 | Y39: 0 | Z39: 0 | AA39: 0 | AB39: 0 | AC39: 0 | AD39: 0 | AE39: 0 | AF39: 0 | AG39: 0 | AH39: 0 | AI39: 0 | AJ39: 0 | AK39: 0 | BP39: 12 | BQ39: =II22 -> Area Daan Mogot | BR39: 172
A40: =ROWS($A$24:A40) -> 17 | B40: hPqnNo | G40: ='Home Int'!$O$15 -> Perorangan (Non Wiraswasta) | H40: ='Home Int'!$O$19 -> Pasangan Bekerja dan memiliki penghasilan | I40: 0 | J40: 0 | K40: 0 | L40: 0 | M40: 0 | N40: 0 | O40: 0 | P40: 0 | Q40: 0 | R40: 0 | S40: 0 | T40: 0 | U40: 0 | V40: 0 | W40: =ROWS($W$24:W40) -> 17 | X40: 0 | Y40: 0 | Z40: 0 | AA40: 0 | AB40: 0 | AC40: 0 | AD40: 0 | AE40: 0 | AF40: 0 | AG40: 0 | AH40: 0 | AI40: 0 | AJ40: 0 | AK40: 0 | BP40: 13 | BQ40: =JE22 -> Area Green Ville | BR40: 194
A41: =ROWS($A$24:A41) -> 18 | B41: W9IJVz | G41: ='Home Int'!$O$15 -> Perorangan (Non Wiraswasta) | H41: ='Home Int'!$O$19 -> Pasangan Bekerja dan memiliki penghasilan | I41: 0 | J41: 0 | K41: 0 | L41: 0 | M41: 0 | N41: 0 | O41: 0 | P41: 0 | Q41: 0 | R41: 0 | S41: 0 | T41: 0 | U41: 0 | V41: 0 | W41: =ROWS($W$24:W41) -> 18 | X41: 0 | Y41: 0 | Z41: 0 | AA41: 0 | AB41: 0 | AC41: 0 | AD41: 0 | AE41: 0 | AF41: 0 | AG41: 0 | AH41: 0 | AI41: 0 | AJ41: 0 | AK41: 0 | BP41: 14 | BQ41: =JY22 -> Kosong | BR41: 214
A42: =ROWS($A$24:A42) -> 19 | B42: 4npsYT | G42: ='Home Int'!$O$15 -> Perorangan (Non Wiraswasta) | H42: ='Home Int'!$O$19 -> Pasangan Bekerja dan memiliki penghasilan | I42: 0 | J42: 0 | K42: 0 | L42: 0 | M42: 0 | N42: 0 | O42: 0 | P42: 0 | Q42: 0 | R42: 0 | S42: 0 | T42: 0 | U42: 0 | V42: 0 | W42: =ROWS($W$24:W42) -> 19 | X42: 0 | Y42: 0 | Z42: 0 | AA42: 0 | AB42: 0 | AC42: 0 | AD42: 0 | AE42: 0 | AF42: 0 | AG42: 0 | AH42: 0 | AI42: 0 | AJ42: 0 | AK42: 0 | BP42: 15 | BQ42: =KE22 -> Graha Sultan | BR42: 220
A43: =ROWS($A$24:A43) -> 20 | B43: qRnlQg | G43: ='Home Int'!$O$15 -> Perorangan (Non Wiraswasta) | H43: ='Home Int'!$O$19 -> Pasangan Bekerja dan memiliki penghasilan | I43: 0 | J43: 0 | K43: 0 | L43: 0 | M43: 0 | N43: 0 | O43: 0 | P43: 0 | Q43: 0 | R43: 0 | S43: 0 | T43: 0 | U43: 0 | V43: 0 | W43: =ROWS($W$24:W43) -> 20 | X43: 0 | Y43: 0 | Z43: 0 | AA43: 0 | AB43: 0 | AC43: 0 | AD43: 0 | AE43: 0 | AF43: 0 | AG43: 0 | AH43: 0 | AI43: 0 | AJ43: 0 | AK43: 0
A44: =ROWS($A$24:A44) -> 21 | B44: ixa71n | G44: ='Home Int'!$O$15 -> Perorangan (Non Wiraswasta) | H44: ='Home Int'!$O$19 -> Pasangan Bekerja dan memiliki penghasilan | I44: 0 | J44: 0 | K44: 0 | L44: 0 | M44: 0 | N44: 0 | O44: 0 | P44: 0 | Q44: 0 | R44: 0 | S44: 0 | T44: 0 | U44: 0 | V44: 0 | W44: =ROWS($W$24:W44) -> 21 | X44: 0 | Y44: 0 | Z44: 0 | AA44: 0 | AB44: 0 | AC44: 0 | AD44: 0 | AE44: 0 | AF44: 0 | AG44: 0 | AH44: 0 | AI44: 0 | AJ44: 0 | AK44: 0
A45: =ROWS($A$24:A45) -> 22 | B45: oa7V9h | G45: ='Home Int'!$O$15 -> Perorangan (Non Wiraswasta) | H45: ='Home Int'!$O$19 -> Pasangan Bekerja dan memiliki penghasilan | I45: 0 | J45: 0 | K45: 0 | L45: 0 | M45: 0 | N45: 0 | O45: 0 | P45: 0 | Q45: 0 | R45: 0 | S45: 0 | T45: 0 | U45: 0 | V45: 0 | W45: =ROWS($W$24:W45) -> 22 | X45: 0 | Y45: 0 | Z45: 0 | AA45: 0 | AB45: 0 | AC45: 0 | AD45: 0 | AE45: 0 | AF45: 0 | AG45: 0 | AH45: 0 | AI45: 0 | AJ45: 0 | AK45: 0
A46: =ROWS($A$24:A46) -> 23 | B46: UdsQh3 | G46: ='Home Int'!$O$15 -> Perorangan (Non Wiraswasta) | H46: ='Home Int'!$O$19 -> Pasangan Bekerja dan memiliki penghasilan | I46: 0 | J46: 0 | K46: 0 | L46: 0 | M46: 0 | N46: 0 | O46: 0 | P46: 0 | Q46: 0 | R46: 0 | S46: 0 | T46: 0 | U46: 0 | V46: 0 | W46: =ROWS($W$24:W46) -> 23 | X46: 0 | Y46: 0 | Z46: 0 | AA46: 0 | AB46: 0 | AC46: 0 | AD46: 0 | AE46: 0 | AF46: 0 | AG46: 0 | AH46: 0 | AI46: 0 | AJ46: 0 | AK46: 0
A47: =ROWS($A$24:A47) -> 24 | B47: ryW54f | G47: ='Home Int'!$O$15 -> Perorangan (Non Wiraswasta) | H47: ='Home Int'!$O$19 -> Pasangan Bekerja dan memiliki penghasilan | I47: 0 | J47: 0 | K47: 0 | L47: 0 | M47: 0 | N47: 0 | O47: 0 | P47: 0 | Q47: 0 | R47: 0 | S47: 0 | T47: 0 | U47: 0 | V47: 0 | W47: =ROWS($W$24:W47) -> 24 | X47: 0 | Y47: 0 | Z47: 0 | AA47: 0 | AB47: 0 | AC47: 0 | AD47: 0 | AE47: 0 | AF47: 0 | AG47: 0 | AH47: 0 | AI47: 0 | AJ47: 0 | AK47: 0
A48: =ROWS($A$24:A48) -> 25 | B48: CU1BjL | G48: ='Home Int'!$O$15 -> Perorangan (Non Wiraswasta) | H48: ='Home Int'!$O$19 -> Pasangan Bekerja dan memiliki penghasilan | I48: 0 | J48: 0 | K48: 0 | L48: 0 | M48: 0 | N48: 0 | O48: 0 | P48: 0 | Q48: 0 | R48: 0 | S48: 0 | T48: 0 | U48: 0 | V48: 0 | W48: =ROWS($W$24:W48) -> 25 | X48: 0 | Y48: 0 | Z48: 0 | AA48: 0 | AB48: 0 | AC48: 0 | AD48: 0 | AE48: 0 | AF48: 0 | AG48: 0 | AH48: 0 | AI48: 0 | AJ48: 0 | AK48: 0
A49: =ROWS($A$24:A49) -> 26 | B49: t2Bx7d | G49: ='Home Int'!$O$15 -> Perorangan (Non Wiraswasta) | H49: ='Home Int'!$O$19 -> Pasangan Bekerja dan memiliki penghasilan | I49: 0 | J49: 0 | K49: 0 | L49: 0 | M49: 0 | N49: 0 | O49: 0 | P49: 0 | Q49: 0 | R49: 0 | S49: 0 | T49: 0 | U49: 0 | V49: 0 | W49: =ROWS($W$24:W49) -> 26 | X49: 0 | Y49: 0 | Z49: 0 | AA49: 0 | AB49: 0 | AC49: 0 | AD49: 0 | AE49: 0 | AF49: 0 | AG49: 0 | AH49: 0 | AI49: 0 | AJ49: 0 | AK49: 0
A50: =ROWS($A$24:A50) -> 27 | B50: QbkEH6 | G50: ='Home Int'!$O$15 -> Perorangan (Non Wiraswasta) | H50: ='Home Int'!$O$19 -> Pasangan Bekerja dan memiliki penghasilan | I50: 0 | J50: 0 | K50: 0 | L50: 0 | M50: 0 | N50: 0 | O50: 0 | P50: 0 | Q50: 0 | R50: 0 | S50: 0 | T50: 0 | U50: 0 | V50: 0 | W50: =ROWS($W$24:W50) -> 27 | X50: 0 | Y50: 0 | Z50: 0 | AA50: 0 | AB50: 0 | AC50: 0 | AD50: 0 | AE50: 0 | AF50: 0 | AG50: 0 | AH50: 0 | AI50: 0 | AJ50: 0 | AK50: 0
A51: =ROWS($A$24:A51) -> 28 | B51: 8af2PO | G51: ='Home Int'!$O$15 -> Perorangan (Non Wiraswasta) | H51: ='Home Int'!$O$19 -> Pasangan Bekerja dan memiliki penghasilan | I51: 0 | J51: 0 | K51: 0 | L51: 0 | M51: 0 | N51: 0 | O51: 0 | P51: 0 | Q51: 0 | R51: 0 | S51: 0 | T51: 0 | U51: 0 | V51: 0 | W51: =ROWS($W$24:W51) -> 28 | X51: 0 | Y51: 0 | Z51: 0 | AA51: 0 | AB51: 0 | AC51: 0 | AD51: 0 | AE51: 0 | AF51: 0 | AG51: 0 | AH51: 0 | AI51: 0 | AJ51: 0 | AK51: 0
A52: =ROWS($A$24:A52) -> 29 | B52: neRwxj | G52: ='Home Int'!$O$15 -> Perorangan (Non Wiraswasta) | H52: ='Home Int'!$O$19 -> Pasangan Bekerja dan memiliki penghasilan | I52: 0 | J52: 0 | K52: 0 | L52: 0 | M52: 0 | N52: 0 | O52: 0 | P52: 0 | Q52: 0 | R52: 0 | S52: 0 | T52: 0 | U52: 0 | V52: 0 | W52: =ROWS($W$24:W52) -> 29 | X52: 0 | Y52: 0 | Z52: 0 | AA52: 0 | AB52: 0 | AC52: 0 | AD52: 0 | AE52: 0 | AF52: 0 | AG52: 0 | AH52: 0 | AI52: 0 | AJ52: 0 | AK52: 0
A53: =ROWS($A$24:A53) -> 30 | B53: 5YXpxR | G53: ='Home Int'!$O$15 -> Perorangan (Non Wiraswasta) | H53: ='Home Int'!$O$19 -> Pasangan Bekerja dan memiliki penghasilan | I53: 0 | J53: 0 | K53: 0 | L53: 0 | M53: 0 | N53: 0 | O53: 0 | P53: 0 | Q53: 0 | R53: 0 | S53: 0 | T53: 0 | U53: 0 | V53: 0 | W53: =ROWS($W$24:W53) -> 30 | X53: 0 | Y53: 0 | Z53: 0 | AA53: 0 | AB53: 0 | AC53: 0 | AD53: 0 | AE53: 0 | AF53: 0 | AG53: 0 | AH53: 0 | AI53: 0 | AJ53: 0 | AK53: 0
A54: =ROWS($A$24:A54) -> 31 | B54: mRTJDj | G54: ='Home Int'!$O$15 -> Perorangan (Non Wiraswasta) | H54: ='Home Int'!$O$19 -> Pasangan Bekerja dan memiliki penghasilan | I54: 0 | J54: 0 | K54: 0 | L54: 0 | M54: 0 | N54: 0 | O54: 0 | P54: 0 | Q54: 0 | R54: 0 | S54: 0 | T54: 0 | U54: 0 | V54: 0 | W54: =ROWS($W$24:W54) -> 31 | X54: 0 | Y54: 0 | Z54: 0 | AA54: 0 | AB54: 0 | AC54: 0 | AD54: 0 | AE54: 0 | AF54: 0 | AG54: 0 | AH54: 0 | AI54: 0 | AJ54: 0 | AK54: 0
... A323: =ROWS($A$24:A323) -> 300 | B323: s5ziKc | G323: ='Home Int'!$O$15 -> Perorangan (Non Wiraswasta) | H323: ='Home Int'!$O$19 -> Pasangan Bekerja dan memiliki penghasilan | I323: 0 | J323: 0 | K323: 0 | L323: 0 | M323: 0 | N323: 0 | O323: 0 | P323: 0 | Q323: 0 | R323: 0 | S323: 0 | T323: 0 | U323: 0 | V323: 0 | W323: =ROWS($W$24:W323) -> 300 | X323: 0 | Y323: 0 | Z323: 0 | AA323: 0 | AB323: 0 | AC323: 0 | AD323: 0 | AE323: 0 | AF323: 0 | AG323: 0 | AH323: 0 | AI323: 0 | AJ323: 0 | AK323: 0

Sheet Asr Int
C2: Wilayah 2
B3: OTR | C3: BATAS ATAS | G3: BATAS BAWAH | L3: LOADING ASURANSI
C4: Passenger | E4: Commercial | G4: Passenger | I4: Commercial
C5: Comprehensive | D5: TLO | E5: Comprehensive | F5: TLO | G5: Comprehensive | H5: TLO | I5: Comprehensive | J5: TLO
B6: 0-125 | C6: 0.0359 | D6: 0.0078 | E6: 0.0369 | F6: 0.0085 | G6: 0.0326 | H6: 0.0065 | I6: 0.0336 | J6: 0.0072 | L6: 2026 | M6: 0 | N6: 0 | O6: Comprehensive
B7: >125-200 | C7: 0.0272 | D7: 0.0053 | E7: 0.0282 | F7: 0.0057 | G7: 0.0247 | H7: 0.0044 | I7: 0.0257 | J7: 0.0048 | L7: =L6-1 -> 2025 | M7: 1 | N7: 0 | O7: Comprehensive
B8: >200-400 | C8: 0.0229 | D8: 0.0042 | E8: 0.0239 | F8: 0.0045 | G8: 0.0208 | H8: 0.0038 | I8: 0.0218 | J8: 0.0041 | L8: =L7-1 -> 2024 | M8: 2 | N8: 0 | O8: Comprehensive
B9: >400-800 | C9: 0.0132 | D9: 0.003 | E9: 0.0142 | F9: 0.0033 | G9: 0.012 | H9: 0.0025 | I9: 0.013 | J9: 0.0028 | L9: =L8-1 -> 2023 | M9: 3 | N9: 0 | O9: Comprehensive
B10: >800 | C10: 0.0116 | D10: 0.0024 | E10: 0.0126 | F10: 0.0026 | G10: 0.0105 | H10: 0.002 | I10: 0.0115 | J10: 0.0022 | L10: =L9-1 -> 2022 | M10: 4 | N10: 0 | O10: Comprehensive
L11: =L10-1 -> 2021 | M11: 5 | N11: 0 | O11: Comprehensive
B12: ='Home Int'!$I$13 -> Passenger | C12: BATAS ATAS | E12: BATAS BAWAH | L12: =L11-1 -> 2020 | M12: 6 | N12: 0.05 | O12: Comprehensive Loading
C13: Comprehensive | D13: TLO | E13: Comprehensive | F13: TLO | L13: =L12-1 -> 2019 | M13: 7 | N13: 0.1 | O13: Comprehensive Loading
B14: 0-125 | C14: =IF($B$12="Passenger",C6,E6) -> 0.0359 | D14: =IF($B$12="Passenger",D6,F6) -> 0.0078 | E14: =IF($B$12="Passenger",G6,I6) -> 0.0326 | F14: =IF($B$12="Passenger",H6,J6) -> 0.0065 | L14: =L13-1 -> 2018 | M14: 8 | N14: 0.15 | O14: Comprehensive Loading
B15: >125-200 | C15: =IF($B$12="Passenger",C7,E7) -> 0.0272 | D15: =IF($B$12="Passenger",D7,F7) -> 0.0053 | E15: =IF($B$12="Passenger",G7,I7) -> 0.0247 | F15: =IF($B$12="Passenger",H7,J7) -> 0.0044 | L15: =L14-1 -> 2017 | M15: 9 | N15: 0.2 | O15: Comprehensive Loading
B16: >200-400 | C16: =IF($B$12="Passenger",C8,E8) -> 0.0229 | D16: =IF($B$12="Passenger",D8,F8) -> 0.0042 | E16: =IF($B$12="Passenger",G8,I8) -> 0.0208 | F16: =IF($B$12="Passenger",H8,J8) -> 0.0038 | L16: =L15-1 -> 2016 | M16: 10 | N16: 0.25 | O16: Comprehensive Loading
B17: >400-800 | C17: =IF($B$12="Passenger",C9,E9) -> 0.0132 | D17: =IF($B$12="Passenger",D9,F9) -> 0.003 | E17: =IF($B$12="Passenger",G9,I9) -> 0.012 | F17: =IF($B$12="Passenger",H9,J9) -> 0.0025 | L17: =L16-1 -> 2015 | M17: 11 | N17: 0
B18: >800 | C18: =IF($B$12="Passenger",C10,E10) -> 0.0116 | D18: =IF($B$12="Passenger",D10,F10) -> 0.0024 | E18: =IF($B$12="Passenger",G10,I10) -> 0.0105 | F18: =IF($B$12="Passenger",H10,J10) -> 0.002 | L18: =L17-1 -> 2014 | M18: 12 | N18: 0
L19: =L18-1 -> 2013 | M19: 13 | N19: 0
B20: =B12 -> Passenger | C20: ='Home Int'!$K$29 -> BATAS BAWAH | L20: =L19-1 -> 2012 | M20: 14 | N20: 0
C21: Compre | D21: TLO
B22: 0-125 | C22: =IF($C$20="BATAS BAWAH",E14,C14) -> 0.0326 | D22: =IF($C$20="BATAS BAWAH",F14,D14) -> 0.0065
B23: >125-200 | C23: =IF($C$20="BATAS BAWAH",E15,C15) -> 0.0247 | D23: =IF($C$20="BATAS BAWAH",F15,D15) -> 0.0044
B24: >200-400 | C24: =IF($C$20="BATAS BAWAH",E16,C16) -> 0.0208 | D24: =IF($C$20="BATAS BAWAH",F16,D16) -> 0.0038
B25: >400-800 | C25: =IF($C$20="BATAS BAWAH",E17,C17) -> 0.012 | D25: =IF($C$20="BATAS BAWAH",F17,D17) -> 0.0025
B26: >800 | C26: =IF($C$20="BATAS BAWAH",E18,C18) -> 0.0105 | D26: =IF($C$20="BATAS BAWAH",F18,D18) -> 0.002
B29: TENOR | C29: ACP BOTTOM | D29: UPPING | E29: ACP JUAL | H29: TJH DANA TUNAI
H30: TJH NON KOMERSIAL | M30: TJH RUPIAH
B31: 12 | C31: =$D$70 -> 0.0065 | D31: =#REF! -> #REF! | E31: =C31+(C31*D31) -> #REF!
B32: 24 | C32: =$E$70 -> 0.013 | D32: =#REF! -> #REF! | E32: =C32+(C32*D32) -> #REF! | G32: 1 | H32: =IF('DT Int'!$D$33>25000000,25000000,'DT Int'!$D$33) -> 0 | I32: =IF('DT Int'!$D$33>50000000,25000000,'DT Int'!$D$33) -> 0 | J32: =IF('DT Int'!$D$33>50000000,25000000,'DT Int'!$D$33-H32-I32) -> 0 | K32: ='DT Int'!$D$33-H32-I32-J32 -> 0 | M32: =(H32*0.01)+(I32*0.005)+(J32*0.0025)+(K32*0.0015) -> 0
B33: 36 | C33: =$F$70 -> 0.01989 | D33: =#REF! -> #REF! | E33: =C33+(C33*D33) -> #REF! | G33: 2 | H33: =IF('DT Int'!$D$33>25000000,25000000,'DT Int'!$D$33) -> 0 | I33: =IF('DT Int'!$D$33>50000000,25000000,'DT Int'!$D$33) -> 0 | J33: =IF('DT Int'!$D$33>50000000,25000000,'DT Int'!$D$33-H33-I33) -> 0 | K33: ='DT Int'!$D$33-H33-I33-J33 -> 0 | M33: =(H33*0.01)+(I33*0.005)+(J33*0.0025)+(K33*0.0015) -> 0
B34: 48 | C34: =$G$70 -> 0.02912 | D34: =#REF! -> #REF! | E34: =C34+(C34*D34) -> #REF! | G34: 3 | H34: =IF('DT Int'!$D$33>25000000,25000000,'DT Int'!$D$33) -> 0 | I34: =IF('DT Int'!$D$33>50000000,25000000,'DT Int'!$D$33) -> 0 | J34: =IF('DT Int'!$D$33>50000000,25000000,'DT Int'!$D$33-H34-I34) -> 0 | K34: ='DT Int'!$D$33-H34-I34-J34 -> 0 | M34: =(H34*0.01)+(I34*0.005)+(J34*0.0025)+(K34*0.0015) -> 0
G35: 4 | H35: =IF('DT Int'!$D$33>25000000,25000000,'DT Int'!$D$33) -> 0 | I35: =IF('DT Int'!$D$33>50000000,25000000,'DT Int'!$D$33) -> 0 | J35: =IF('DT Int'!$D$33>50000000,25000000,'DT Int'!$D$33-H35-I35) -> 0 | K35: ='DT Int'!$D$33-H35-I35-J35 -> 0 | M35: =(H35*0.01)+(I35*0.005)+(J35*0.0025)+(K35*0.0015) -> 0 | X35: =IF(#REF!="COMPRE",1,0)+#REF! -> #REF! | Y35: =IF(#REF!="TLO",1,0)+#REF! -> #REF!
G36: 5 | H36: =IF('DT Int'!$D$33>25000000,25000000,'DT Int'!$D$33) -> 0 | I36: =IF('DT Int'!$D$33>50000000,25000000,'DT Int'!$D$33) -> 0 | J36: =IF('DT Int'!$D$33>50000000,25000000,'DT Int'!$D$33-H36-I36) -> 0 | K36: ='DT Int'!$D$33-H36-I36-J36 -> 0 | M36: =(H36*0.01)+(I36*0.005)+(J36*0.0025)+(K36*0.0015) -> 0
C37: RATE ACP BARU 2025 | H37: TJH PEMBIAYAAN USED CAR
C38: 1 | D38: 2 | E38: 3 | F38: 4 | H38: TJH NON KOMERSIAL | M38: TJH RUPIAH
C39: 18-35th | D39: 36-45th | E39: 46-50th | F39: 51-60th
B40: 1 | C40: 0.005 | D40: 0.005 | E40: 0.005 | F40: 0.005 | G40: 1 | H40: =IF('UC Int'!$D$33>25000000,25000000,'UC Int'!$D$33) -> 0 | I40: =IF('UC Int'!$D$33>50000000,25000000,'UC Int'!$D$33-H40) -> 0 | J40: =IF('UC Int'!$D$33>50000000,25000000,'UC Int'!$D$33-H40-I40) -> 0 | K40: ='UC Int'!$D$33-H40-I40-J40 -> 0 | M40: =(H40*0.01)+(I40*0.005)+(J40*0.0025)+(K40*0.0015) -> 0
B41: =B40+1 -> 2 | C41: 0.005 | D41: 0.005 | E41: 0.005 | F41: 0.005 | G41: 2 | H41: =IF('UC Int'!$D$33>25000000,25000000,'UC Int'!$D$33) -> 0 | I41: =IF('UC Int'!$D$33>50000000,25000000,'UC Int'!$D$33-H41) -> 0 | J41: =IF('UC Int'!$D$33>50000000,25000000,'UC Int'!$D$33-H41-I41) -> 0 | K41: ='UC Int'!$D$33-H41-I41-J41 -> 0 | M41: =(H41*0.01)+(I41*0.005)+(J41*0.0025)+(K41*0.0015) -> 0
B42: =B41+1 -> 3 | C42: 0.0053 | D42: 0.0053 | E42: 0.0053 | F42: 0.0053 | G42: 3 | H42: =IF('UC Int'!$D$33>25000000,25000000,'UC Int'!$D$33) -> 0 | I42: =IF('UC Int'!$D$33>50000000,25000000,'UC Int'!$D$33-H42) -> 0 | J42: =IF('UC Int'!$D$33>50000000,25000000,'UC Int'!$D$33-H42-I42) -> 0 | K42: ='UC Int'!$D$33-H42-I42-J42 -> 0 | M42: =(H42*0.01)+(I42*0.005)+(J42*0.0025)+(K42*0.0015) -> 0
B43: =B42+1 -> 4 | C43: 0.0071 | D43: 0.0071 | E43: 0.0071 | F43: 0.0071 | G43: 4 | H43: =IF('UC Int'!$D$33>25000000,25000000,'UC Int'!$D$33) -> 0 | I43: =IF('UC Int'!$D$33>50000000,25000000,'UC Int'!$D$33-H43) -> 0 | J43: =IF('UC Int'!$D$33>50000000,25000000,'UC Int'!$D$33-H43-I43) -> 0 | K43: ='UC Int'!$D$33-H43-I43-J43 -> 0 | M43: =(H43*0.01)+(I43*0.005)+(J43*0.0025)+(K43*0.0015) -> 0
B44: =B43+1 -> 5 | C44: 0.0064 | D44: 0.0064 | E44: 0.0064 | F44: 0.0064 | G44: 5 | H44: =IF('UC Int'!$D$33>25000000,25000000,'UC Int'!$D$33) -> 0 | I44: =IF('UC Int'!$D$33>50000000,25000000,'UC Int'!$D$33-H44) -> 0 | J44: =IF('UC Int'!$D$33>50000000,25000000,'UC Int'!$D$33-H44-I44) -> 0 | K44: ='UC Int'!$D$33-H44-I44-J44 -> 0 | M44: =(H44*0.01)+(I44*0.005)+(J44*0.0025)+(K44*0.0015) -> 0
B45: =B44+1 -> 6 | C45: 0.0053 | D45: 0.0053 | E45: 0.0053 | F45: 0.0053
H46: TJH | I46: Pengemudi | J46: Penumpang | K46: Jml Penumpang
H47: 0 | I47: 0 | J47: 0 | K47: 0
H48: 5000000 | I48: 10000000 | J48: 10000000 | K48: 4
H49: 10000000
H50: 15000000
H51: 20000000
H52: 25000000
H53: 30000000
H54: 35000000
H55: 40000000
H56: 45000000
H57: 50000000
C60: 18-35 tahun | D60: 36-45 tahun | E60: 46-50 tahun | F60: 51-60 tahun
B61: 1 | C61: 0.0044 | D61: 0.005 | E61: 0.0062 | F61: 0.007
B62: 2 | C62: 0.0086 | D62: 0.01 | E62: 0.0124 | F62: 0.015
B63: 3 | C63: 0.0131 | D63: 0.0153 | E63: 0.0189 | F63: 0.023
B64: 4 | C64: 0.0194 | D64: 0.0224 | E64: 0.0255 | F64: 0.031
B65: 5 | C65: 0.0249 | D65: 0.0288 | E65: 0.0322 | F65: 0.04
B66: 6 | C66: 0.0307 | D66: 0.0341 | E66: 0.0392 | F66: 0.05
C67: 0.0055
B68: Dana Tunai | J68: Used Car
B69: RATE ACP | D69: 1 | E69: 2 | F69: 3 | G69: 4 | H69: 5 | J69: RATE ACP | L69: 1 | M69: 2 | N69: 3 | O69: 4 | P69: 5
B70: ='DT Int'!$S$4 -> 0.3 | C70: 18-35 tahun | D70: =$D$61+($D$61*B70) -> 0.0065 | E70: =$D$62+($D$62*B70) -> 0.013 | F70: =$D$63+($D$63*B70) -> 0.01989 | G70: =$D$64+($D$64*B70) -> 0.02912 | H70: =$D$65+($D$65*B70) -> 0.03744 | J70: ='UC Int'!$S$4 -> 0.3 | K70: 18-35 tahun | L70: =$D$61+($D$61*J70) -> 0.0065 | M70: =$D$62+($D$62*J70) -> 0.013 | N70: =$D$63+($D$63*J70) -> 0.01989 | O70: =$D$64+($D$64*J70) -> 0.02912 | P70: =$D$65+($D$65*J70) -> 0.03744
B71: ='DT Int'!$S$4 -> 0.3 | C71: 36-45 tahun | D71: =$D$61+($D$61*B71) -> 0.0065 | E71: =$D$62+($D$62*B71) -> 0.013 | F71: =$D$63+($D$63*B71) -> 0.01989 | G71: =$D$64+($D$64*B71) -> 0.02912 | H71: =$D$65+($D$65*B71) -> 0.03744 | J71: ='UC Int'!$S$4 -> 0.3 | K71: 36-45 tahun | L71: =$D$61+($D$61*J71) -> 0.0065 | M71: =$D$62+($D$62*J71) -> 0.013 | N71: =$D$63+($D$63*J71) -> 0.01989 | O71: =$D$64+($D$64*J71) -> 0.02912 | P71: =$D$65+($D$65*J71) -> 0.03744
